Workbook

Sheet 使い方
A1: このファイルの使い方についてご説明させて頂きます。
A3: ① ファイル形式の変更
A5: ★ | B5: ファイルサイズを小さくする為 「Excel バイナリ ブック」という形式で保存していますが、このまま入力するとデータが正常に保存できない恐れがあるため
B6: 次の手順でファイル形式の変更をお願いいたします。
B7: ・「Excel バイナリ ブック」から「Excel ブック」への変更
C8: 『Excel版専用伝票ファイル』を開きます。（このファイルのことです）
C16: ファイルメニューから「名前を付けて保存」を選択して、ファイルの種類を
C17: 「Excelブック（*.xlsx）」で保存します。
C18: （*.xlsxが選択肢に無い場合は、*.xlsを選択します）
C26: ※請求データの入力作業は、この「Excelブック（*.xlsx もしくは *.xls）」の状態で行ってください。
A29: ② 請求データの入力
A30: ★ | B30: 入力は 請求データ入力 シートで行います。
B31: ・請求基本情報（住所、会社名、取引先ｺｰﾄﾞ、電話番号、課税事業者の方は適格請求書発行事業者登録番号)
B32: ・請求年月を「西暦4桁+月2桁」の数字6桁にて入力
C33: ↓
B34: 入力した内容が「合計請求書」・「個別」シートに反映されますので、入力内容に応じて印刷してください。
A35: ★ | B35: 入力1行につき、1伝票№となります。
B36: 同一工事への請求につきましては1明細1枚とせず、できる限り1枚で作成し、御社様式の明細書を別途添付ください。
A38: 【印刷について】
A40: ★ | B40: 入力完了後「合計請求書」シートと「個別000-000」シートを印刷します。
A42: ★ | B42: 「合計請求書」シート → 印刷用紙に指定はありません。A4にて印刷し、請求印を押印の上ご提出ください。
A44: ★ | B44: 「個別000-000」シート → 弊社指定の用紙に印刷の上、請求印を押印しご提出ください。
E45: 弊社指定用紙：ヒサゴのマルチプリンタ帳票 品番：FSC2013 A4 カラー 3面6穴
F46: ※Amazon、ASKUL等で購入可能です。
A47: ★ | B47: 藤田建装の専用伝票（専用請求書）と同様に、伝票№ひとつにつき、３枚一組となっています。
C48: ② 納品書（原価計算書）
C49: ③ 請求明細書 | G49: この３枚一組を1伝票としてご提出をお願い致します。
C50: ④ 管理伝票 | G50: （専用伝票の①が御社控えとなっている為、Excelでは印刷を省略しています）
A52: ★ | B52: ”１シート 10伝票” になっています。請求データ入力シートに入力した行数分が自動的に印刷範囲に指定されますので
B53: 印刷時に特にページ数を指定する必要はありません。
C54: ↓
B55: ＜複数シートを同時に印刷したい場合＞
B56: シートを複数選択すると、印刷したい部分を一度に印刷できます。
A59: 【お問い合わせの際は】
A61: ★ | B61: ご請求書提出後に藤田建装へお問い合わせを頂く場合は、伝票№をお伝え頂けるとスムーズです。
B62: T№ と書かれている部分が伝票№になります。
A64: 【請求書の再発行について】
B65: 一度藤田建装宛にご提出いただいた請求書を再発行する場合、請求書Noはそのままでも構いませんが、
B66: 印刷した専用伝票の備考欄に
C67: ・「再発行」の文字
C68: ・再発行理由(簡単にで構いません。)
B69: を記載していただきますようお願いいたします。(②～④迄)
A71: 【請求データ入力 のサンプルです】 | G71: 赤字は補足です。
C72: お手数ですが、初めに請求年月を 西暦4桁＋月2桁 で入力してください。（例：2023年1月の場合 → 202301）
C73: 請求年月 | F73: 202304 | H73: 取引先コード
E74: ↑※伝票№の採番に必要な情報となっています。 | I74: ↑※伝票に反映していますので消さないでください。 | Q74: 藤田建装へお問い合わせの際はこちらの番号をお知らせください↓
A75: ｼｰﾄ№ | B75: 連番 | C75: 完成納品年月日 | F75: 御社ご担当者名 | G75: 藤田建装担当者 | H75: 工事ｺｰﾄﾞ | I75: 工事名 | J75: 内容 | K75: 数量 | L75: 単価 単位 | M75: 単価 | N75: 金額 （税抜） | O75: 消費税 | P75: 金額 （税込） | Q75: T№ （伝票№）
C76: 西暦年 | D76: 月 | E76: 日 | H76: (4桁-4桁-2桁)
A77: 101-110 | B77: 101 | C77: 2023 | D77: 4 | E77: 1 | F77: 取引 太郎様 | G77: 藤田 太郎様 | H77: 9999-9999-99 | I77: 全社（出向社員人件費） | J77: 10月度業務委託費 | K77: 1 | L77: 式 | M77: 1375000 | N77: 1375000 | O77: =IF(N77="","",ROUNDDOWN(N77*0.1,0)) -> 137500 | P77: =+N77+O77 -> 1512500 | Q77: 2304101
B78: 102 | J78: ↑伝票№ひとつにつき、ひとつの内容（項目）としてください | Q78: 2304102
B79: 103 | Q79: 2304103
B80: 104 | Q80: 2304104
B81: 105 | Q81: 2304105
B82: 106 | Q82: 2304106
B83: 107 | Q83: 2304107
B84: 108 | Q84: 2304108
B85: 109 | Q85: 2304109
B86: 110 | Q86: 2304110

Sheet 請求データ入力
B1: 【請求基本情報】 | F1: 「※」の箇所は必ず入力ください。
C2: ※住所 | F2: 〒110-0012 東京都台東区竜泉3-40-4 | J2: ※取引先コード | K2: 72130
J4: ※電話番号 | K4: 090-4609-2757
C6: ※会社名 | F6: 有限会社木村左官工業 | J6: 登録番号
J7: ↑適格請求書発行事業者登録番号をお持ちの場合は必ず入力ください。
C9: お手数ですが、初めに請求年月を 西暦4桁＋月2桁 で入力してください。（例：2023年5月の場合 → 202305）
C10: ※請求年月 | F10: 202602 | N10: 非課税事業者の方はこちらの税率を「0％」にしてください。→ | O10: ※消費税率
F11: ↑伝票№の採番に必要な情報の為必ずご入力ください！！ | N11: 税率を変更する場合はこちらを修正ください。→ | O11: 0.1
A12: ｼｰﾄ№ | B12: 連番 | C12: 完成納品年月日 | F12: 御社ご担当者名 | G12: 藤田建装担当者 | H12: 工事ｺｰﾄﾞ | I12: 工事名 | J12: 内容 | K12: 数量 | L12: 単価 単位 | M12: 単価 | N12: 金額 （税抜） | O12: 消費税 | P12: 金額 （税込） | Q12: T№ （伝票№）
C13: 西暦年 | D13: 月 | E13: 日 | H13: (4桁-4桁-2桁)
B14: 例： | C14: 2023 | D14: 4 | E14: 30 | F14: 取引 太郎 | G14: 藤田 太郎 | H14: 9999-9999-01 | I14: 藤田亭 改装工事 | J14: 工事一式 | K14: 1 | L14: 式 | M14: 1375000 | N14: =IF(M14="","",K14*M14) -> 1375000 | O14: =IF(N14="","",ROUNDDOWN(N14*$O$11,0)) -> 137500 | P14: =IF(N14="","",N14+O14) -> 1512500
A15: =B15&"-"&B24 -> 001-010 | B15: 001 | C15: 2026 | D15: 2 | E15: 28 | F15: 木村 正男 | G15: 石川 ほのか 様 | H15: 2302-0258-02 | I15: QB PREMIUM青葉台ﾓﾙﾀﾙ流出補償工事 | J15: 明細書1参照 | K15: 1 | L15: 式 | M15: 30000 | N15: =IF(M15="","",K15*M15) -> 30000 | O15: =IF(N15="","",ROUNDDOWN(N15*$O$11,0)) -> 3000 | P15: =IF(N15="","",N15+O15) -> 33000 | Q15: =CONCATENATE(MID(F10,3,4),B15) -> 2602001
B16: 002 | C16: 2026 | D16: 2 | E16: 28 | F16: 木村 正男 | G16: 石川 ほのか 様 | H16: 2302-0258-03 | I16: QB PREMIUM青葉台東急ｽｸｴｱ店子ﾌﾞﾚｰｶｰ交換工事 | J16: 明細書2参照 | K16: 1 | L16: 式 | M16: 60000 | N16: =IF(M16="","",K16*M16) -> 60000 | O16: =IF(N16="","",ROUNDDOWN(N16*$O$11,0)) -> 6000 | P16: =IF(N16="","",N16+O16) -> 66000 | Q16: =CONCATENATE(MID(F10,3,4),B16) -> 2602002
B17: 003 | C17: 2026 | D17: 2 | E17: 28 | F17: 木村 正男 | G17: 島田 結 様 | H17: 2702-0425-01 | I17: KFCｲｵﾝﾓｰﾙ川口店改装工事 | J17: 明細書3参照 | K17: 1 | L17: 式 | M17: 35000 | N17: =IF(M17="","",K17*M17) -> 35000 | O17: =IF(N17="","",ROUNDDOWN(N17*$O$11,0)) -> 3500 | P17: =IF(N17="","",N17+O17) -> 38500 | Q17: =CONCATENATE(MID(F10,3,4),B17) -> 2602003
B18: 004 | C18: 2026 | D18: 4 | E18: 30 | F18: 園原 | G18: nan 様 | H18: 20260415 | J18: 明細書4参照 | K18: 1 | L18: 式 | M18: 5300 | N18: =IF(M18="","",K18*M18) -> 5300 | O18: =IF(N18="","",ROUNDDOWN(N18*$O$11,0)) -> 530 | P18: =IF(N18="","",N18+O18) -> 5830 | Q18: =CONCATENATE(MID(F10,3,4),B18) -> 2602004
B19: 005 | N19: =IF(M19="","",K19*M19) | O19: =IF(N19="","",ROUNDDOWN(N19*$O$11,0)) | P19: =IF(N19="","",N19+O19) | Q19: =CONCATENATE(MID(F10,3,4),B19) -> 2602005
B20: 006 | N20: =IF(M20="","",K20*M20) | O20: =IF(N20="","",ROUNDDOWN(N20*$O$11,0)) | P20: =IF(N20="","",N20+O20) | Q20: =CONCATENATE(MID(F10,3,4),B20) -> 2602006
B21: 007 | N21: =IF(M21="","",K21*M21) | O21: =IF(N21="","",ROUNDDOWN(N21*$O$11,0)) | P21: =IF(N21="","",N21+O21) | Q21: =CONCATENATE(MID(F10,3,4),B21) -> 2602007
B22: 008 | N22: =IF(M22="","",K22*M22) | O22: =IF(N22="","",ROUNDDOWN(N22*$O$11,0)) | P22: =IF(N22="","",N22+O22) | Q22: =CONCATENATE(MID(F10,3,4),B22) -> 2602008
B23: 009 | N23: =IF(M23="","",K23*M23) | O23: =IF(N23="","",ROUNDDOWN(N23*$O$11,0)) | P23: =IF(N23="","",N23+O23) | Q23: =CONCATENATE(MID(F10,3,4),B23) -> 2602009
B24: 010 | N24: =IF(M24="","",K24*M24) | O24: =IF(N24="","",ROUNDDOWN(N24*$O$11,0)) | P24: =IF(N24="","",N24+O24) | Q24: =CONCATENATE(MID(F10,3,4),B24) -> 2602010
A25: =B25&"-"&B34 -> 011-020 | B25: 011 | N25: =IF(M25="","",K25*M25) | O25: =IF(N25="","",ROUNDDOWN(N25*$O$11,0)) | P25: =IF(N25="","",N25+O25) | Q25: =CONCATENATE(MID(F10,3,4),B25) -> 2602011
B26: 012 | N26: =IF(M26="","",K26*M26) | O26: =IF(N26="","",ROUNDDOWN(N26*$O$11,0)) | P26: =IF(N26="","",N26+O26) | Q26: =CONCATENATE(MID(F10,3,4),B26) -> 2602012
B27: 013 | N27: =IF(M27="","",K27*M27) | O27: =IF(N27="","",ROUNDDOWN(N27*$O$11,0)) | P27: =IF(N27="","",N27+O27) | Q27: =CONCATENATE(MID(F10,3,4),B27) -> 2602013
B28: 014 | N28: =IF(M28="","",K28*M28) | O28: =IF(N28="","",ROUNDDOWN(N28*$O$11,0)) | P28: =IF(N28="","",N28+O28) | Q28: =CONCATENATE(MID(F10,3,4),B28) -> 2602014
B29: 015 | N29: =IF(M29="","",K29*M29) | O29: =IF(N29="","",ROUNDDOWN(N29*$O$11,0)) | P29: =IF(N29="","",N29+O29) | Q29: =CONCATENATE(MID(F10,3,4),B29) -> 2602015
B30: 016 | N30: =IF(M30="","",K30*M30) | O30: =IF(N30="","",ROUNDDOWN(N30*$O$11,0)) | P30: =IF(N30="","",N30+O30) | Q30: =CONCATENATE(MID(F10,3,4),B30) -> 2602016
B31: 017 | N31: =IF(M31="","",K31*M31) | O31: =IF(N31="","",ROUNDDOWN(N31*$O$11,0)) | P31: =IF(N31="","",N31+O31) | Q31: =CONCATENATE(MID(F10,3,4),B31) -> 2602017
B32: 018 | N32: =IF(M32="","",K32*M32) | O32: =IF(N32="","",ROUNDDOWN(N32*$O$11,0)) | P32: =IF(N32="","",N32+O32) | Q32: =CONCATENATE(MID(F10,3,4),B32) -> 2602018
B33: 019 | N33: =IF(M33="","",K33*M33) | O33: =IF(N33="","",ROUNDDOWN(N33*$O$11,0)) | P33: =IF(N33="","",N33+O33) | Q33: =CONCATENATE(MID(F10,3,4),B33) -> 2602019
B34: 020 | N34: =IF(M34="","",K34*M34) | O34: =IF(N34="","",ROUNDDOWN(N34*$O$11,0)) | P34: =IF(N34="","",N34+O34) | Q34: =CONCATENATE(MID(F10,3,4),B34) -> 2602020
A35: =B35&"-"&B44 -> 021-030 | B35: 021 | N35: =IF(M35="","",K35*M35) | O35: =IF(N35="","",ROUNDDOWN(N35*$O$11,0)) | P35: =IF(N35="","",N35+O35) | Q35: =CONCATENATE(MID(F10,3,4),B35) -> 2602021
B36: 022 | N36: =IF(M36="","",K36*M36) | O36: =IF(N36="","",ROUNDDOWN(N36*$O$11,0)) | P36: =IF(N36="","",N36+O36) | Q36: =CONCATENATE(MID(F10,3,4),B36) -> 2602022
B37: 023 | N37: =IF(M37="","",K37*M37) | O37: =IF(N37="","",ROUNDDOWN(N37*$O$11,0)) | P37: =IF(N37="","",N37+O37) | Q37: =CONCATENATE(MID(F10,3,4),B37) -> 2602023
B38: 024 | N38: =IF(M38="","",K38*M38) | O38: =IF(N38="","",ROUNDDOWN(N38*$O$11,0)) | P38: =IF(N38="","",N38+O38) | Q38: =CONCATENATE(MID(F10,3,4),B38) -> 2602024
B39: 025 | N39: =IF(M39="","",K39*M39) | O39: =IF(N39="","",ROUNDDOWN(N39*$O$11,0)) | P39: =IF(N39="","",N39+O39) | Q39: =CONCATENATE(MID(F10,3,4),B39) -> 2602025
B40: 026 | N40: =IF(M40="","",K40*M40) | O40: =IF(N40="","",ROUNDDOWN(N40*$O$11,0)) | P40: =IF(N40="","",N40+O40) | Q40: =CONCATENATE(MID(F10,3,4),B40) -> 2602026
B41: 027 | N41: =IF(M41="","",K41*M41) | O41: =IF(N41="","",ROUNDDOWN(N41*$O$11,0)) | P41: =IF(N41="","",N41+O41) | Q41: =CONCATENATE(MID(F10,3,4),B41) -> 2602027
B42: 028 | N42: =IF(M42="","",K42*M42) | O42: =IF(N42="","",ROUNDDOWN(N42*$O$11,0)) | P42: =IF(N42="","",N42+O42) | Q42: =CONCATENATE(MID(F10,3,4),B42) -> 2602028
B43: 029 | N43: =IF(M43="","",K43*M43) | O43: =IF(N43="","",ROUNDDOWN(N43*$O$11,0)) | P43: =IF(N43="","",N43+O43) | Q43: =CONCATENATE(MID(F10,3,4),B43) -> 2602029
B44: 030 | N44: =IF(M44="","",K44*M44) | O44: =IF(N44="","",ROUNDDOWN(N44*$O$11,0)) | P44: =IF(N44="","",N44+O44) | Q44: =CONCATENATE(MID(F10,3,4),B44) -> 2602030
A45: =B45&"-"&B54 -> 031-040 | B45: 031 | N45: =IF(M45="","",K45*M45) | O45: =IF(N45="","",ROUNDDOWN(N45*$O$11,0)) | P45: =IF(N45="","",N45+O45) | Q45: =CONCATENATE(MID(F10,3,4),B45) -> 2602031
B46: 032 | N46: =IF(M46="","",K46*M46) | O46: =IF(N46="","",ROUNDDOWN(N46*$O$11,0)) | P46: =IF(N46="","",N46+O46) | Q46: =CONCATENATE(MID(F10,3,4),B46) -> 2602032
B47: 033 | N47: =IF(M47="","",K47*M47) | O47: =IF(N47="","",ROUNDDOWN(N47*$O$11,0)) | P47: =IF(N47="","",N47+O47) | Q47: =CONCATENATE(MID(F10,3,4),B47) -> 2602033
B48: 034 | N48: =IF(M48="","",K48*M48) | O48: =IF(N48="","",ROUNDDOWN(N48*$O$11,0)) | P48: =IF(N48="","",N48+O48) | Q48: =CONCATENATE(MID(F10,3,4),B48) -> 2602034
B49: 035 | N49: =IF(M49="","",K49*M49) | O49: =IF(N49="","",ROUNDDOWN(N49*$O$11,0)) | P49: =IF(N49="","",N49+O49) | Q49: =CONCATENATE(MID(F10,3,4),B49) -> 2602035
B50: 036 | N50: =IF(M50="","",K50*M50) | O50: =IF(N50="","",ROUNDDOWN(N50*$O$11,0)) | P50: =IF(N50="","",N50+O50) | Q50: =CONCATENATE(MID(F10,3,4),B50) -> 2602036
B51: 037 | N51: =IF(M51="","",K51*M51) | O51: =IF(N51="","",ROUNDDOWN(N51*$O$11,0)) | P51: =IF(N51="","",N51+O51) | Q51: =CONCATENATE(MID(F10,3,4),B51) -> 2602037
B52: 038 | N52: =IF(M52="","",K52*M52) | O52: =IF(N52="","",ROUNDDOWN(N52*$O$11,0)) | P52: =IF(N52="","",N52+O52) | Q52: =CONCATENATE(MID(F10,3,4),B52) -> 2602038
B53: 039 | N53: =IF(M53="","",K53*M53) | O53: =IF(N53="","",ROUNDDOWN(N53*$O$11,0)) | P53: =IF(N53="","",N53+O53) | Q53: =CONCATENATE(MID(F10,3,4),B53) -> 2602039
B54: 040 | N54: =IF(M54="","",K54*M54) | O54: =IF(N54="","",ROUNDDOWN(N54*$O$11,0)) | P54: =IF(N54="","",N54+O54) | Q54: =CONCATENATE(MID(F10,3,4),B54) -> 2602040
A55: =B55&"-"&B64 -> 041-050 | B55: 041 | N55: =IF(M55="","",K55*M55) | O55: =IF(N55="","",ROUNDDOWN(N55*$O$11,0)) | P55: =IF(N55="","",N55+O55) | Q55: =CONCATENATE(MID(F10,3,4),B55) -> 2602041
B56: 042 | N56: =IF(M56="","",K56*M56) | O56: =IF(N56="","",ROUNDDOWN(N56*$O$11,0)) | P56: =IF(N56="","",N56+O56) | Q56: =CONCATENATE(MID(F10,3,4),B56) -> 2602042
B57: 043 | N57: =IF(M57="","",K57*M57) | O57: =IF(N57="","",ROUNDDOWN(N57*$O$11,0)) | P57: =IF(N57="","",N57+O57) | Q57: =CONCATENATE(MID(F10,3,4),B57) -> 2602043
B58: 044 | N58: =IF(M58="","",K58*M58) | O58: =IF(N58="","",ROUNDDOWN(N58*$O$11,0)) | P58: =IF(N58="","",N58+O58) | Q58: =CONCATENATE(MID(F10,3,4),B58) -> 2602044
B59: 045 | N59: =IF(M59="","",K59*M59) | O59: =IF(N59="","",ROUNDDOWN(N59*$O$11,0)) | P59: =IF(N59="","",N59+O59) | Q59: =CONCATENATE(MID(F10,3,4),B59) -> 2602045
B60: 046 | N60: =IF(M60="","",K60*M60) | O60: =IF(N60="","",ROUNDDOWN(N60*$O$11,0)) | P60: =IF(N60="","",N60+O60) | Q60: =CONCATENATE(MID(F10,3,4),B60) -> 2602046
B61: 047 | N61: =IF(M61="","",K61*M61) | O61: =IF(N61="","",ROUNDDOWN(N61*$O$11,0)) | P61: =IF(N61="","",N61+O61) | Q61: =CONCATENATE(MID(F10,3,4),B61) -> 2602047
B62: 048 | N62: =IF(M62="","",K62*M62) | O62: =IF(N62="","",ROUNDDOWN(N62*$O$11,0)) | P62: =IF(N62="","",N62+O62) | Q62: =CONCATENATE(MID(F10,3,4),B62) -> 2602048
B63: 049 | N63: =IF(M63="","",K63*M63) | O63: =IF(N63="","",ROUNDDOWN(N63*$O$11,0)) | P63: =IF(N63="","",N63+O63) | Q63: =CONCATENATE(MID(F10,3,4),B63) -> 2602049
B64: 050 | N64: =IF(M64="","",K64*M64) | O64: =IF(N64="","",ROUNDDOWN(N64*$O$11,0)) | P64: =IF(N64="","",N64+O64) | Q64: =CONCATENATE(MID(F10,3,4),B64) -> 2602050
A65: =B65&"-"&B74 -> 051-060 | B65: 051 | N65: =IF(M65="","",K65*M65) | O65: =IF(N65="","",ROUNDDOWN(N65*$O$11,0)) | P65: =IF(N65="","",N65+O65) | Q65: =CONCATENATE(MID(F10,3,4),B65) -> 2602051
B66: 052 | N66: =IF(M66="","",K66*M66) | O66: =IF(N66="","",ROUNDDOWN(N66*$O$11,0)) | P66: =IF(N66="","",N66+O66) | Q66: =CONCATENATE(MID(F10,3,4),B66) -> 2602052
B67: 053 | N67: =IF(M67="","",K67*M67) | O67: =IF(N67="","",ROUNDDOWN(N67*$O$11,0)) | P67: =IF(N67="","",N67+O67) | Q67: =CONCATENATE(MID(F10,3,4),B67) -> 2602053
B68: 054 | N68: =IF(M68="","",K68*M68) | O68: =IF(N68="","",ROUNDDOWN(N68*$O$11,0)) | P68: =IF(N68="","",N68+O68) | Q68: =CONCATENATE(MID(F10,3,4),B68) -> 2602054
B69: 055 | N69: =IF(M69="","",K69*M69) | O69: =IF(N69="","",ROUNDDOWN(N69*$O$11,0)) | P69: =IF(N69="","",N69+O69) | Q69: =CONCATENATE(MID(F10,3,4),B69) -> 2602055
B70: 056 | N70: =IF(M70="","",K70*M70) | O70: =IF(N70="","",ROUNDDOWN(N70*$O$11,0)) | P70: =IF(N70="","",N70+O70) | Q70: =CONCATENATE(MID(F10,3,4),B70) -> 2602056
B71: 057 | N71: =IF(M71="","",K71*M71) | O71: =IF(N71="","",ROUNDDOWN(N71*$O$11,0)) | P71: =IF(N71="","",N71+O71) | Q71: =CONCATENATE(MID(F10,3,4),B71) -> 2602057
B72: 058 | N72: =IF(M72="","",K72*M72) | O72: =IF(N72="","",ROUNDDOWN(N72*$O$11,0)) | P72: =IF(N72="","",N72+O72) | Q72: =CONCATENATE(MID(F10,3,4),B72) -> 2602058
B73: 059 | N73: =IF(M73="","",K73*M73) | O73: =IF(N73="","",ROUNDDOWN(N73*$O$11,0)) | P73: =IF(N73="","",N73+O73) | Q73: =CONCATENATE(MID(F10,3,4),B73) -> 2602059
B74: 060 | N74: =IF(M74="","",K74*M74) | O74: =IF(N74="","",ROUNDDOWN(N74*$O$11,0)) | P74: =IF(N74="","",N74+O74) | Q74: =CONCATENATE(MID(F10,3,4),B74) -> 2602060
A75: =B75&"-"&B84 -> 061-070 | B75: 061 | N75: =IF(M75="","",K75*M75) | O75: =IF(N75="","",ROUNDDOWN(N75*$O$11,0)) | P75: =IF(N75="","",N75+O75) | Q75: =CONCATENATE(MID(F10,3,4),B75) -> 2602061
B76: 062 | N76: =IF(M76="","",K76*M76) | O76: =IF(N76="","",ROUNDDOWN(N76*$O$11,0)) | P76: =IF(N76="","",N76+O76) | Q76: =CONCATENATE(MID(F10,3,4),B76) -> 2602062
B77: 063 | N77: =IF(M77="","",K77*M77) | O77: =IF(N77="","",ROUNDDOWN(N77*$O$11,0)) | P77: =IF(N77="","",N77+O77) | Q77: =CONCATENATE(MID(F10,3,4),B77) -> 2602063
B78: 064 | N78: =IF(M78="","",K78*M78) | O78: =IF(N78="","",ROUNDDOWN(N78*$O$11,0)) | P78: =IF(N78="","",N78+O78) | Q78: =CONCATENATE(MID(F10,3,4),B78) -> 2602064
B79: 065 | N79: =IF(M79="","",K79*M79) | O79: =IF(N79="","",ROUNDDOWN(N79*$O$11,0)) | P79: =IF(N79="","",N79+O79) | Q79: =CONCATENATE(MID(F10,3,4),B79) -> 2602065
B80: 066 | N80: =IF(M80="","",K80*M80) | O80: =IF(N80="","",ROUNDDOWN(N80*$O$11,0)) | P80: =IF(N80="","",N80+O80) | Q80: =CONCATENATE(MID(F10,3,4),B80) -> 2602066
B81: 067 | N81: =IF(M81="","",K81*M81) | O81: =IF(N81="","",ROUNDDOWN(N81*$O$11,0)) | P81: =IF(N81="","",N81+O81) | Q81: =CONCATENATE(MID(F10,3,4),B81) -> 2602067
B82: 068 | N82: =IF(M82="","",K82*M82) | O82: =IF(N82="","",ROUNDDOWN(N82*$O$11,0)) | P82: =IF(N82="","",N82+O82) | Q82: =CONCATENATE(MID(F10,3,4),B82) -> 2602068
B83: 069 | N83: =IF(M83="","",K83*M83) | O83: =IF(N83="","",ROUNDDOWN(N83*$O$11,0)) | P83: =IF(N83="","",N83+O83) | Q83: =CONCATENATE(MID(F10,3,4),B83) -> 2602069
B84: 070 | N84: =IF(M84="","",K84*M84) | O84: =IF(N84="","",ROUNDDOWN(N84*$O$11,0)) | P84: =IF(N84="","",N84+O84) | Q84: =CONCATENATE(MID(F10,3,4),B84) -> 2602070
A85: =B85&"-"&B94 -> 071-080 | B85: 071 | N85: =IF(M85="","",K85*M85) | O85: =IF(N85="","",ROUNDDOWN(N85*$O$11,0)) | P85: =IF(N85="","",N85+O85) | Q85: =CONCATENATE(MID(F10,3,4),B85) -> 2602071
B86: 072 | N86: =IF(M86="","",K86*M86) | O86: =IF(N86="","",ROUNDDOWN(N86*$O$11,0)) | P86: =IF(N86="","",N86+O86) | Q86: =CONCATENATE(MID(F10,3,4),B86) -> 2602072
B87: 073 | N87: =IF(M87="","",K87*M87) | O87: =IF(N87="","",ROUNDDOWN(N87*$O$11,0)) | P87: =IF(N87="","",N87+O87) | Q87: =CONCATENATE(MID(F10,3,4),B87) -> 2602073
B88: 074 | N88: =IF(M88="","",K88*M88) | O88: =IF(N88="","",ROUNDDOWN(N88*$O$11,0)) | P88: =IF(N88="","",N88+O88) | Q88: =CONCATENATE(MID(F10,3,4),B88) -> 2602074
B89: 075 | N89: =IF(M89="","",K89*M89) | O89: =IF(N89="","",ROUNDDOWN(N89*$O$11,0)) | P89: =IF(N89="","",N89+O89) | Q89: =CONCATENATE(MID(F10,3,4),B89) -> 2602075
B90: 076 | N90: =IF(M90="","",K90*M90) | O90: =IF(N90="","",ROUNDDOWN(N90*$O$11,0)) | P90: =IF(N90="","",N90+O90) | Q90: =CONCATENATE(MID(F10,3,4),B90) -> 2602076
B91: 077 | N91: =IF(M91="","",K91*M91) | O91: =IF(N91="","",ROUNDDOWN(N91*$O$11,0)) | P91: =IF(N91="","",N91+O91) | Q91: =CONCATENATE(MID(F10,3,4),B91) -> 2602077
B92: 078 | N92: =IF(M92="","",K92*M92) | O92: =IF(N92="","",ROUNDDOWN(N92*$O$11,0)) | P92: =IF(N92="","",N92+O92) | Q92: =CONCATENATE(MID(F10,3,4),B92) -> 2602078
B93: 079 | N93: =IF(M93="","",K93*M93) | O93: =IF(N93="","",ROUNDDOWN(N93*$O$11,0)) | P93: =IF(N93="","",N93+O93) | Q93: =CONCATENATE(MID(F10,3,4),B93) -> 2602079
B94: 080 | N94: =IF(M94="","",K94*M94) | O94: =IF(N94="","",ROUNDDOWN(N94*$O$11,0)) | P94: =IF(N94="","",N94+O94) | Q94: =CONCATENATE(MID(F10,3,4),B94) -> 2602080
A95: =B95&"-"&B104 -> 081-090 | B95: 081 | N95: =IF(M95="","",K95*M95) | O95: =IF(N95="","",ROUNDDOWN(N95*$O$11,0)) | P95: =IF(N95="","",N95+O95) | Q95: =CONCATENATE(MID(F10,3,4),B95) -> 2602081
B96: 082 | N96: =IF(M96="","",K96*M96) | O96: =IF(N96="","",ROUNDDOWN(N96*$O$11,0)) | P96: =IF(N96="","",N96+O96) | Q96: =CONCATENATE(MID(F10,3,4),B96) -> 2602082
B97: 083 | N97: =IF(M97="","",K97*M97) | O97: =IF(N97="","",ROUNDDOWN(N97*$O$11,0)) | P97: =IF(N97="","",N97+O97) | Q97: =CONCATENATE(MID(F10,3,4),B97) -> 2602083
B98: 084 | N98: =IF(M98="","",K98*M98) | O98: =IF(N98="","",ROUNDDOWN(N98*$O$11,0)) | P98: =IF(N98="","",N98+O98) | Q98: =CONCATENATE(MID(F10,3,4),B98) -> 2602084
B99: 085 | N99: =IF(M99="","",K99*M99) | O99: =IF(N99="","",ROUNDDOWN(N99*$O$11,0)) | P99: =IF(N99="","",N99+O99) | Q99: =CONCATENATE(MID(F10,3,4),B99) -> 2602085
B100: 086 | N100: =IF(M100="","",K100*M100) | O100: =IF(N100="","",ROUNDDOWN(N100*$O$11,0)) | P100: =IF(N100="","",N100+O100) | Q100: =CONCATENATE(MID(F10,3,4),B100) -> 2602086
B101: 087 | N101: =IF(M101="","",K101*M101) | O101: =IF(N101="","",ROUNDDOWN(N101*$O$11,0)) | P101: =IF(N101="","",N101+O101) | Q101: =CONCATENATE(MID(F10,3,4),B101) -> 2602087
B102: 088 | N102: =IF(M102="","",K102*M102) | O102: =IF(N102="","",ROUNDDOWN(N102*$O$11,0)) | P102: =IF(N102="","",N102+O102) | Q102: =CONCATENATE(MID(F10,3,4),B102) -> 2602088
B103: 089 | N103: =IF(M103="","",K103*M103) | O103: =IF(N103="","",ROUNDDOWN(N103*$O$11,0)) | P103: =IF(N103="","",N103+O103) | Q103: =CONCATENATE(MID(F10,3,4),B103) -> 2602089
...

Sheet 合計請求書
C1: ■ | E1: =LEFT(E10,4)&"年"&RIGHT(E10,2)&"月分合計請求書" -> 2026年02月分合計請求書 | M1: =G10 -> 72130
M2: ="日付："&LEFT(E10,4)&"年"&RIGHT(E10,2)&"月末日" -> 日付：2026年02月末日 | P2: 印刷範囲 | Q2: =IF(MAX($AP$5:$AP$19)=0,1,MAX($AP$5:$AP$19)) -> 1 | R2: 行目 | S2: 14 | T2: 列目まで印刷する
B3: 〒111-0035
B4: 東京都台東区西浅草1-7-4 | J4: 住所： | K4: =請求データ入力!F2 -> 〒110-0012 東京都台東区竜泉3-40-4
B5: 株式会社藤田建装 御中
J6: 会社名： | K6: =請求データ入力!F6 -> 有限会社木村左官工業 | N6: 印
J8: TEL: | K8: =請求データ入力!K4 -> 090-4609-2757
B10: 請求年月 | E10: =請求データ入力!F10 -> 202602 | F10: 取引先コード | G10: =請求データ入力!K2 -> 72130 | I10: =LEFT(E10,4)&"年"&RIGHT(E10,2)&"月分合計金額(税込)" -> 2026年02月分合計金額(税込) | M10: =SUM(M14:M113) -> 143330
A12: 連番 | B12: 完成納品年月日 | E12: 工事ｺｰﾄﾞ | F12: 工事名 | G12: 内容 | H12: 数量 | I12: 単価 単位 | J12: 単価 | K12: 金額 （税抜） | L12: 消費税 | M12: 金額 （税込） | N12: T№ （伝票№）
B13: 西暦年 | C13: 月 | D13: 日 | E13: (4桁-4桁-2桁)
A14: 001 | B14: =IF(請求データ入力!C15="","",請求データ入力!C15) -> 2026 | C14: =IF(請求データ入力!D15="","",請求データ入力!D15) -> 2 | D14: =IF(請求データ入力!E15="","",請求データ入力!E15) -> 28 | E14: =IF(請求データ入力!H15="","",請求データ入力!H15) -> 2302-0258-02 | F14: =IF(請求データ入力!I15="","",請求データ入力!I15) -> QB PREMIUM青葉台ﾓﾙﾀﾙ流出補償工事 | G14: =IF(請求データ入力!J15="","",請求データ入力!J15) -> 明細書1参照 | H14: =IF(請求データ入力!K15="","",請求データ入力!K15) -> 1 | I14: =IF(請求データ入力!L15="","",請求データ入力!L15) -> 式 | J14: =IF(請求データ入力!M15="","",請求データ入力!M15) -> 30000 | K14: =IF(請求データ入力!N15="","",請求データ入力!N15) -> 30000 | L14: =IF(請求データ入力!O15="","",請求データ入力!O15) -> 3000 | M14: =IF(請求データ入力!P15="","",請求データ入力!P15) -> 33000 | N14: =CONCATENATE(MID(E10,3,4),A14) -> 2602001
A15: 002 | B15: =IF(請求データ入力!C16="","",請求データ入力!C16) -> 2026 | C15: =IF(請求データ入力!D16="","",請求データ入力!D16) -> 2 | D15: =IF(請求データ入力!E16="","",請求データ入力!E16) -> 28 | E15: =IF(請求データ入力!H16="","",請求データ入力!H16) -> 2302-0258-03 | F15: =IF(請求データ入力!I16="","",請求データ入力!I16) -> QB PREMIUM青葉台東急ｽｸｴｱ店子ﾌﾞﾚｰｶｰ交換工事 | G15: =IF(請求データ入力!J16="","",請求データ入力!J16) -> 明細書2参照 | H15: =IF(請求データ入力!K16="","",請求データ入力!K16) -> 1 | I15: =IF(請求データ入力!L16="","",請求データ入力!L16) -> 式 | J15: =IF(請求データ入力!M16="","",請求データ入力!M16) -> 60000 | K15: =IF(請求データ入力!N16="","",請求データ入力!N16) -> 60000 | L15: =IF(請求データ入力!O16="","",請求データ入力!O16) -> 6000 | M15: =IF(請求データ入力!P16="","",請求データ入力!P16) -> 66000 | N15: =CONCATENATE(MID(E10,3,4),A15) -> 2602002
A16: 003 | B16: =IF(請求データ入力!C17="","",請求データ入力!C17) -> 2026 | C16: =IF(請求データ入力!D17="","",請求データ入力!D17) -> 2 | D16: =IF(請求データ入力!E17="","",請求データ入力!E17) -> 28 | E16: =IF(請求データ入力!H17="","",請求データ入力!H17) -> 2702-0425-01 | F16: =IF(請求データ入力!I17="","",請求データ入力!I17) -> KFCｲｵﾝﾓｰﾙ川口店改装工事 | G16: =IF(請求データ入力!J17="","",請求データ入力!J17) -> 明細書3参照 | H16: =IF(請求データ入力!K17="","",請求データ入力!K17) -> 1 | I16: =IF(請求データ入力!L17="","",請求データ入力!L17) -> 式 | J16: =IF(請求データ入力!M17="","",請求データ入力!M17) -> 35000 | K16: =IF(請求データ入力!N17="","",請求データ入力!N17) -> 35000 | L16: =IF(請求データ入力!O17="","",請求データ入力!O17) -> 3500 | M16: =IF(請求データ入力!P17="","",請求データ入力!P17) -> 38500 | N16: =CONCATENATE(MID(E10,3,4),A16) -> 2602003
A17: 004 | B17: =IF(請求データ入力!C18="","",請求データ入力!C18) -> 2026 | C17: =IF(請求データ入力!D18="","",請求データ入力!D18) -> 4 | D17: =IF(請求データ入力!E18="","",請求データ入力!E18) -> 30 | E17: =IF(請求データ入力!H18="","",請求データ入力!H18) -> 20260415 | F17: =IF(請求データ入力!I18="","",請求データ入力!I18) | G17: =IF(請求データ入力!J18="","",請求データ入力!J18) -> 明細書4参照 | H17: =IF(請求データ入力!K18="","",請求データ入力!K18) -> 1 | I17: =IF(請求データ入力!L18="","",請求データ入力!L18) -> 式 | J17: =IF(請求データ入力!M18="","",請求データ入力!M18) -> 5300 | K17: =IF(請求データ入力!N18="","",請求データ入力!N18) -> 5300 | L17: =IF(請求データ入力!O18="","",請求データ入力!O18) -> 530 | M17: =IF(請求データ入力!P18="","",請求データ入力!P18) -> 5830 | N17: =CONCATENATE(MID(E10,3,4),A17) -> 2602004
A18: 005 | B18: =IF(請求データ入力!C19="","",請求データ入力!C19) | C18: =IF(請求データ入力!D19="","",請求データ入力!D19) | D18: =IF(請求データ入力!E19="","",請求データ入力!E19) | E18: =IF(請求データ入力!H19="","",請求データ入力!H19) | F18: =IF(請求データ入力!I19="","",請求データ入力!I19) | G18: =IF(請求データ入力!J19="","",請求データ入力!J19) | H18: =IF(請求データ入力!K19="","",請求データ入力!K19) | I18: =IF(請求データ入力!L19="","",請求データ入力!L19) | J18: =IF(請求データ入力!M19="","",請求データ入力!M19) | K18: =IF(請求データ入力!N19="","",請求データ入力!N19) | L18: =IF(請求データ入力!O19="","",請求データ入力!O19) | M18: =IF(請求データ入力!P19="","",請求データ入力!P19) | N18: =CONCATENATE(MID(E10,3,4),A18) -> 2602005
A19: 006 | B19: =IF(請求データ入力!C20="","",請求データ入力!C20) | C19: =IF(請求データ入力!D20="","",請求データ入力!D20) | D19: =IF(請求データ入力!E20="","",請求データ入力!E20) | E19: =IF(請求データ入力!H20="","",請求データ入力!H20) | F19: =IF(請求データ入力!I20="","",請求データ入力!I20) | G19: =IF(請求データ入力!J20="","",請求データ入力!J20) | H19: =IF(請求データ入力!K20="","",請求データ入力!K20) | I19: =IF(請求データ入力!L20="","",請求データ入力!L20) | J19: =IF(請求データ入力!M20="","",請求データ入力!M20) | K19: =IF(請求データ入力!N20="","",請求データ入力!N20) | L19: =IF(請求データ入力!O20="","",請求データ入力!O20) | M19: =IF(請求データ入力!P20="","",請求データ入力!P20) | N19: =CONCATENATE(MID(E10,3,4),A19) -> 2602006
A20: 007 | B20: =IF(請求データ入力!C21="","",請求データ入力!C21) | C20: =IF(請求データ入力!D21="","",請求データ入力!D21) | D20: =IF(請求データ入力!E21="","",請求データ入力!E21) | E20: =IF(請求データ入力!H21="","",請求データ入力!H21) | F20: =IF(請求データ入力!I21="","",請求データ入力!I21) | G20: =IF(請求データ入力!J21="","",請求データ入力!J21) | H20: =IF(請求データ入力!K21="","",請求データ入力!K21) | I20: =IF(請求データ入力!L21="","",請求データ入力!L21) | J20: =IF(請求データ入力!M21="","",請求データ入力!M21) | K20: =IF(請求データ入力!N21="","",請求データ入力!N21) | L20: =IF(請求データ入力!O21="","",請求データ入力!O21) | M20: =IF(請求データ入力!P21="","",請求データ入力!P21) | N20: =CONCATENATE(MID(E10,3,4),A20) -> 2602007
A21: 008 | B21: =IF(請求データ入力!C22="","",請求データ入力!C22) | C21: =IF(請求データ入力!D22="","",請求データ入力!D22) | D21: =IF(請求データ入力!E22="","",請求データ入力!E22) | E21: =IF(請求データ入力!H22="","",請求データ入力!H22) | F21: =IF(請求データ入力!I22="","",請求データ入力!I22) | G21: =IF(請求データ入力!J22="","",請求データ入力!J22) | H21: =IF(請求データ入力!K22="","",請求データ入力!K22) | I21: =IF(請求データ入力!L22="","",請求データ入力!L22) | J21: =IF(請求データ入力!M22="","",請求データ入力!M22) | K21: =IF(請求データ入力!N22="","",請求データ入力!N22) | L21: =IF(請求データ入力!O22="","",請求データ入力!O22) | M21: =IF(請求データ入力!P22="","",請求データ入力!P22) | N21: =CONCATENATE(MID(E10,3,4),A21) -> 2602008
A22: 009 | B22: =IF(請求データ入力!C23="","",請求データ入力!C23) | C22: =IF(請求データ入力!D23="","",請求データ入力!D23) | D22: =IF(請求データ入力!E23="","",請求データ入力!E23) | E22: =IF(請求データ入力!H23="","",請求データ入力!H23) | F22: =IF(請求データ入力!I23="","",請求データ入力!I23) | G22: =IF(請求データ入力!J23="","",請求データ入力!J23) | H22: =IF(請求データ入力!K23="","",請求データ入力!K23) | I22: =IF(請求データ入力!L23="","",請求データ入力!L23) | J22: =IF(請求データ入力!M23="","",請求データ入力!M23) | K22: =IF(請求データ入力!N23="","",請求データ入力!N23) | L22: =IF(請求データ入力!O23="","",請求データ入力!O23) | M22: =IF(請求データ入力!P23="","",請求データ入力!P23) | N22: =CONCATENATE(MID(E10,3,4),A22) -> 2602009
A23: 010 | B23: =IF(請求データ入力!C24="","",請求データ入力!C24) | C23: =IF(請求データ入力!D24="","",請求データ入力!D24) | D23: =IF(請求データ入力!E24="","",請求データ入力!E24) | E23: =IF(請求データ入力!H24="","",請求データ入力!H24) | F23: =IF(請求データ入力!I24="","",請求データ入力!I24) | G23: =IF(請求データ入力!J24="","",請求データ入力!J24) | H23: =IF(請求データ入力!K24="","",請求データ入力!K24) | I23: =IF(請求データ入力!L24="","",請求データ入力!L24) | J23: =IF(請求データ入力!M24="","",請求データ入力!M24) | K23: =IF(請求データ入力!N24="","",請求データ入力!N24) | L23: =IF(請求データ入力!O24="","",請求データ入力!O24) | M23: =IF(請求データ入力!P24="","",請求データ入力!P24) | N23: =CONCATENATE(MID(E10,3,4),A23) -> 2602010
A24: 011 | B24: =IF(請求データ入力!C25="","",請求データ入力!C25) | C24: =IF(請求データ入力!D25="","",請求データ入力!D25) | D24: =IF(請求データ入力!E25="","",請求データ入力!E25) | E24: =IF(請求データ入力!H25="","",請求データ入力!H25) | F24: =IF(請求データ入力!I25="","",請求データ入力!I25) | G24: =IF(請求データ入力!J25="","",請求データ入力!J25) | H24: =IF(請求データ入力!K25="","",請求データ入力!K25) | I24: =IF(請求データ入力!L25="","",請求データ入力!L25) | J24: =IF(請求データ入力!M25="","",請求データ入力!M25) | K24: =IF(請求データ入力!N25="","",請求データ入力!N25) | L24: =IF(請求データ入力!O25="","",請求データ入力!O25) | M24: =IF(請求データ入力!P25="","",請求データ入力!P25) | N24: =CONCATENATE(MID(E10,3,4),A24) -> 2602011
A25: 012 | B25: =IF(請求データ入力!C26="","",請求データ入力!C26) | C25: =IF(請求データ入力!D26="","",請求データ入力!D26) | D25: =IF(請求データ入力!E26="","",請求データ入力!E26) | E25: =IF(請求データ入力!H26="","",請求データ入力!H26) | F25: =IF(請求データ入力!I26="","",請求データ入力!I26) | G25: =IF(請求データ入力!J26="","",請求データ入力!J26) | H25: =IF(請求データ入力!K26="","",請求データ入力!K26) | I25: =IF(請求データ入力!L26="","",請求データ入力!L26) | J25: =IF(請求データ入力!M26="","",請求データ入力!M26) | K25: =IF(請求データ入力!N26="","",請求データ入力!N26) | L25: =IF(請求データ入力!O26="","",請求データ入力!O26) | M25: =IF(請求データ入力!P26="","",請求データ入力!P26) | N25: =CONCATENATE(MID(E10,3,4),A25) -> 2602012
A26: 013 | B26: =IF(請求データ入力!C27="","",請求データ入力!C27) | C26: =IF(請求データ入力!D27="","",請求データ入力!D27) | D26: =IF(請求データ入力!E27="","",請求データ入力!E27) | E26: =IF(請求データ入力!H27="","",請求データ入力!H27) | F26: =IF(請求データ入力!I27="","",請求データ入力!I27) | G26: =IF(請求データ入力!J27="","",請求データ入力!J27) | H26: =IF(請求データ入力!K27="","",請求データ入力!K27) | I26: =IF(請求データ入力!L27="","",請求データ入力!L27) | J26: =IF(請求データ入力!M27="","",請求データ入力!M27) | K26: =IF(請求データ入力!N27="","",請求データ入力!N27) | L26: =IF(請求データ入力!O27="","",請求データ入力!O27) | M26: =IF(請求データ入力!P27="","",請求データ入力!P27) | N26: =CONCATENATE(MID(E10,3,4),A26) -> 2602013
A27: 014 | B27: =IF(請求データ入力!C28="","",請求データ入力!C28) | C27: =IF(請求データ入力!D28="","",請求データ入力!D28) | D27: =IF(請求データ入力!E28="","",請求データ入力!E28) | E27: =IF(請求データ入力!H28="","",請求データ入力!H28) | F27: =IF(請求データ入力!I28="","",請求データ入力!I28) | G27: =IF(請求データ入力!J28="","",請求データ入力!J28) | H27: =IF(請求データ入力!K28="","",請求データ入力!K28) | I27: =IF(請求データ入力!L28="","",請求データ入力!L28) | J27: =IF(請求データ入力!M28="","",請求データ入力!M28) | K27: =IF(請求データ入力!N28="","",請求データ入力!N28) | L27: =IF(請求データ入力!O28="","",請求データ入力!O28) | M27: =IF(請求データ入力!P28="","",請求データ入力!P28) | N27: =CONCATENATE(MID(E10,3,4),A27) -> 2602014
A28: 015 | B28: =IF(請求データ入力!C29="","",請求データ入力!C29) | C28: =IF(請求データ入力!D29="","",請求データ入力!D29) | D28: =IF(請求データ入力!E29="","",請求データ入力!E29) | E28: =IF(請求データ入力!H29="","",請求データ入力!H29) | F28: =IF(請求データ入力!I29="","",請求データ入力!I29) | G28: =IF(請求データ入力!J29="","",請求データ入力!J29) | H28: =IF(請求データ入力!K29="","",請求データ入力!K29) | I28: =IF(請求データ入力!L29="","",請求データ入力!L29) | J28: =IF(請求データ入力!M29="","",請求データ入力!M29) | K28: =IF(請求データ入力!N29="","",請求データ入力!N29) | L28: =IF(請求データ入力!O29="","",請求データ入力!O29) | M28: =IF(請求データ入力!P29="","",請求データ入力!P29) | N28: =CONCATENATE(MID(E10,3,4),A28) -> 2602015
A29: 016 | B29: =IF(請求データ入力!C30="","",請求データ入力!C30) | C29: =IF(請求データ入力!D30="","",請求データ入力!D30) | D29: =IF(請求データ入力!E30="","",請求データ入力!E30) | E29: =IF(請求データ入力!H30="","",請求データ入力!H30) | F29: =IF(請求データ入力!I30="","",請求データ入力!I30) | G29: =IF(請求データ入力!J30="","",請求データ入力!J30) | H29: =IF(請求データ入力!K30="","",請求データ入力!K30) | I29: =IF(請求データ入力!L30="","",請求データ入力!L30) | J29: =IF(請求データ入力!M30="","",請求データ入力!M30) | K29: =IF(請求データ入力!N30="","",請求データ入力!N30) | L29: =IF(請求データ入力!O30="","",請求データ入力!O30) | M29: =IF(請求データ入力!P30="","",請求データ入力!P30) | N29: =CONCATENATE(MID(E10,3,4),A29) -> 2602016
A30: 017 | B30: =IF(請求データ入力!C31="","",請求データ入力!C31) | C30: =IF(請求データ入力!D31="","",請求データ入力!D31) | D30: =IF(請求データ入力!E31="","",請求データ入力!E31) | E30: =IF(請求データ入力!H31="","",請求データ入力!H31) | F30: =IF(請求データ入力!I31="","",請求データ入力!I31) | G30: =IF(請求データ入力!J31="","",請求データ入力!J31) | H30: =IF(請求データ入力!K31="","",請求データ入力!K31) | I30: =IF(請求データ入力!L31="","",請求データ入力!L31) | J30: =IF(請求データ入力!M31="","",請求データ入力!M31) | K30: =IF(請求データ入力!N31="","",請求データ入力!N31) | L30: =IF(請求データ入力!O31="","",請求データ入力!O31) | M30: =IF(請求データ入力!P31="","",請求データ入力!P31) | N30: =CONCATENATE(MID(E10,3,4),A30) -> 2602017
A31: 018 | B31: =IF(請求データ入力!C32="","",請求データ入力!C32) | C31: =IF(請求データ入力!D32="","",請求データ入力!D32) | D31: =IF(請求データ入力!E32="","",請求データ入力!E32) | E31: =IF(請求データ入力!H32="","",請求データ入力!H32) | F31: =IF(請求データ入力!I32="","",請求データ入力!I32) | G31: =IF(請求データ入力!J32="","",請求データ入力!J32) | H31: =IF(請求データ入力!K32="","",請求データ入力!K32) | I31: =IF(請求データ入力!L32="","",請求データ入力!L32) | J31: =IF(請求データ入力!M32="","",請求データ入力!M32) | K31: =IF(請求データ入力!N32="","",請求データ入力!N32) | L31: =IF(請求データ入力!O32="","",請求データ入力!O32) | M31: =IF(請求データ入力!P32="","",請求データ入力!P32) | N31: =CONCATENATE(MID(E10,3,4),A31) -> 2602018
A32: 019 | B32: =IF(請求データ入力!C33="","",請求データ入力!C33) | C32: =IF(請求データ入力!D33="","",請求データ入力!D33) | D32: =IF(請求データ入力!E33="","",請求データ入力!E33) | E32: =IF(請求データ入力!H33="","",請求データ入力!H33) | F32: =IF(請求データ入力!I33="","",請求データ入力!I33) | G32: =IF(請求データ入力!J33="","",請求データ入力!J33) | H32: =IF(請求データ入力!K33="","",請求データ入力!K33) | I32: =IF(請求データ入力!L33="","",請求データ入力!L33) | J32: =IF(請求データ入力!M33="","",請求データ入力!M33) | K32: =IF(請求データ入力!N33="","",請求データ入力!N33) | L32: =IF(請求データ入力!O33="","",請求データ入力!O33) | M32: =IF(請求データ入力!P33="","",請求データ入力!P33) | N32: =CONCATENATE(MID(E10,3,4),A32) -> 2602019
A33: 020 | B33: =IF(請求データ入力!C34="","",請求データ入力!C34) | C33: =IF(請求データ入力!D34="","",請求データ入力!D34) | D33: =IF(請求データ入力!E34="","",請求データ入力!E34) | E33: =IF(請求データ入力!H34="","",請求データ入力!H34) | F33: =IF(請求データ入力!I34="","",請求データ入力!I34) | G33: =IF(請求データ入力!J34="","",請求データ入力!J34) | H33: =IF(請求データ入力!K34="","",請求データ入力!K34) | I33: =IF(請求データ入力!L34="","",請求データ入力!L34) | J33: =IF(請求データ入力!M34="","",請求データ入力!M34) | K33: =IF(請求データ入力!N34="","",請求データ入力!N34) | L33: =IF(請求データ入力!O34="","",請求データ入力!O34) | M33: =IF(請求データ入力!P34="","",請求データ入力!P34) | N33: =CONCATENATE(MID(E10,3,4),A33) -> 2602020
A34: 021 | B34: =IF(請求データ入力!C35="","",請求データ入力!C35) | C34: =IF(請求データ入力!D35="","",請求データ入力!D35) | D34: =IF(請求データ入力!E35="","",請求データ入力!E35) | E34: =IF(請求データ入力!H35="","",請求データ入力!H35) | F34: =IF(請求データ入力!I35="","",請求データ入力!I35) | G34: =IF(請求データ入力!J35="","",請求データ入力!J35) | H34: =IF(請求データ入力!K35="","",請求データ入力!K35) | I34: =IF(請求データ入力!L35="","",請求データ入力!L35) | J34: =IF(請求データ入力!M35="","",請求データ入力!M35) | K34: =IF(請求データ入力!N35="","",請求データ入力!N35) | L34: =IF(請求データ入力!O35="","",請求データ入力!O35) | M34: =IF(請求データ入力!P35="","",請求データ入力!P35) | N34: =CONCATENATE(MID(E10,3,4),A34) -> 2602021
A35: 022 | B35: =IF(請求データ入力!C36="","",請求データ入力!C36) | C35: =IF(請求データ入力!D36="","",請求データ入力!D36) | D35: =IF(請求データ入力!E36="","",請求データ入力!E36) | E35: =IF(請求データ入力!H36="","",請求データ入力!H36) | F35: =IF(請求データ入力!I36="","",請求データ入力!I36) | G35: =IF(請求データ入力!J36="","",請求データ入力!J36) | H35: =IF(請求データ入力!K36="","",請求データ入力!K36) | I35: =IF(請求データ入力!L36="","",請求データ入力!L36) | J35: =IF(請求データ入力!M36="","",請求データ入力!M36) | K35: =IF(請求データ入力!N36="","",請求データ入力!N36) | L35: =IF(請求データ入力!O36="","",請求データ入力!O36) | M35: =IF(請求データ入力!P36="","",請求データ入力!P36) | N35: =CONCATENATE(MID(E10,3,4),A35) -> 2602022
A36: 023 | B36: =IF(請求データ入力!C37="","",請求データ入力!C37) | C36: =IF(請求データ入力!D37="","",請求データ入力!D37) | D36: =IF(請求データ入力!E37="","",請求データ入力!E37) | E36: =IF(請求データ入力!H37="","",請求データ入力!H37) | F36: =IF(請求データ入力!I37="","",請求データ入力!I37) | G36: =IF(請求データ入力!J37="","",請求データ入力!J37) | H36: =IF(請求データ入力!K37="","",請求データ入力!K37) | I36: =IF(請求データ入力!L37="","",請求データ入力!L37) | J36: =IF(請求データ入力!M37="","",請求データ入力!M37) | K36: =IF(請求データ入力!N37="","",請求データ入力!N37) | L36: =IF(請求データ入力!O37="","",請求データ入力!O37) | M36: =IF(請求データ入力!P37="","",請求データ入力!P37) | N36: =CONCATENATE(MID(E10,3,4),A36) -> 2602023
A37: 024 | B37: =IF(請求データ入力!C38="","",請求データ入力!C38) | C37: =IF(請求データ入力!D38="","",請求データ入力!D38) | D37: =IF(請求データ入力!E38="","",請求データ入力!E38) | E37: =IF(請求データ入力!H38="","",請求データ入力!H38) | F37: =IF(請求データ入力!I38="","",請求データ入力!I38) | G37: =IF(請求データ入力!J38="","",請求データ入力!J38) | H37: =IF(請求データ入力!K38="","",請求データ入力!K38) | I37: =IF(請求データ入力!L38="","",請求データ入力!L38) | J37: =IF(請求データ入力!M38="","",請求データ入力!M38) | K37: =IF(請求データ入力!N38="","",請求データ入力!N38) | L37: =IF(請求データ入力!O38="","",請求データ入力!O38) | M37: =IF(請求データ入力!P38="","",請求データ入力!P38) | N37: =CONCATENATE(MID(E10,3,4),A37) -> 2602024
A38: 025 | B38: =IF(請求データ入力!C39="","",請求データ入力!C39) | C38: =IF(請求データ入力!D39="","",請求データ入力!D39) | D38: =IF(請求データ入力!E39="","",請求データ入力!E39) | E38: =IF(請求データ入力!H39="","",請求データ入力!H39) | F38: =IF(請求データ入力!I39="","",請求データ入力!I39) | G38: =IF(請求データ入力!J39="","",請求データ入力!J39) | H38: =IF(請求データ入力!K39="","",請求データ入力!K39) | I38: =IF(請求データ入力!L39="","",請求データ入力!L39) | J38: =IF(請求データ入力!M39="","",請求データ入力!M39) | K38: =IF(請求データ入力!N39="","",請求データ入力!N39) | L38: =IF(請求データ入力!O39="","",請求データ入力!O39) | M38: =IF(請求データ入力!P39="","",請求データ入力!P39) | N38: =CONCATENATE(MID(E10,3,4),A38) -> 2602025
A39: 026 | B39: =IF(請求データ入力!C40="","",請求データ入力!C40) | C39: =IF(請求データ入力!D40="","",請求データ入力!D40) | D39: =IF(請求データ入力!E40="","",請求データ入力!E40) | E39: =IF(請求データ入力!H40="","",請求データ入力!H40) | F39: =IF(請求データ入力!I40="","",請求データ入力!I40) | G39: =IF(請求データ入力!J40="","",請求データ入力!J40) | H39: =IF(請求データ入力!K40="","",請求データ入力!K40) | I39: =IF(請求データ入力!L40="","",請求データ入力!L40) | J39: =IF(請求データ入力!M40="","",請求データ入力!M40) | K39: =IF(請求データ入力!N40="","",請求データ入力!N40) | L39: =IF(請求データ入力!O40="","",請求データ入力!O40) | M39: =IF(請求データ入力!P40="","",請求データ入力!P40) | N39: =CONCATENATE(MID(E10,3,4),A39) -> 2602026
A40: 027 | B40: =IF(請求データ入力!C41="","",請求データ入力!C41) | C40: =IF(請求データ入力!D41="","",請求データ入力!D41) | D40: =IF(請求データ入力!E41="","",請求データ入力!E41) | E40: =IF(請求データ入力!H41="","",請求データ入力!H41) | F40: =IF(請求データ入力!I41="","",請求データ入力!I41) | G40: =IF(請求データ入力!J41="","",請求データ入力!J41) | H40: =IF(請求データ入力!K41="","",請求データ入力!K41) | I40: =IF(請求データ入力!L41="","",請求データ入力!L41) | J40: =IF(請求データ入力!M41="","",請求データ入力!M41) | K40: =IF(請求データ入力!N41="","",請求データ入力!N41) | L40: =IF(請求データ入力!O41="","",請求データ入力!O41) | M40: =IF(請求データ入力!P41="","",請求データ入力!P41) | N40: =CONCATENATE(MID(E10,3,4),A40) -> 2602027
A41: 028 | B41: =IF(請求データ入力!C42="","",請求データ入力!C42) | C41: =IF(請求データ入力!D42="","",請求データ入力!D42) | D41: =IF(請求データ入力!E42="","",請求データ入力!E42) | E41: =IF(請求データ入力!H42="","",請求データ入力!H42) | F41: =IF(請求データ入力!I42="","",請求データ入力!I42) | G41: =IF(請求データ入力!J42="","",請求データ入力!J42) | H41: =IF(請求データ入力!K42="","",請求データ入力!K42) | I41: =IF(請求データ入力!L42="","",請求データ入力!L42) | J41: =IF(請求データ入力!M42="","",請求データ入力!M42) | K41: =IF(請求データ入力!N42="","",請求データ入力!N42) | L41: =IF(請求データ入力!O42="","",請求データ入力!O42) | M41: =IF(請求データ入力!P42="","",請求データ入力!P42) | N41: =CONCATENATE(MID(E10,3,4),A41) -> 2602028
A42: 029 | B42: =IF(請求データ入力!C43="","",請求データ入力!C43) | C42: =IF(請求データ入力!D43="","",請求データ入力!D43) | D42: =IF(請求データ入力!E43="","",請求データ入力!E43) | E42: =IF(請求データ入力!H43="","",請求データ入力!H43) | F42: =IF(請求データ入力!I43="","",請求データ入力!I43) | G42: =IF(請求データ入力!J43="","",請求データ入力!J43) | H42: =IF(請求データ入力!K43="","",請求データ入力!K43) | I42: =IF(請求データ入力!L43="","",請求データ入力!L43) | J42: =IF(請求データ入力!M43="","",請求データ入力!M43) | K42: =IF(請求データ入力!N43="","",請求データ入力!N43) | L42: =IF(請求データ入力!O43="","",請求データ入力!O43) | M42: =IF(請求データ入力!P43="","",請求データ入力!P43) | N42: =CONCATENATE(MID(E10,3,4),A42) -> 2602029
A43: 030 | B43: =IF(請求データ入力!C44="","",請求データ入力!C44) | C43: =IF(請求データ入力!D44="","",請求データ入力!D44) | D43: =IF(請求データ入力!E44="","",請求データ入力!E44) | E43: =IF(請求データ入力!H44="","",請求データ入力!H44) | F43: =IF(請求データ入力!I44="","",請求データ入力!I44) | G43: =IF(請求データ入力!J44="","",請求データ入力!J44) | H43: =IF(請求データ入力!K44="","",請求データ入力!K44) | I43: =IF(請求データ入力!L44="","",請求データ入力!L44) | J43: =IF(請求データ入力!M44="","",請求データ入力!M44) | K43: =IF(請求データ入力!N44="","",請求データ入力!N44) | L43: =IF(請求データ入力!O44="","",請求データ入力!O44) | M43: =IF(請求データ入力!P44="","",請求データ入力!P44) | N43: =CONCATENATE(MID(E10,3,4),A43) -> 2602030
A44: 031 | B44: =IF(請求データ入力!C45="","",請求データ入力!C45) | C44: =IF(請求データ入力!D45="","",請求データ入力!D45) | D44: =IF(請求データ入力!E45="","",請求データ入力!E45) | E44: =IF(請求データ入力!H45="","",請求データ入力!H45) | F44: =IF(請求データ入力!I45="","",請求データ入力!I45) | G44: =IF(請求データ入力!J45="","",請求データ入力!J45) | H44: =IF(請求データ入力!K45="","",請求データ入力!K45) | I44: =IF(請求データ入力!L45="","",請求データ入力!L45) | J44: =IF(請求データ入力!M45="","",請求データ入力!M45) | K44: =IF(請求データ入力!N45="","",請求データ入力!N45) | L44: =IF(請求データ入力!O45="","",請求データ入力!O45) | M44: =IF(請求データ入力!P45="","",請求データ入力!P45) | N44: =CONCATENATE(MID(E10,3,4),A44) -> 2602031
A45: 032 | B45: =IF(請求データ入力!C46="","",請求データ入力!C46) | C45: =IF(請求データ入力!D46="","",請求データ入力!D46) | D45: =IF(請求データ入力!E46="","",請求データ入力!E46) | E45: =IF(請求データ入力!H46="","",請求データ入力!H46) | F45: =IF(請求データ入力!I46="","",請求データ入力!I46) | G45: =IF(請求データ入力!J46="","",請求データ入力!J46) | H45: =IF(請求データ入力!K46="","",請求データ入力!K46) | I45: =IF(請求データ入力!L46="","",請求データ入力!L46) | J45: =IF(請求データ入力!M46="","",請求データ入力!M46) | K45: =IF(請求データ入力!N46="","",請求データ入力!N46) | L45: =IF(請求データ入力!O46="","",請求データ入力!O46) | M45: =IF(請求データ入力!P46="","",請求データ入力!P46) | N45: =CONCATENATE(MID(E10,3,4),A45) -> 2602032
A46: 033 | B46: =IF(請求データ入力!C47="","",請求データ入力!C47) | C46: =IF(請求データ入力!D47="","",請求データ入力!D47) | D46: =IF(請求データ入力!E47="","",請求データ入力!E47) | E46: =IF(請求データ入力!H47="","",請求データ入力!H47) | F46: =IF(請求データ入力!I47="","",請求データ入力!I47) | G46: =IF(請求データ入力!J47="","",請求データ入力!J47) | H46: =IF(請求データ入力!K47="","",請求データ入力!K47) | I46: =IF(請求データ入力!L47="","",請求データ入力!L47) | J46: =IF(請求データ入力!M47="","",請求データ入力!M47) | K46: =IF(請求データ入力!N47="","",請求データ入力!N47) | L46: =IF(請求データ入力!O47="","",請求データ入力!O47) | M46: =IF(請求データ入力!P47="","",請求データ入力!P47) | N46: =CONCATENATE(MID(E10,3,4),A46) -> 2602033
A47: 034 | B47: =IF(請求データ入力!C48="","",請求データ入力!C48) | C47: =IF(請求データ入力!D48="","",請求データ入力!D48) | D47: =IF(請求データ入力!E48="","",請求データ入力!E48) | E47: =IF(請求データ入力!H48="","",請求データ入力!H48) | F47: =IF(請求データ入力!I48="","",請求データ入力!I48) | G47: =IF(請求データ入力!J48="","",請求データ入力!J48) | H47: =IF(請求データ入力!K48="","",請求データ入力!K48) | I47: =IF(請求データ入力!L48="","",請求データ入力!L48) | J47: =IF(請求データ入力!M48="","",請求データ入力!M48) | K47: =IF(請求データ入力!N48="","",請求データ入力!N48) | L47: =IF(請求データ入力!O48="","",請求データ入力!O48) | M47: =IF(請求データ入力!P48="","",請求データ入力!P48) | N47: =CONCATENATE(MID(E10,3,4),A47) -> 2602034
A48: 035 | B48: =IF(請求データ入力!C49="","",請求データ入力!C49) | C48: =IF(請求データ入力!D49="","",請求データ入力!D49) | D48: =IF(請求データ入力!E49="","",請求データ入力!E49) | E48: =IF(請求データ入力!H49="","",請求データ入力!H49) | F48: =IF(請求データ入力!I49="","",請求データ入力!I49) | G48: =IF(請求データ入力!J49="","",請求データ入力!J49) | H48: =IF(請求データ入力!K49="","",請求データ入力!K49) | I48: =IF(請求データ入力!L49="","",請求データ入力!L49) | J48: =IF(請求データ入力!M49="","",請求データ入力!M49) | K48: =IF(請求データ入力!N49="","",請求データ入力!N49) | L48: =IF(請求データ入力!O49="","",請求データ入力!O49) | M48: =IF(請求データ入力!P49="","",請求データ入力!P49) | N48: =CONCATENATE(MID(E10,3,4),A48) -> 2602035
A49: 036 | B49: =IF(請求データ入力!C50="","",請求データ入力!C50) | C49: =IF(請求データ入力!D50="","",請求データ入力!D50) | D49: =IF(請求データ入力!E50="","",請求データ入力!E50) | E49: =IF(請求データ入力!H50="","",請求データ入力!H50) | F49: =IF(請求データ入力!I50="","",請求データ入力!I50) | G49: =IF(請求データ入力!J50="","",請求データ入力!J50) | H49: =IF(請求データ入力!K50="","",請求データ入力!K50) | I49: =IF(請求データ入力!L50="","",請求データ入力!L50) | J49: =IF(請求データ入力!M50="","",請求データ入力!M50) | K49: =IF(請求データ入力!N50="","",請求データ入力!N50) | L49: =IF(請求データ入力!O50="","",請求データ入力!O50) | M49: =IF(請求データ入力!P50="","",請求データ入力!P50) | N49: =CONCATENATE(MID(E10,3,4),A49) -> 2602036
A50: 037 | B50: =IF(請求データ入力!C51="","",請求データ入力!C51) | C50: =IF(請求データ入力!D51="","",請求データ入力!D51) | D50: =IF(請求データ入力!E51="","",請求データ入力!E51) | E50: =IF(請求データ入力!H51="","",請求データ入力!H51) | F50: =IF(請求データ入力!I51="","",請求データ入力!I51) | G50: =IF(請求データ入力!J51="","",請求データ入力!J51) | H50: =IF(請求データ入力!K51="","",請求データ入力!K51) | I50: =IF(請求データ入力!L51="","",請求データ入力!L51) | J50: =IF(請求データ入力!M51="","",請求データ入力!M51) | K50: =IF(請求データ入力!N51="","",請求データ入力!N51) | L50: =IF(請求データ入力!O51="","",請求データ入力!O51) | M50: =IF(請求データ入力!P51="","",請求データ入力!P51) | N50: =CONCATENATE(MID(E10,3,4),A50) -> 2602037
A51: 038 | B51: =IF(請求データ入力!C52="","",請求データ入力!C52) | C51: =IF(請求データ入力!D52="","",請求データ入力!D52) | D51: =IF(請求データ入力!E52="","",請求データ入力!E52) | E51: =IF(請求データ入力!H52="","",請求データ入力!H52) | F51: =IF(請求データ入力!I52="","",請求データ入力!I52) | G51: =IF(請求データ入力!J52="","",請求データ入力!J52) | H51: =IF(請求データ入力!K52="","",請求データ入力!K52) | I51: =IF(請求データ入力!L52="","",請求データ入力!L52) | J51: =IF(請求データ入力!M52="","",請求データ入力!M52) | K51: =IF(請求データ入力!N52="","",請求データ入力!N52) | L51: =IF(請求データ入力!O52="","",請求データ入力!O52) | M51: =IF(請求データ入力!P52="","",請求データ入力!P52) | N51: =CONCATENATE(MID(E10,3,4),A51) -> 2602038
A52: 039 | B52: =IF(請求データ入力!C53="","",請求データ入力!C53) | C52: =IF(請求データ入力!D53="","",請求データ入力!D53) | D52: =IF(請求データ入力!E53="","",請求データ入力!E53) | E52: =IF(請求データ入力!H53="","",請求データ入力!H53) | F52: =IF(請求データ入力!I53="","",請求データ入力!I53) | G52: =IF(請求データ入力!J53="","",請求データ入力!J53) | H52: =IF(請求データ入力!K53="","",請求データ入力!K53) | I52: =IF(請求データ入力!L53="","",請求データ入力!L53) | J52: =IF(請求データ入力!M53="","",請求データ入力!M53) | K52: =IF(請求データ入力!N53="","",請求データ入力!N53) | L52: =IF(請求データ入力!O53="","",請求データ入力!O53) | M52: =IF(請求データ入力!P53="","",請求データ入力!P53) | N52: =CONCATENATE(MID(E10,3,4),A52) -> 2602039
A53: 040 | B53: =IF(請求データ入力!C54="","",請求データ入力!C54) | C53: =IF(請求データ入力!D54="","",請求データ入力!D54) | D53: =IF(請求データ入力!E54="","",請求データ入力!E54) | E53: =IF(請求データ入力!H54="","",請求データ入力!H54) | F53: =IF(請求データ入力!I54="","",請求データ入力!I54) | G53: =IF(請求データ入力!J54="","",請求データ入力!J54) | H53: =IF(請求データ入力!K54="","",請求データ入力!K54) | I53: =IF(請求データ入力!L54="","",請求データ入力!L54) | J53: =IF(請求データ入力!M54="","",請求データ入力!M54) | K53: =IF(請求データ入力!N54="","",請求データ入力!N54) | L53: =IF(請求データ入力!O54="","",請求データ入力!O54) | M53: =IF(請求データ入力!P54="","",請求データ入力!P54) | N53: =CONCATENATE(MID(E10,3,4),A53) -> 2602040
A54: 041 | B54: =IF(請求データ入力!C55="","",請求データ入力!C55) | C54: =IF(請求データ入力!D55="","",請求データ入力!D55) | D54: =IF(請求データ入力!E55="","",請求データ入力!E55) | E54: =IF(請求データ入力!H55="","",請求データ入力!H55) | F54: =IF(請求データ入力!I55="","",請求データ入力!I55) | G54: =IF(請求データ入力!J55="","",請求データ入力!J55) | H54: =IF(請求データ入力!K55="","",請求データ入力!K55) | I54: =IF(請求データ入力!L55="","",請求データ入力!L55) | J54: =IF(請求データ入力!M55="","",請求データ入力!M55) | K54: =IF(請求データ入力!N55="","",請求データ入力!N55) | L54: =IF(請求データ入力!O55="","",請求データ入力!O55) | M54: =IF(請求データ入力!P55="","",請求データ入力!P55) | N54: =CONCATENATE(MID(E10,3,4),A54) -> 2602041
A55: 042 | B55: =IF(請求データ入力!C56="","",請求データ入力!C56) | C55: =IF(請求データ入力!D56="","",請求データ入力!D56) | D55: =IF(請求データ入力!E56="","",請求データ入力!E56) | E55: =IF(請求データ入力!H56="","",請求データ入力!H56) | F55: =IF(請求データ入力!I56="","",請求データ入力!I56) | G55: =IF(請求データ入力!J56="","",請求データ入力!J56) | H55: =IF(請求データ入力!K56="","",請求データ入力!K56) | I55: =IF(請求データ入力!L56="","",請求データ入力!L56) | J55: =IF(請求データ入力!M56="","",請求データ入力!M56) | K55: =IF(請求データ入力!N56="","",請求データ入力!N56) | L55: =IF(請求データ入力!O56="","",請求データ入力!O56) | M55: =IF(請求データ入力!P56="","",請求データ入力!P56) | N55: =CONCATENATE(MID(E10,3,4),A55) -> 2602042
A56: 043 | B56: =IF(請求データ入力!C57="","",請求データ入力!C57) | C56: =IF(請求データ入力!D57="","",請求データ入力!D57) | D56: =IF(請求データ入力!E57="","",請求データ入力!E57) | E56: =IF(請求データ入力!H57="","",請求データ入力!H57) | F56: =IF(請求データ入力!I57="","",請求データ入力!I57) | G56: =IF(請求データ入力!J57="","",請求データ入力!J57) | H56: =IF(請求データ入力!K57="","",請求データ入力!K57) | I56: =IF(請求データ入力!L57="","",請求データ入力!L57) | J56: =IF(請求データ入力!M57="","",請求データ入力!M57) | K56: =IF(請求データ入力!N57="","",請求データ入力!N57) | L56: =IF(請求データ入力!O57="","",請求データ入力!O57) | M56: =IF(請求データ入力!P57="","",請求データ入力!P57) | N56: =CONCATENATE(MID(E10,3,4),A56) -> 2602043
A57: 044 | B57: =IF(請求データ入力!C58="","",請求データ入力!C58) | C57: =IF(請求データ入力!D58="","",請求データ入力!D58) | D57: =IF(請求データ入力!E58="","",請求データ入力!E58) | E57: =IF(請求データ入力!H58="","",請求データ入力!H58) | F57: =IF(請求データ入力!I58="","",請求データ入力!I58) | G57: =IF(請求データ入力!J58="","",請求データ入力!J58) | H57: =IF(請求データ入力!K58="","",請求データ入力!K58) | I57: =IF(請求データ入力!L58="","",請求データ入力!L58) | J57: =IF(請求データ入力!M58="","",請求データ入力!M58) | K57: =IF(請求データ入力!N58="","",請求データ入力!N58) | L57: =IF(請求データ入力!O58="","",請求データ入力!O58) | M57: =IF(請求データ入力!P58="","",請求データ入力!P58) | N57: =CONCATENATE(MID(E10,3,4),A57) -> 2602044
A58: 045 | B58: =IF(請求データ入力!C59="","",請求データ入力!C59) | C58: =IF(請求データ入力!D59="","",請求データ入力!D59) | D58: =IF(請求データ入力!E59="","",請求データ入力!E59) | E58: =IF(請求データ入力!H59="","",請求データ入力!H59) | F58: =IF(請求データ入力!I59="","",請求データ入力!I59) | G58: =IF(請求データ入力!J59="","",請求データ入力!J59) | H58: =IF(請求データ入力!K59="","",請求データ入力!K59) | I58: =IF(請求データ入力!L59="","",請求データ入力!L59) | J58: =IF(請求データ入力!M59="","",請求データ入力!M59) | K58: =IF(請求データ入力!N59="","",請求データ入力!N59) | L58: =IF(請求データ入力!O59="","",請求データ入力!O59) | M58: =IF(請求データ入力!P59="","",請求データ入力!P59) | N58: =CONCATENATE(MID(E10,3,4),A58) -> 2602045
A59: 046 | B59: =IF(請求データ入力!C60="","",請求データ入力!C60) | C59: =IF(請求データ入力!D60="","",請求データ入力!D60) | D59: =IF(請求データ入力!E60="","",請求データ入力!E60) | E59: =IF(請求データ入力!H60="","",請求データ入力!H60) | F59: =IF(請求データ入力!I60="","",請求データ入力!I60) | G59: =IF(請求データ入力!J60="","",請求データ入力!J60) | H59: =IF(請求データ入力!K60="","",請求データ入力!K60) | I59: =IF(請求データ入力!L60="","",請求データ入力!L60) | J59: =IF(請求データ入力!M60="","",請求データ入力!M60) | K59: =IF(請求データ入力!N60="","",請求データ入力!N60) | L59: =IF(請求データ入力!O60="","",請求データ入力!O60) | M59: =IF(請求データ入力!P60="","",請求データ入力!P60) | N59: =CONCATENATE(MID(E10,3,4),A59) -> 2602046
A60: 047 | B60: =IF(請求データ入力!C61="","",請求データ入力!C61) | C60: =IF(請求データ入力!D61="","",請求データ入力!D61) | D60: =IF(請求データ入力!E61="","",請求データ入力!E61) | E60: =IF(請求データ入力!H61="","",請求データ入力!H61) | F60: =IF(請求データ入力!I61="","",請求データ入力!I61) | G60: =IF(請求データ入力!J61="","",請求データ入力!J61) | H60: =IF(請求データ入力!K61="","",請求データ入力!K61) | I60: =IF(請求データ入力!L61="","",請求データ入力!L61) | J60: =IF(請求データ入力!M61="","",請求データ入力!M61) | K60: =IF(請求データ入力!N61="","",請求データ入力!N61) | L60: =IF(請求データ入力!O61="","",請求データ入力!O61) | M60: =IF(請求データ入力!P61="","",請求データ入力!P61) | N60: =CONCATENATE(MID(E10,3,4),A60) -> 2602047
A61: 048 | B61: =IF(請求データ入力!C62="","",請求データ入力!C62) | C61: =IF(請求データ入力!D62="","",請求データ入力!D62) | D61: =IF(請求データ入力!E62="","",請求データ入力!E62) | E61: =IF(請求データ入力!H62="","",請求データ入力!H62) | F61: =IF(請求データ入力!I62="","",請求データ入力!I62) | G61: =IF(請求データ入力!J62="","",請求データ入力!J62) | H61: =IF(請求データ入力!K62="","",請求データ入力!K62) | I61: =IF(請求データ入力!L62="","",請求データ入力!L62) | J61: =IF(請求データ入力!M62="","",請求データ入力!M62) | K61: =IF(請求データ入力!N62="","",請求データ入力!N62) | L61: =IF(請求データ入力!O62="","",請求データ入力!O62) | M61: =IF(請求データ入力!P62="","",請求データ入力!P62) | N61: =CONCATENATE(MID(E10,3,4),A61) -> 2602048
A62: 049 | B62: =IF(請求データ入力!C63="","",請求データ入力!C63) | C62: =IF(請求データ入力!D63="","",請求データ入力!D63) | D62: =IF(請求データ入力!E63="","",請求データ入力!E63) | E62: =IF(請求データ入力!H63="","",請求データ入力!H63) | F62: =IF(請求データ入力!I63="","",請求データ入力!I63) | G62: =IF(請求データ入力!J63="","",請求データ入力!J63) | H62: =IF(請求データ入力!K63="","",請求データ入力!K63) | I62: =IF(請求データ入力!L63="","",請求データ入力!L63) | J62: =IF(請求データ入力!M63="","",請求データ入力!M63) | K62: =IF(請求データ入力!N63="","",請求データ入力!N63) | L62: =IF(請求データ入力!O63="","",請求データ入力!O63) | M62: =IF(請求データ入力!P63="","",請求データ入力!P63) | N62: =CONCATENATE(MID(E10,3,4),A62) -> 2602049
A63: 050 | B63: =IF(請求データ入力!C64="","",請求データ入力!C64) | C63: =IF(請求データ入力!D64="","",請求データ入力!D64) | D63: =IF(請求データ入力!E64="","",請求データ入力!E64) | E63: =IF(請求データ入力!H64="","",請求データ入力!H64) | F63: =IF(請求データ入力!I64="","",請求データ入力!I64) | G63: =IF(請求データ入力!J64="","",請求データ入力!J64) | H63: =IF(請求データ入力!K64="","",請求データ入力!K64) | I63: =IF(請求データ入力!L64="","",請求データ入力!L64) | J63: =IF(請求データ入力!M64="","",請求データ入力!M64) | K63: =IF(請求データ入力!N64="","",請求データ入力!N64) | L63: =IF(請求データ入力!O64="","",請求データ入力!O64) | M63: =IF(請求データ入力!P64="","",請求データ入力!P64) | N63: =CONCATENATE(MID(E10,3,4),A63) -> 2602050
A64: 051 | B64: =IF(請求データ入力!C65="","",請求データ入力!C65) | C64: =IF(請求データ入力!D65="","",請求データ入力!D65) | D64: =IF(請求データ入力!E65="","",請求データ入力!E65) | E64: =IF(請求データ入力!H65="","",請求データ入力!H65) | F64: =IF(請求データ入力!I65="","",請求データ入力!I65) | G64: =IF(請求データ入力!J65="","",請求データ入力!J65) | H64: =IF(請求データ入力!K65="","",請求データ入力!K65) | I64: =IF(請求データ入力!L65="","",請求データ入力!L65) | J64: =IF(請求データ入力!M65="","",請求データ入力!M65) | K64: =IF(請求データ入力!N65="","",請求データ入力!N65) | L64: =IF(請求データ入力!O65="","",請求データ入力!O65) | M64: =IF(請求データ入力!P65="","",請求データ入力!P65) | N64: =CONCATENATE(MID(E10,3,4),A64) -> 2602051
A65: 052 | B65: =IF(請求データ入力!C66="","",請求データ入力!C66) | C65: =IF(請求データ入力!D66="","",請求データ入力!D66) | D65: =IF(請求データ入力!E66="","",請求データ入力!E66) | E65: =IF(請求データ入力!H66="","",請求データ入力!H66) | F65: =IF(請求データ入力!I66="","",請求データ入力!I66) | G65: =IF(請求データ入力!J66="","",請求データ入力!J66) | H65: =IF(請求データ入力!K66="","",請求データ入力!K66) | I65: =IF(請求データ入力!L66="","",請求データ入力!L66) | J65: =IF(請求データ入力!M66="","",請求データ入力!M66) | K65: =IF(請求データ入力!N66="","",請求データ入力!N66) | L65: =IF(請求データ入力!O66="","",請求データ入力!O66) | M65: =IF(請求データ入力!P66="","",請求データ入力!P66) | N65: =CONCATENATE(MID(E10,3,4),A65) -> 2602052
A66: 053 | B66: =IF(請求データ入力!C67="","",請求データ入力!C67) | C66: =IF(請求データ入力!D67="","",請求データ入力!D67) | D66: =IF(請求データ入力!E67="","",請求データ入力!E67) | E66: =IF(請求データ入力!H67="","",請求データ入力!H67) | F66: =IF(請求データ入力!I67="","",請求データ入力!I67) | G66: =IF(請求データ入力!J67="","",請求データ入力!J67) | H66: =IF(請求データ入力!K67="","",請求データ入力!K67) | I66: =IF(請求データ入力!L67="","",請求データ入力!L67) | J66: =IF(請求データ入力!M67="","",請求データ入力!M67) | K66: =IF(請求データ入力!N67="","",請求データ入力!N67) | L66: =IF(請求データ入力!O67="","",請求データ入力!O67) | M66: =IF(請求データ入力!P67="","",請求データ入力!P67) | N66: =CONCATENATE(MID(E10,3,4),A66) -> 2602053
A67: 054 | B67: =IF(請求データ入力!C68="","",請求データ入力!C68) | C67: =IF(請求データ入力!D68="","",請求データ入力!D68) | D67: =IF(請求データ入力!E68="","",請求データ入力!E68) | E67: =IF(請求データ入力!H68="","",請求データ入力!H68) | F67: =IF(請求データ入力!I68="","",請求データ入力!I68) | G67: =IF(請求データ入力!J68="","",請求データ入力!J68) | H67: =IF(請求データ入力!K68="","",請求データ入力!K68) | I67: =IF(請求データ入力!L68="","",請求データ入力!L68) | J67: =IF(請求データ入力!M68="","",請求データ入力!M68) | K67: =IF(請求データ入力!N68="","",請求データ入力!N68) | L67: =IF(請求データ入力!O68="","",請求データ入力!O68) | M67: =IF(請求データ入力!P68="","",請求データ入力!P68) | N67: =CONCATENATE(MID(E10,3,4),A67) -> 2602054
A68: 055 | B68: =IF(請求データ入力!C69="","",請求データ入力!C69) | C68: =IF(請求データ入力!D69="","",請求データ入力!D69) | D68: =IF(請求データ入力!E69="","",請求データ入力!E69) | E68: =IF(請求データ入力!H69="","",請求データ入力!H69) | F68: =IF(請求データ入力!I69="","",請求データ入力!I69) | G68: =IF(請求データ入力!J69="","",請求データ入力!J69) | H68: =IF(請求データ入力!K69="","",請求データ入力!K69) | I68: =IF(請求データ入力!L69="","",請求データ入力!L69) | J68: =IF(請求データ入力!M69="","",請求データ入力!M69) | K68: =IF(請求データ入力!N69="","",請求データ入力!N69) | L68: =IF(請求データ入力!O69="","",請求データ入力!O69) | M68: =IF(請求データ入力!P69="","",請求データ入力!P69) | N68: =CONCATENATE(MID(E10,3,4),A68) -> 2602055
A69: 056 | B69: =IF(請求データ入力!C70="","",請求データ入力!C70) | C69: =IF(請求データ入力!D70="","",請求データ入力!D70) | D69: =IF(請求データ入力!E70="","",請求データ入力!E70) | E69: =IF(請求データ入力!H70="","",請求データ入力!H70) | F69: =IF(請求データ入力!I70="","",請求データ入力!I70) | G69: =IF(請求データ入力!J70="","",請求データ入力!J70) | H69: =IF(請求データ入力!K70="","",請求データ入力!K70) | I69: =IF(請求データ入力!L70="","",請求データ入力!L70) | J69: =IF(請求データ入力!M70="","",請求データ入力!M70) | K69: =IF(請求データ入力!N70="","",請求データ入力!N70) | L69: =IF(請求データ入力!O70="","",請求データ入力!O70) | M69: =IF(請求データ入力!P70="","",請求データ入力!P70) | N69: =CONCATENATE(MID(E10,3,4),A69) -> 2602056
A70: 057 | B70: =IF(請求データ入力!C71="","",請求データ入力!C71) | C70: =IF(請求データ入力!D71="","",請求データ入力!D71) | D70: =IF(請求データ入力!E71="","",請求データ入力!E71) | E70: =IF(請求データ入力!H71="","",請求データ入力!H71) | F70: =IF(請求データ入力!I71="","",請求データ入力!I71) | G70: =IF(請求データ入力!J71="","",請求データ入力!J71) | H70: =IF(請求データ入力!K71="","",請求データ入力!K71) | I70: =IF(請求データ入力!L71="","",請求データ入力!L71) | J70: =IF(請求データ入力!M71="","",請求データ入力!M71) | K70: =IF(請求データ入力!N71="","",請求データ入力!N71) | L70: =IF(請求データ入力!O71="","",請求データ入力!O71) | M70: =IF(請求データ入力!P71="","",請求データ入力!P71) | N70: =CONCATENATE(MID(E10,3,4),A70) -> 2602057
A71: 058 | B71: =IF(請求データ入力!C72="","",請求データ入力!C72) | C71: =IF(請求データ入力!D72="","",請求データ入力!D72) | D71: =IF(請求データ入力!E72="","",請求データ入力!E72) | E71: =IF(請求データ入力!H72="","",請求データ入力!H72) | F71: =IF(請求データ入力!I72="","",請求データ入力!I72) | G71: =IF(請求データ入力!J72="","",請求データ入力!J72) | H71: =IF(請求データ入力!K72="","",請求データ入力!K72) | I71: =IF(請求データ入力!L72="","",請求データ入力!L72) | J71: =IF(請求データ入力!M72="","",請求データ入力!M72) | K71: =IF(請求データ入力!N72="","",請求データ入力!N72) | L71: =IF(請求データ入力!O72="","",請求データ入力!O72) | M71: =IF(請求データ入力!P72="","",請求データ入力!P72) | N71: =CONCATENATE(MID(E10,3,4),A71) -> 2602058
A72: 059 | B72: =IF(請求データ入力!C73="","",請求データ入力!C73) | C72: =IF(請求データ入力!D73="","",請求データ入力!D73) | D72: =IF(請求データ入力!E73="","",請求データ入力!E73) | E72: =IF(請求データ入力!H73="","",請求データ入力!H73) | F72: =IF(請求データ入力!I73="","",請求データ入力!I73) | G72: =IF(請求データ入力!J73="","",請求データ入力!J73) | H72: =IF(請求データ入力!K73="","",請求データ入力!K73) | I72: =IF(請求データ入力!L73="","",請求データ入力!L73) | J72: =IF(請求データ入力!M73="","",請求データ入力!M73) | K72: =IF(請求データ入力!N73="","",請求データ入力!N73) | L72: =IF(請求データ入力!O73="","",請求データ入力!O73) | M72: =IF(請求データ入力!P73="","",請求データ入力!P73) | N72: =CONCATENATE(MID(E10,3,4),A72) -> 2602059
A73: 060 | B73: =IF(請求データ入力!C74="","",請求データ入力!C74) | C73: =IF(請求データ入力!D74="","",請求データ入力!D74) | D73: =IF(請求データ入力!E74="","",請求データ入力!E74) | E73: =IF(請求データ入力!H74="","",請求データ入力!H74) | F73: =IF(請求データ入力!I74="","",請求データ入力!I74) | G73: =IF(請求データ入力!J74="","",請求データ入力!J74) | H73: =IF(請求データ入力!K74="","",請求データ入力!K74) | I73: =IF(請求データ入力!L74="","",請求データ入力!L74) | J73: =IF(請求データ入力!M74="","",請求データ入力!M74) | K73: =IF(請求データ入力!N74="","",請求データ入力!N74) | L73: =IF(請求データ入力!O74="","",請求データ入力!O74) | M73: =IF(請求データ入力!P74="","",請求データ入力!P74) | N73: =CONCATENATE(MID(E10,3,4),A73) -> 2602060
A74: 061 | B74: =IF(請求データ入力!C75="","",請求データ入力!C75) | C74: =IF(請求データ入力!D75="","",請求データ入力!D75) | D74: =IF(請求データ入力!E75="","",請求データ入力!E75) | E74: =IF(請求データ入力!H75="","",請求データ入力!H75) | F74: =IF(請求データ入力!I75="","",請求データ入力!I75) | G74: =IF(請求データ入力!J75="","",請求データ入力!J75) | H74: =IF(請求データ入力!K75="","",請求データ入力!K75) | I74: =IF(請求データ入力!L75="","",請求データ入力!L75) | J74: =IF(請求データ入力!M75="","",請求データ入力!M75) | K74: =IF(請求データ入力!N75="","",請求データ入力!N75) | L74: =IF(請求データ入力!O75="","",請求データ入力!O75) | M74: =IF(請求データ入力!P75="","",請求データ入力!P75) | N74: =CONCATENATE(MID(E10,3,4),A74) -> 2602061
A75: 062 | B75: =IF(請求データ入力!C76="","",請求データ入力!C76) | C75: =IF(請求データ入力!D76="","",請求データ入力!D76) | D75: =IF(請求データ入力!E76="","",請求データ入力!E76) | E75: =IF(請求データ入力!H76="","",請求データ入力!H76) | F75: =IF(請求データ入力!I76="","",請求データ入力!I76) | G75: =IF(請求データ入力!J76="","",請求データ入力!J76) | H75: =IF(請求データ入力!K76="","",請求データ入力!K76) | I75: =IF(請求データ入力!L76="","",請求データ入力!L76) | J75: =IF(請求データ入力!M76="","",請求データ入力!M76) | K75: =IF(請求データ入力!N76="","",請求データ入力!N76) | L75: =IF(請求データ入力!O76="","",請求データ入力!O76) | M75: =IF(請求データ入力!P76="","",請求データ入力!P76) | N75: =CONCATENATE(MID(E10,3,4),A75) -> 2602062
A76: 063 | B76: =IF(請求データ入力!C77="","",請求データ入力!C77) | C76: =IF(請求データ入力!D77="","",請求データ入力!D77) | D76: =IF(請求データ入力!E77="","",請求データ入力!E77) | E76: =IF(請求データ入力!H77="","",請求データ入力!H77) | F76: =IF(請求データ入力!I77="","",請求データ入力!I77) | G76: =IF(請求データ入力!J77="","",請求データ入力!J77) | H76: =IF(請求データ入力!K77="","",請求データ入力!K77) | I76: =IF(請求データ入力!L77="","",請求データ入力!L77) | J76: =IF(請求データ入力!M77="","",請求データ入力!M77) | K76: =IF(請求データ入力!N77="","",請求データ入力!N77) | L76: =IF(請求データ入力!O77="","",請求データ入力!O77) | M76: =IF(請求データ入力!P77="","",請求データ入力!P77) | N76: =CONCATENATE(MID(E10,3,4),A76) -> 2602063
A77: 064 | B77: =IF(請求データ入力!C78="","",請求データ入力!C78) | C77: =IF(請求データ入力!D78="","",請求データ入力!D78) | D77: =IF(請求データ入力!E78="","",請求データ入力!E78) | E77: =IF(請求データ入力!H78="","",請求データ入力!H78) | F77: =IF(請求データ入力!I78="","",請求データ入力!I78) | G77: =IF(請求データ入力!J78="","",請求データ入力!J78) | H77: =IF(請求データ入力!K78="","",請求データ入力!K78) | I77: =IF(請求データ入力!L78="","",請求データ入力!L78) | J77: =IF(請求データ入力!M78="","",請求データ入力!M78) | K77: =IF(請求データ入力!N78="","",請求データ入力!N78) | L77: =IF(請求データ入力!O78="","",請求データ入力!O78) | M77: =IF(請求データ入力!P78="","",請求データ入力!P78) | N77: =CONCATENATE(MID(E10,3,4),A77) -> 2602064
A78: 065 | B78: =IF(請求データ入力!C79="","",請求データ入力!C79) | C78: =IF(請求データ入力!D79="","",請求データ入力!D79) | D78: =IF(請求データ入力!E79="","",請求データ入力!E79) | E78: =IF(請求データ入力!H79="","",請求データ入力!H79) | F78: =IF(請求データ入力!I79="","",請求データ入力!I79) | G78: =IF(請求データ入力!J79="","",請求データ入力!J79) | H78: =IF(請求データ入力!K79="","",請求データ入力!K79) | I78: =IF(請求データ入力!L79="","",請求データ入力!L79) | J78: =IF(請求データ入力!M79="","",請求データ入力!M79) | K78: =IF(請求データ入力!N79="","",請求データ入力!N79) | L78: =IF(請求データ入力!O79="","",請求データ入力!O79) | M78: =IF(請求データ入力!P79="","",請求データ入力!P79) | N78: =CONCATENATE(MID(E10,3,4),A78) -> 2602065
A79: 066 | B79: =IF(請求データ入力!C80="","",請求データ入力!C80) | C79: =IF(請求データ入力!D80="","",請求データ入力!D80) | D79: =IF(請求データ入力!E80="","",請求データ入力!E80) | E79: =IF(請求データ入力!H80="","",請求データ入力!H80) | F79: =IF(請求データ入力!I80="","",請求データ入力!I80) | G79: =IF(請求データ入力!J80="","",請求データ入力!J80) | H79: =IF(請求データ入力!K80="","",請求データ入力!K80) | I79: =IF(請求データ入力!L80="","",請求データ入力!L80) | J79: =IF(請求データ入力!M80="","",請求データ入力!M80) | K79: =IF(請求データ入力!N80="","",請求データ入力!N80) | L79: =IF(請求データ入力!O80="","",請求データ入力!O80) | M79: =IF(請求データ入力!P80="","",請求データ入力!P80) | N79: =CONCATENATE(MID(E10,3,4),A79) -> 2602066
A80: 067 | B80: =IF(請求データ入力!C81="","",請求データ入力!C81) | C80: =IF(請求データ入力!D81="","",請求データ入力!D81) | D80: =IF(請求データ入力!E81="","",請求データ入力!E81) | E80: =IF(請求データ入力!H81="","",請求データ入力!H81) | F80: =IF(請求データ入力!I81="","",請求データ入力!I81) | G80: =IF(請求データ入力!J81="","",請求データ入力!J81) | H80: =IF(請求データ入力!K81="","",請求データ入力!K81) | I80: =IF(請求データ入力!L81="","",請求データ入力!L81) | J80: =IF(請求データ入力!M81="","",請求データ入力!M81) | K80: =IF(請求データ入力!N81="","",請求データ入力!N81) | L80: =IF(請求データ入力!O81="","",請求データ入力!O81) | M80: =IF(請求データ入力!P81="","",請求データ入力!P81) | N80: =CONCATENATE(MID(E10,3,4),A80) -> 2602067
A81: 068 | B81: =IF(請求データ入力!C82="","",請求データ入力!C82) | C81: =IF(請求データ入力!D82="","",請求データ入力!D82) | D81: =IF(請求データ入力!E82="","",請求データ入力!E82) | E81: =IF(請求データ入力!H82="","",請求データ入力!H82) | F81: =IF(請求データ入力!I82="","",請求データ入力!I82) | G81: =IF(請求データ入力!J82="","",請求データ入力!J82) | H81: =IF(請求データ入力!K82="","",請求データ入力!K82) | I81: =IF(請求データ入力!L82="","",請求データ入力!L82) | J81: =IF(請求データ入力!M82="","",請求データ入力!M82) | K81: =IF(請求データ入力!N82="","",請求データ入力!N82) | L81: =IF(請求データ入力!O82="","",請求データ入力!O82) | M81: =IF(請求データ入力!P82="","",請求データ入力!P82) | N81: =CONCATENATE(MID(E10,3,4),A81) -> 2602068
A82: 069 | B82: =IF(請求データ入力!C83="","",請求データ入力!C83) | C82: =IF(請求データ入力!D83="","",請求データ入力!D83) | D82: =IF(請求データ入力!E83="","",請求データ入力!E83) | E82: =IF(請求データ入力!H83="","",請求データ入力!H83) | F82: =IF(請求データ入力!I83="","",請求データ入力!I83) | G82: =IF(請求データ入力!J83="","",請求データ入力!J83) | H82: =IF(請求データ入力!K83="","",請求データ入力!K83) | I82: =IF(請求データ入力!L83="","",請求データ入力!L83) | J82: =IF(請求データ入力!M83="","",請求データ入力!M83) | K82: =IF(請求データ入力!N83="","",請求データ入力!N83) | L82: =IF(請求データ入力!O83="","",請求データ入力!O83) | M82: =IF(請求データ入力!P83="","",請求データ入力!P83) | N82: =CONCATENATE(MID(E10,3,4),A82) -> 2602069
A83: 070 | B83: =IF(請求データ入力!C84="","",請求データ入力!C84) | C83: =IF(請求データ入力!D84="","",請求データ入力!D84) | D83: =IF(請求データ入力!E84="","",請求データ入力!E84) | E83: =IF(請求データ入力!H84="","",請求データ入力!H84) | F83: =IF(請求データ入力!I84="","",請求データ入力!I84) | G83: =IF(請求データ入力!J84="","",請求データ入力!J84) | H83: =IF(請求データ入力!K84="","",請求データ入力!K84) | I83: =IF(請求データ入力!L84="","",請求データ入力!L84) | J83: =IF(請求データ入力!M84="","",請求データ入力!M84) | K83: =IF(請求データ入力!N84="","",請求データ入力!N84) | L83: =IF(請求データ入力!O84="","",請求データ入力!O84) | M83: =IF(請求データ入力!P84="","",請求データ入力!P84) | N83: =CONCATENATE(MID(E10,3,4),A83) -> 2602070
A84: 071 | B84: =IF(請求データ入力!C85="","",請求データ入力!C85) | C84: =IF(請求データ入力!D85="","",請求データ入力!D85) | D84: =IF(請求データ入力!E85="","",請求データ入力!E85) | E84: =IF(請求データ入力!H85="","",請求データ入力!H85) | F84: =IF(請求データ入力!I85="","",請求データ入力!I85) | G84: =IF(請求データ入力!J85="","",請求データ入力!J85) | H84: =IF(請求データ入力!K85="","",請求データ入力!K85) | I84: =IF(請求データ入力!L85="","",請求データ入力!L85) | J84: =IF(請求データ入力!M85="","",請求データ入力!M85) | K84: =IF(請求データ入力!N85="","",請求データ入力!N85) | L84: =IF(請求データ入力!O85="","",請求データ入力!O85) | M84: =IF(請求データ入力!P85="","",請求データ入力!P85) | N84: =CONCATENATE(MID(E10,3,4),A84) -> 2602071
A85: 072 | B85: =IF(請求データ入力!C86="","",請求データ入力!C86) | C85: =IF(請求データ入力!D86="","",請求データ入力!D86) | D85: =IF(請求データ入力!E86="","",請求データ入力!E86) | E85: =IF(請求データ入力!H86="","",請求データ入力!H86) | F85: =IF(請求データ入力!I86="","",請求データ入力!I86) | G85: =IF(請求データ入力!J86="","",請求データ入力!J86) | H85: =IF(請求データ入力!K86="","",請求データ入力!K86) | I85: =IF(請求データ入力!L86="","",請求データ入力!L86) | J85: =IF(請求データ入力!M86="","",請求データ入力!M86) | K85: =IF(請求データ入力!N86="","",請求データ入力!N86) | L85: =IF(請求データ入力!O86="","",請求データ入力!O86) | M85: =IF(請求データ入力!P86="","",請求データ入力!P86) | N85: =CONCATENATE(MID(E10,3,4),A85) -> 2602072
A86: 073 | B86: =IF(請求データ入力!C87="","",請求データ入力!C87) | C86: =IF(請求データ入力!D87="","",請求データ入力!D87) | D86: =IF(請求データ入力!E87="","",請求データ入力!E87) | E86: =IF(請求データ入力!H87="","",請求データ入力!H87) | F86: =IF(請求データ入力!I87="","",請求データ入力!I87) | G86: =IF(請求データ入力!J87="","",請求データ入力!J87) | H86: =IF(請求データ入力!K87="","",請求データ入力!K87) | I86: =IF(請求データ入力!L87="","",請求データ入力!L87) | J86: =IF(請求データ入力!M87="","",請求データ入力!M87) | K86: =IF(請求データ入力!N87="","",請求データ入力!N87) | L86: =IF(請求データ入力!O87="","",請求データ入力!O87) | M86: =IF(請求データ入力!P87="","",請求データ入力!P87) | N86: =CONCATENATE(MID(E10,3,4),A86) -> 2602073
A87: 074 | B87: =IF(請求データ入力!C88="","",請求データ入力!C88) | C87: =IF(請求データ入力!D88="","",請求データ入力!D88) | D87: =IF(請求データ入力!E88="","",請求データ入力!E88) | E87: =IF(請求データ入力!H88="","",請求データ入力!H88) | F87: =IF(請求データ入力!I88="","",請求データ入力!I88) | G87: =IF(請求データ入力!J88="","",請求データ入力!J88) | H87: =IF(請求データ入力!K88="","",請求データ入力!K88) | I87: =IF(請求データ入力!L88="","",請求データ入力!L88) | J87: =IF(請求データ入力!M88="","",請求データ入力!M88) | K87: =IF(請求データ入力!N88="","",請求データ入力!N88) | L87: =IF(請求データ入力!O88="","",請求データ入力!O88) | M87: =IF(請求データ入力!P88="","",請求データ入力!P88) | N87: =CONCATENATE(MID(E10,3,4),A87) -> 2602074
A88: 075 | B88: =IF(請求データ入力!C89="","",請求データ入力!C89) | C88: =IF(請求データ入力!D89="","",請求データ入力!D89) | D88: =IF(請求データ入力!E89="","",請求データ入力!E89) | E88: =IF(請求データ入力!H89="","",請求データ入力!H89) | F88: =IF(請求データ入力!I89="","",請求データ入力!I89) | G88: =IF(請求データ入力!J89="","",請求データ入力!J89) | H88: =IF(請求データ入力!K89="","",請求データ入力!K89) | I88: =IF(請求データ入力!L89="","",請求データ入力!L89) | J88: =IF(請求データ入力!M89="","",請求データ入力!M89) | K88: =IF(請求データ入力!N89="","",請求データ入力!N89) | L88: =IF(請求データ入力!O89="","",請求データ入力!O89) | M88: =IF(請求データ入力!P89="","",請求データ入力!P89) | N88: =CONCATENATE(MID(E10,3,4),A88) -> 2602075
A89: 076 | B89: =IF(請求データ入力!C90="","",請求データ入力!C90) | C89: =IF(請求データ入力!D90="","",請求データ入力!D90) | D89: =IF(請求データ入力!E90="","",請求データ入力!E90) | E89: =IF(請求データ入力!H90="","",請求データ入力!H90) | F89: =IF(請求データ入力!I90="","",請求データ入力!I90) | G89: =IF(請求データ入力!J90="","",請求データ入力!J90) | H89: =IF(請求データ入力!K90="","",請求データ入力!K90) | I89: =IF(請求データ入力!L90="","",請求データ入力!L90) | J89: =IF(請求データ入力!M90="","",請求データ入力!M90) | K89: =IF(請求データ入力!N90="","",請求データ入力!N90) | L89: =IF(請求データ入力!O90="","",請求データ入力!O90) | M89: =IF(請求データ入力!P90="","",請求データ入力!P90) | N89: =CONCATENATE(MID(E10,3,4),A89) -> 2602076
A90: 077 | B90: =IF(請求データ入力!C91="","",請求データ入力!C91) | C90: =IF(請求データ入力!D91="","",請求データ入力!D91) | D90: =IF(請求データ入力!E91="","",請求データ入力!E91) | E90: =IF(請求データ入力!H91="","",請求データ入力!H91) | F90: =IF(請求データ入力!I91="","",請求データ入力!I91) | G90: =IF(請求データ入力!J91="","",請求データ入力!J91) | H90: =IF(請求データ入力!K91="","",請求データ入力!K91) | I90: =IF(請求データ入力!L91="","",請求データ入力!L91) | J90: =IF(請求データ入力!M91="","",請求データ入力!M91) | K90: =IF(請求データ入力!N91="","",請求データ入力!N91) | L90: =IF(請求データ入力!O91="","",請求データ入力!O91) | M90: =IF(請求データ入力!P91="","",請求データ入力!P91) | N90: =CONCATENATE(MID(E10,3,4),A90) -> 2602077
A91: 078 | B91: =IF(請求データ入力!C92="","",請求データ入力!C92) | C91: =IF(請求データ入力!D92="","",請求データ入力!D92) | D91: =IF(請求データ入力!E92="","",請求データ入力!E92) | E91: =IF(請求データ入力!H92="","",請求データ入力!H92) | F91: =IF(請求データ入力!I92="","",請求データ入力!I92) | G91: =IF(請求データ入力!J92="","",請求データ入力!J92) | H91: =IF(請求データ入力!K92="","",請求データ入力!K92) | I91: =IF(請求データ入力!L92="","",請求データ入力!L92) | J91: =IF(請求データ入力!M92="","",請求データ入力!M92) | K91: =IF(請求データ入力!N92="","",請求データ入力!N92) | L91: =IF(請求データ入力!O92="","",請求データ入力!O92) | M91: =IF(請求データ入力!P92="","",請求データ入力!P92) | N91: =CONCATENATE(MID(E10,3,4),A91) -> 2602078
A92: 079 | B92: =IF(請求データ入力!C93="","",請求データ入力!C93) | C92: =IF(請求データ入力!D93="","",請求データ入力!D93) | D92: =IF(請求データ入力!E93="","",請求データ入力!E93) | E92: =IF(請求データ入力!H93="","",請求データ入力!H93) | F92: =IF(請求データ入力!I93="","",請求データ入力!I93) | G92: =IF(請求データ入力!J93="","",請求データ入力!J93) | H92: =IF(請求データ入力!K93="","",請求データ入力!K93) | I92: =IF(請求データ入力!L93="","",請求データ入力!L93) | J92: =IF(請求データ入力!M93="","",請求データ入力!M93) | K92: =IF(請求データ入力!N93="","",請求データ入力!N93) | L92: =IF(請求データ入力!O93="","",請求データ入力!O93) | M92: =IF(請求データ入力!P93="","",請求データ入力!P93) | N92: =CONCATENATE(MID(E10,3,4),A92) -> 2602079
A93: 080 | B93: =IF(請求データ入力!C94="","",請求データ入力!C94) | C93: =IF(請求データ入力!D94="","",請求データ入力!D94) | D93: =IF(請求データ入力!E94="","",請求データ入力!E94) | E93: =IF(請求データ入力!H94="","",請求データ入力!H94) | F93: =IF(請求データ入力!I94="","",請求データ入力!I94) | G93: =IF(請求データ入力!J94="","",請求データ入力!J94) | H93: =IF(請求データ入力!K94="","",請求データ入力!K94) | I93: =IF(請求データ入力!L94="","",請求データ入力!L94) | J93: =IF(請求データ入力!M94="","",請求データ入力!M94) | K93: =IF(請求データ入力!N94="","",請求データ入力!N94) | L93: =IF(請求データ入力!O94="","",請求データ入力!O94) | M93: =IF(請求データ入力!P94="","",請求データ入力!P94) | N93: =CONCATENATE(MID(E10,3,4),A93) -> 2602080
A94: 081 | B94: =IF(請求データ入力!C95="","",請求データ入力!C95) | C94: =IF(請求データ入力!D95="","",請求データ入力!D95) | D94: =IF(請求データ入力!E95="","",請求データ入力!E95) | E94: =IF(請求データ入力!H95="","",請求データ入力!H95) | F94: =IF(請求データ入力!I95="","",請求データ入力!I95) | G94: =IF(請求データ入力!J95="","",請求データ入力!J95) | H94: =IF(請求データ入力!K95="","",請求データ入力!K95) | I94: =IF(請求データ入力!L95="","",請求データ入力!L95) | J94: =IF(請求データ入力!M95="","",請求データ入力!M95) | K94: =IF(請求データ入力!N95="","",請求データ入力!N95) | L94: =IF(請求データ入力!O95="","",請求データ入力!O95) | M94: =IF(請求データ入力!P95="","",請求データ入力!P95) | N94: =CONCATENATE(MID(E10,3,4),A94) -> 2602081
A95: 082 | B95: =IF(請求データ入力!C96="","",請求データ入力!C96) | C95: =IF(請求データ入力!D96="","",請求データ入力!D96) | D95: =IF(請求データ入力!E96="","",請求データ入力!E96) | E95: =IF(請求データ入力!H96="","",請求データ入力!H96) | F95: =IF(請求データ入力!I96="","",請求データ入力!I96) | G95: =IF(請求データ入力!J96="","",請求データ入力!J96) | H95: =IF(請求データ入力!K96="","",請求データ入力!K96) | I95: =IF(請求データ入力!L96="","",請求データ入力!L96) | J95: =IF(請求データ入力!M96="","",請求データ入力!M96) | K95: =IF(請求データ入力!N96="","",請求データ入力!N96) | L95: =IF(請求データ入力!O96="","",請求データ入力!O96) | M95: =IF(請求データ入力!P96="","",請求データ入力!P96) | N95: =CONCATENATE(MID(E10,3,4),A95) -> 2602082
A96: 083 | B96: =IF(請求データ入力!C97="","",請求データ入力!C97) | C96: =IF(請求データ入力!D97="","",請求データ入力!D97) | D96: =IF(請求データ入力!E97="","",請求データ入力!E97) | E96: =IF(請求データ入力!H97="","",請求データ入力!H97) | F96: =IF(請求データ入力!I97="","",請求データ入力!I97) | G96: =IF(請求データ入力!J97="","",請求データ入力!J97) | H96: =IF(請求データ入力!K97="","",請求データ入力!K97) | I96: =IF(請求データ入力!L97="","",請求データ入力!L97) | J96: =IF(請求データ入力!M97="","",請求データ入力!M97) | K96: =IF(請求データ入力!N97="","",請求データ入力!N97) | L96: =IF(請求データ入力!O97="","",請求データ入力!O97) | M96: =IF(請求データ入力!P97="","",請求データ入力!P97) | N96: =CONCATENATE(MID(E10,3,4),A96) -> 2602083
A97: 084 | B97: =IF(請求データ入力!C98="","",請求データ入力!C98) | C97: =IF(請求データ入力!D98="","",請求データ入力!D98) | D97: =IF(請求データ入力!E98="","",請求データ入力!E98) | E97: =IF(請求データ入力!H98="","",請求データ入力!H98) | F97: =IF(請求データ入力!I98="","",請求データ入力!I98) | G97: =IF(請求データ入力!J98="","",請求データ入力!J98) | H97: =IF(請求データ入力!K98="","",請求データ入力!K98) | I97: =IF(請求データ入力!L98="","",請求データ入力!L98) | J97: =IF(請求データ入力!M98="","",請求データ入力!M98) | K97: =IF(請求データ入力!N98="","",請求データ入力!N98) | L97: =IF(請求データ入力!O98="","",請求データ入力!O98) | M97: =IF(請求データ入力!P98="","",請求データ入力!P98) | N97: =CONCATENATE(MID(E10,3,4),A97) -> 2602084
A98: 085 | B98: =IF(請求データ入力!C99="","",請求データ入力!C99) | C98: =IF(請求データ入力!D99="","",請求データ入力!D99) | D98: =IF(請求データ入力!E99="","",請求データ入力!E99) | E98: =IF(請求データ入力!H99="","",請求データ入力!H99) | F98: =IF(請求データ入力!I99="","",請求データ入力!I99) | G98: =IF(請求データ入力!J99="","",請求データ入力!J99) | H98: =IF(請求データ入力!K99="","",請求データ入力!K99) | I98: =IF(請求データ入力!L99="","",請求データ入力!L99) | J98: =IF(請求データ入力!M99="","",請求データ入力!M99) | K98: =IF(請求データ入力!N99="","",請求データ入力!N99) | L98: =IF(請求データ入力!O99="","",請求データ入力!O99) | M98: =IF(請求データ入力!P99="","",請求データ入力!P99) | N98: =CONCATENATE(MID(E10,3,4),A98) -> 2602085
A99: 086 | B99: =IF(請求データ入力!C100="","",請求データ入力!C100) | C99: =IF(請求データ入力!D100="","",請求データ入力!D100) | D99: =IF(請求データ入力!E100="","",請求データ入力!E100) | E99: =IF(請求データ入力!H100="","",請求データ入力!H100) | F99: =IF(請求データ入力!I100="","",請求データ入力!I100) | G99: =IF(請求データ入力!J100="","",請求データ入力!J100) | H99: =IF(請求データ入力!K100="","",請求データ入力!K100) | I99: =IF(請求データ入力!L100="","",請求データ入力!L100) | J99: =IF(請求データ入力!M100="","",請求データ入力!M100) | K99: =IF(請求データ入力!N100="","",請求データ入力!N100) | L99: =IF(請求データ入力!O100="","",請求データ入力!O100) | M99: =IF(請求データ入力!P100="","",請求データ入力!P100) | N99: =CONCATENATE(MID(E10,3,4),A99) -> 2602086
A100: 087 | B100: =IF(請求データ入力!C101="","",請求データ入力!C101) | C100: =IF(請求データ入力!D101="","",請求データ入力!D101) | D100: =IF(請求データ入力!E101="","",請求データ入力!E101) | E100: =IF(請求データ入力!H101="","",請求データ入力!H101) | F100: =IF(請求データ入力!I101="","",請求データ入力!I101) | G100: =IF(請求データ入力!J101="","",請求データ入力!J101) | H100: =IF(請求データ入力!K101="","",請求データ入力!K101) | I100: =IF(請求データ入力!L101="","",請求データ入力!L101) | J100: =IF(請求データ入力!M101="","",請求データ入力!M101) | K100: =IF(請求データ入力!N101="","",請求データ入力!N101) | L100: =IF(請求データ入力!O101="","",請求データ入力!O101) | M100: =IF(請求データ入力!P101="","",請求データ入力!P101) | N100: =CONCATENATE(MID(E10,3,4),A100) -> 2602087
A101: 088 | B101: =IF(請求データ入力!C102="","",請求データ入力!C102) | C101: =IF(請求データ入力!D102="","",請求データ入力!D102) | D101: =IF(請求データ入力!E102="","",請求データ入力!E102) | E101: =IF(請求データ入力!H102="","",請求データ入力!H102) | F101: =IF(請求データ入力!I102="","",請求データ入力!I102) | G101: =IF(請求データ入力!J102="","",請求データ入力!J102) | H101: =IF(請求データ入力!K102="","",請求データ入力!K102) | I101: =IF(請求データ入力!L102="","",請求データ入力!L102) | J101: =IF(請求データ入力!M102="","",請求データ入力!M102) | K101: =IF(請求データ入力!N102="","",請求データ入力!N102) | L101: =IF(請求データ入力!O102="","",請求データ入力!O102) | M101: =IF(請求データ入力!P102="","",請求データ入力!P102) | N101: =CONCATENATE(MID(E10,3,4),A101) -> 2602088
A102: 089 | B102: =IF(請求データ入力!C103="","",請求データ入力!C103) | C102: =IF(請求データ入力!D103="","",請求データ入力!D103) | D102: =IF(請求データ入力!E103="","",請求データ入力!E103) | E102: =IF(請求データ入力!H103="","",請求データ入力!H103) | F102: =IF(請求データ入力!I103="","",請求データ入力!I103) | G102: =IF(請求データ入力!J103="","",請求データ入力!J103) | H102: =IF(請求データ入力!K103="","",請求データ入力!K103) | I102: =IF(請求データ入力!L103="","",請求データ入力!L103) | J102: =IF(請求データ入力!M103="","",請求データ入力!M103) | K102: =IF(請求データ入力!N103="","",請求データ入力!N103) | L102: =IF(請求データ入力!O103="","",請求データ入力!O103) | M102: =IF(請求データ入力!P103="","",請求データ入力!P103) | N102: =CONCATENATE(MID(E10,3,4),A102) -> 2602089
A103: 090 | B103: =IF(請求データ入力!C104="","",請求データ入力!C104) | C103: =IF(請求データ入力!D104="","",請求データ入力!D104) | D103: =IF(請求データ入力!E104="","",請求データ入力!E104) | E103: =IF(請求データ入力!H104="","",請求データ入力!H104) | F103: =IF(請求データ入力!I104="","",請求データ入力!I104) | G103: =IF(請求データ入力!J104="","",請求データ入力!J104) | H103: =IF(請求データ入力!K104="","",請求データ入力!K104) | I103: =IF(請求データ入力!L104="","",請求データ入力!L104) | J103: =IF(請求データ入力!M104="","",請求データ入力!M104) | K103: =IF(請求データ入力!N104="","",請求データ入力!N104) | L103: =IF(請求データ入力!O104="","",請求データ入力!O104) | M103: =IF(請求データ入力!P104="","",請求データ入力!P104) | N103: =CONCATENATE(MID(E10,3,4),A103) -> 2602090
...

Sheet 個別001-010
B1: ② 納品書 （原価計算書） | P1: ㈱藤田建装 現場担当→課管理 | AA1: 備 考 | AM1: 301
E2: ◆ 内 容 | N2: ◆ 数 量 | R2: ◆ 単 価 | V2: ◆ 金 額 | AO2: 印刷範囲 | AP2: =IF(MAX($AP$5:$AP$19)=0,1,MAX($AP$5:$AP$19)) -> 248 | AQ2: 行目 | AR2: =IF(AP2=1,1,38) -> 38 | AS2: 列目まで印刷する
B3: =請求データ入力!J15 -> 明細書1参照 | N3: =請求データ入力!K15 -> 1 | P3: =請求データ入力!L15 -> 式 | R3: =請求データ入力!M15 -> 30000 | V3: =請求データ入力!N15 -> 30000
AA4: 差替No. | AO4: 伝票№連番 | AP4: 行数
AA5: 未請求No. | AO5: 001 | AP5: =IF(VLOOKUP(AO5,請求データ入力!$B$15:$P$114,9)=0,"",62) -> 62
AA6: 経理責任者 | AE6: 経理担当 | AI6: 現場担当 | AO6: 002 | AP6: =IF(VLOOKUP(AO6,請求データ入力!$B$15:$P$114,9)=0,"",124) -> 124
AO7: 003 | AP7: =IF(VLOOKUP(AO7,請求データ入力!$B$15:$P$114,9)=0,"",186) -> 186
AO8: 004 | AP8: =IF(VLOOKUP(AO8,請求データ入力!$B$15:$P$114,9)=0,"",248) -> 248
AO9: 005 | AP9: =IF(VLOOKUP(AO9,請求データ入力!$B$15:$P$114,9)=0,"",310)
B10: ◆取引先名/コード | G10: =請求データ入力!$K$2 -> 72130 | L10: 登録番号 | R10: ◆計（税抜） | AO10: 006 | AP10: =IF(VLOOKUP(AO10,請求データ入力!$B$15:$P$114,9)=0,"",372)
L11: =請求データ入力!$K$6 -> 0 | V11: =請求データ入力!N15 -> 30000
B12: =請求データ入力!$F$2 -> 〒110-0012 東京都台東区竜泉3-40-4 | R12: ◆消費税 | AO12: 007 | AP12: =IF(VLOOKUP(AO12,請求データ入力!$B$15:$P$114,9)=0,"",434)
R13: （切捨） | T13: =請求データ入力!$O$11 -> 0.1 | V13: =請求データ入力!O15 -> 3000
B14: =請求データ入力!$F$6 -> 有限会社木村左官工業 | R14: ◆税込合計金額 | AO14: 008 | AP14: =IF(VLOOKUP(AO14,請求データ入力!$B$15:$P$114,9)=0,"",496)
V15: =請求データ入力!P15 -> 33000 | AC15: 明細 （ 有 ・ 無 ）
R16: ◆取引先担当者 | V16: ◆完成納品年月日 | AC16: 検 算 | AI16: INPUT | AO16: 009 | AP16: =IF(VLOOKUP(AO16,請求データ入力!$B$15:$P$114,9)=0,"",558)
B17: ="TEL："&請求データ入力!$K$4 -> TEL：090-4609-2757 | R17: =請求データ入力!F15 -> 木村 正男 | V17: =CONCATENATE(請求データ入力!C15,"/",請求データ入力!D15,"/",請求データ入力!E15) -> 2026/2/28
B18: ◆工事コード/工事名 | R18: ◆藤田建装担当者 | AO18: 010 | AP18: =IF(VLOOKUP(AO18,請求データ入力!$B$15:$P$114,9)=0,"",620)
B19: =請求データ入力!H15 -> 2302-0258-02 | G19: =請求データ入力!I15 -> QB PREMIUM青葉台ﾓﾙﾀﾙ流出補償工事 | R19: =請求データ入力!G15 -> 石川 ほのか 様 | V19: T№ | W19: =請求データ入力!Q15 -> 2602001
B22: ③ 請求明細書 | P22: ㈱藤田建装 経理管理 | AA22: 備 考
E23: ◆ 内 容 | N23: ◆ 数 量 | R23: ◆ 単 価 | V23: ◆ 金 額
B24: =B3 -> 明細書1参照 | N24: =N3 -> 1 | P24: =P3 -> 式 | R24: =R3 -> 30000 | V24: =V3 -> 30000
AA25: 差替No.
AA26: 未請求No.
AA27: 経理責任者 | AE27: 経理担当 | AI27: 現場担当
B31: ◆取引先名/コード | G31: =請求データ入力!$K$2 -> 72130 | L31: 登録番号 | R31: ◆計（税抜）
L32: =請求データ入力!$K$6 -> 0 | V32: =V11 -> 30000
B33: =請求データ入力!$F$2 -> 〒110-0012 東京都台東区竜泉3-40-4 | R33: ◆消費税
R34: （切捨） | T34: =請求データ入力!$O$11 -> 0.1 | V34: =V13 -> 3000
B35: =請求データ入力!$F$6 -> 有限会社木村左官工業 | R35: ◆税込合計金額
V36: =V15 -> 33000 | AC36: 明細 （ 有 ・ 無 ）
R37: ◆取引先担当者 | V37: ◆完成納品年月日 | AC37: 検 算 | AI37: INPUT
B38: ="TEL："&請求データ入力!$K$4 -> TEL：090-4609-2757 | R38: =R17 -> 木村 正男 | V38: =V17 -> 2026/2/28
B39: ◆工事コード/工事名 | R39: ◆藤田建装担当者
B40: =B19 -> 2302-0258-02 | G40: =G19 -> QB PREMIUM青葉台ﾓﾙﾀﾙ流出補償工事 | R40: =R19 -> 石川 ほのか 様 | V40: T№ | W40: =W19 -> 2602001
B43: ④ 管理伝票 | P43: ㈱藤田建装 事業部管理 | AA43: 備 考
E44: ◆ 内 容 | N44: ◆ 数 量 | R44: ◆ 単 価 | V44: ◆ 金 額
B45: =B24 -> 明細書1参照 | N45: =N24 -> 1 | P45: =P24 -> 式 | R45: =R24 -> 30000 | V45: =V24 -> 30000
AA46: 差替No.
AA47: 未請求No.
AA48: 経理責任者 | AE48: 経理担当 | AI48: 現場担当
B52: ◆取引先名/コード | G52: =請求データ入力!$K$2 -> 72130 | L52: 登録番号 | R52: ◆計（税抜）
L53: =請求データ入力!$K$6 -> 0 | V53: =V32 -> 30000
B54: =請求データ入力!$F$2 -> 〒110-0012 東京都台東区竜泉3-40-4 | R54: ◆消費税
R55: （切捨） | T55: =請求データ入力!$O$11 -> 0.1 | V55: =V34 -> 3000
B56: =請求データ入力!$F$6 -> 有限会社木村左官工業 | R56: ◆税込合計金額
V57: =V36 -> 33000 | AC57: 明細 （ 有 ・ 無 ）
R58: ◆取引先担当者 | V58: ◆完成納品年月日 | AC58: 検 算 | AI58: INPUT
B59: ="TEL："&請求データ入力!$K$4 -> TEL：090-4609-2757 | R59: =R38 -> 木村 正男 | V59: =V38 -> 2026/2/28
B60: ◆工事コード/工事名 | R60: ◆藤田建装担当者
B61: =B40 -> 2302-0258-02 | G61: =G40 -> QB PREMIUM青葉台ﾓﾙﾀﾙ流出補償工事 | R61: =R40 -> 石川 ほのか 様 | V61: T№ | W61: =W40 -> 2602001
B63: ② 納品書 （原価計算書） | P63: ㈱藤田建装 現場担当→課管理 | AA63: 備 考 | AM63: 302
E64: ◆ 内 容 | N64: ◆ 数 量 | R64: ◆ 単 価 | V64: ◆ 金 額
B65: =請求データ入力!J16 -> 明細書2参照 | N65: =請求データ入力!K16 -> 1 | P65: =請求データ入力!L16 -> 式 | R65: =請求データ入力!M16 -> 60000 | V65: =請求データ入力!N16 -> 60000
AA66: 差替No.
AA67: 未請求No.
AA68: 経理責任者 | AE68: 経理担当 | AI68: 現場担当
B72: ◆取引先名/コード | G72: =請求データ入力!$K$2 -> 72130 | L72: 登録番号 | R72: ◆計（税抜）
L73: =請求データ入力!$K$6 -> 0 | V73: =請求データ入力!N16 -> 60000
B74: =請求データ入力!$F$2 -> 〒110-0012 東京都台東区竜泉3-40-4 | R74: ◆消費税
R75: （切捨） | T75: =請求データ入力!$O$11 -> 0.1 | V75: =請求データ入力!O16 -> 6000
B76: =請求データ入力!$F$6 -> 有限会社木村左官工業 | R76: ◆税込合計金額
V77: =請求データ入力!P16 -> 66000 | AC77: 明細 （ 有 ・ 無 ）
R78: ◆取引先担当者 | V78: ◆完成納品年月日 | AC78: 検 算 | AI78: INPUT
B79: ="TEL："&請求データ入力!$K$4 -> TEL：090-4609-2757 | R79: =請求データ入力!F16 -> 木村 正男 | V79: =CONCATENATE(請求データ入力!C16,"/",請求データ入力!D16,"/",請求データ入力!E16) -> 2026/2/28
B80: ◆工事コード/工事名 | R80: ◆藤田建装担当者
B81: =請求データ入力!H16 -> 2302-0258-03 | G81: =請求データ入力!I16 -> QB PREMIUM青葉台東急ｽｸｴｱ店子ﾌﾞﾚｰｶｰ交換工事 | R81: =請求データ入力!G16 -> 石川 ほのか 様 | V81: T№ | W81: =請求データ入力!Q16 -> 2602002
B84: ③ 請求明細書 | P84: ㈱藤田建装 経理管理 | AA84: 備 考
E85: ◆ 内 容 | N85: ◆ 数 量 | R85: ◆ 単 価 | V85: ◆ 金 額
B86: =B65 -> 明細書2参照 | N86: =N65 -> 1 | P86: =P65 -> 式 | R86: =R65 -> 60000 | V86: =V65 -> 60000
AA87: 差替No.
AA88: 未請求No.
AA89: 経理責任者 | AE89: 経理担当 | AI89: 現場担当
B93: ◆取引先名/コード | G93: =請求データ入力!$K$2 -> 72130 | L93: 登録番号 | R93: ◆計（税抜）
L94: =請求データ入力!$K$6 -> 0 | V94: =V73 -> 60000
B95: =請求データ入力!$F$2 -> 〒110-0012 東京都台東区竜泉3-40-4 | R95: ◆消費税
R96: （切捨） | T96: =請求データ入力!$O$11 -> 0.1 | V96: =V75 -> 6000
B97: =請求データ入力!$F$6 -> 有限会社木村左官工業 | R97: ◆税込合計金額
V98: =V77 -> 66000 | AC98: 明細 （ 有 ・ 無 ）
R99: ◆取引先担当者 | V99: ◆完成納品年月日 | AC99: 検 算 | AI99: INPUT
B100: ="TEL："&請求データ入力!$K$4 -> TEL：090-4609-2757 | R100: =R79 -> 木村 正男 | V100: =V79 -> 2026/2/28
B101: ◆工事コード/工事名 | R101: ◆藤田建装担当者
B102: =B81 -> 2302-0258-03 | G102: =G81 -> QB PREMIUM青葉台東急ｽｸｴｱ店子ﾌﾞﾚｰｶｰ交換工事 | R102: =R81 -> 石川 ほのか 様 | V102: T№ | W102: =W81 -> 2602002
B105: ④ 管理伝票 | P105: ㈱藤田建装 事業部管理 | AA105: 備 考
E106: ◆ 内 容 | N106: ◆ 数 量 | R106: ◆ 単 価 | V106: ◆ 金 額
B107: =B86 -> 明細書2参照 | N107: =N86 -> 1 | P107: =P86 -> 式 | R107: =R86 -> 60000 | V107: =V86 -> 60000
AA108: 差替No.
AA109: 未請求No.
AA110: 経理責任者 | AE110: 経理担当 | AI110: 現場担当
B114: ◆取引先名/コード | G114: =請求データ入力!$K$2 -> 72130 | L114: 登録番号 | R114: ◆計（税抜）
L115: =請求データ入力!$K$6 -> 0 | V115: =V94 -> 60000
B116: =請求データ入力!$F$2 -> 〒110-0012 東京都台東区竜泉3-40-4 | R116: ◆消費税
R117: （切捨） | T117: =請求データ入力!$O$11 -> 0.1 | V117: =V96 -> 6000
B118: =請求データ入力!$F$6 -> 有限会社木村左官工業 | R118: ◆税込合計金額
V119: =V98 -> 66000 | AC119: 明細 （ 有 ・ 無 ）
R120: ◆取引先担当者 | V120: ◆完成納品年月日 | AC120: 検 算 | AI120: INPUT
B121: ="TEL："&請求データ入力!$K$4 -> TEL：090-4609-2757 | R121: =R100 -> 木村 正男 | V121: =V100 -> 2026/2/28
B122: ◆工事コード/工事名 | R122: ◆藤田建装担当者
B123: =B102 -> 2302-0258-03 | G123: =G102 -> QB PREMIUM青葉台東急ｽｸｴｱ店子ﾌﾞﾚｰｶｰ交換工事 | R123: =R102 -> 石川 ほのか 様 | V123: T№ | W123: =W102 -> 2602002
B125: ② 納品書 （原価計算書） | P125: ㈱藤田建装 現場担当→課管理 | AA125: 備 考 | AM125: 303
...

Sheet 個別011-020
B1: ② 納品書 （原価計算書） | P1: ㈱藤田建装 現場担当→課管理 | AA1: 備 考 | AM1: 311
E2: ◆ 内 容 | N2: ◆ 数 量 | R2: ◆ 単 価 | V2: ◆ 金 額 | AO2: 印刷範囲 | AP2: =IF(MAX($AP$5:$AP$19)=0,1,MAX($AP$5:$AP$19)) -> 1 | AQ2: 行目 | AR2: =IF(AP2=1,1,38) -> 1 | AS2: 列目まで印刷する
B3: =請求データ入力!J25 -> 0 | N3: =請求データ入力!K25 -> 0 | P3: =請求データ入力!L25 -> 0 | R3: =請求データ入力!M25 -> 0 | V3: =請求データ入力!N25
AA4: 差替No. | AO4: 伝票№連番 | AP4: 行数
AA5: 未請求No. | AO5: 011 | AP5: =IF(VLOOKUP(AO5,請求データ入力!$B$15:$P$114,9)=0,"",62)
AA6: 経理責任者 | AE6: 経理担当 | AI6: 現場担当 | AO6: 012 | AP6: =IF(VLOOKUP(AO6,請求データ入力!$B$15:$P$114,9)=0,"",124)
AO7: 013 | AP7: =IF(VLOOKUP(AO7,請求データ入力!$B$15:$P$114,9)=0,"",186)
AO8: 014 | AP8: =IF(VLOOKUP(AO8,請求データ入力!$B$15:$P$114,9)=0,"",248)
AO9: 015 | AP9: =IF(VLOOKUP(AO9,請求データ入力!$B$15:$P$114,9)=0,"",310)
B10: ◆取引先名/コード | G10: =請求データ入力!$K$2 -> 72130 | L10: 登録番号 | R10: ◆計（税抜） | AO10: 016 | AP10: =IF(VLOOKUP(AO10,請求データ入力!$B$15:$P$114,9)=0,"",372)
L11: =請求データ入力!$K$6 -> 0 | V11: =請求データ入力!N25
B12: =請求データ入力!$F$2 -> 〒110-0012 東京都台東区竜泉3-40-4 | R12: ◆消費税 | AO12: 017 | AP12: =IF(VLOOKUP(AO12,請求データ入力!$B$15:$P$114,9)=0,"",434)
R13: （切捨） | T13: =請求データ入力!$O$11 -> 0.1 | V13: =請求データ入力!O25
B14: =請求データ入力!$F$6 -> 有限会社木村左官工業 | R14: ◆税込合計金額 | AO14: 018 | AP14: =IF(VLOOKUP(AO14,請求データ入力!$B$15:$P$114,9)=0,"",496)
V15: =請求データ入力!P25 | AC15: 明細 （ 有 ・ 無 ）
R16: ◆取引先担当者 | V16: ◆完成納品年月日 | AC16: 検 算 | AI16: INPUT | AO16: 019 | AP16: =IF(VLOOKUP(AO16,請求データ入力!$B$15:$P$114,9)=0,"",558)
B17: ="TEL："&請求データ入力!$K$4 -> TEL：090-4609-2757 | R17: =請求データ入力!F25 -> 0 | V17: =CONCATENATE(請求データ入力!C25,"/",請求データ入力!D25,"/",請求データ入力!E25) -> //
B18: ◆工事コード/工事名 | R18: ◆藤田建装担当者 | AO18: 020 | AP18: =IF(VLOOKUP(AO18,請求データ入力!$B$15:$P$114,9)=0,"",620)
B19: =請求データ入力!H25 -> 0 | G19: =請求データ入力!I25 -> 0 | R19: =請求データ入力!G25 -> 0 | V19: T№ | W19: =請求データ入力!Q25 -> 2602011
B22: ③ 請求明細書 | P22: ㈱藤田建装 経理管理 | AA22: 備 考
E23: ◆ 内 容 | N23: ◆ 数 量 | R23: ◆ 単 価 | V23: ◆ 金 額
B24: =B3 -> 0 | N24: =N3 -> 0 | P24: =P3 -> 0 | R24: =R3 -> 0 | V24: =V3
AA25: 差替No.
AA26: 未請求No.
AA27: 経理責任者 | AE27: 経理担当 | AI27: 現場担当
B31: ◆取引先名/コード | G31: =請求データ入力!$K$2 -> 72130 | L31: 登録番号 | R31: ◆計（税抜）
L32: =請求データ入力!$K$6 -> 0 | V32: =V11
B33: =請求データ入力!$F$2 -> 〒110-0012 東京都台東区竜泉3-40-4 | R33: ◆消費税
R34: （切捨） | T34: =請求データ入力!$O$11 -> 0.1 | V34: =V13
B35: =請求データ入力!$F$6 -> 有限会社木村左官工業 | R35: ◆税込合計金額
V36: =V15 | AC36: 明細 （ 有 ・ 無 ）
R37: ◆取引先担当者 | V37: ◆完成納品年月日 | AC37: 検 算 | AI37: INPUT
B38: ="TEL："&請求データ入力!$K$4 -> TEL：090-4609-2757 | R38: =R17 -> 0 | V38: =V17 -> //
B39: ◆工事コード/工事名 | R39: ◆藤田建装担当者
B40: =B19 -> 0 | G40: =G19 -> 0 | R40: =R19 -> 0 | V40: T№ | W40: =W19 -> 2602011
B43: ④ 管理伝票 | P43: ㈱藤田建装 事業部管理 | AA43: 備 考
E44: ◆ 内 容 | N44: ◆ 数 量 | R44: ◆ 単 価 | V44: ◆ 金 額
B45: =B24 -> 0 | N45: =N24 -> 0 | P45: =P24 -> 0 | R45: =R24 -> 0 | V45: =V24
AA46: 差替No.
AA47: 未請求No.
AA48: 経理責任者 | AE48: 経理担当 | AI48: 現場担当
B52: ◆取引先名/コード | G52: =請求データ入力!$K$2 -> 72130 | L52: 登録番号 | R52: ◆計（税抜）
L53: =請求データ入力!$K$6 -> 0 | V53: =V32
B54: =請求データ入力!$F$2 -> 〒110-0012 東京都台東区竜泉3-40-4 | R54: ◆消費税
R55: （切捨） | T55: =請求データ入力!$O$11 -> 0.1 | V55: =V34
B56: =請求データ入力!$F$6 -> 有限会社木村左官工業 | R56: ◆税込合計金額
V57: =V36 | AC57: 明細 （ 有 ・ 無 ）
R58: ◆取引先担当者 | V58: ◆完成納品年月日 | AC58: 検 算 | AI58: INPUT
B59: ="TEL："&請求データ入力!$K$4 -> TEL：090-4609-2757 | R59: =R38 -> 0 | V59: =V38 -> //
B60: ◆工事コード/工事名 | R60: ◆藤田建装担当者
B61: =B40 -> 0 | G61: =G40 -> 0 | R61: =R40 -> 0 | V61: T№ | W61: =W40 -> 2602011
B63: ② 納品書 （原価計算書） | P63: ㈱藤田建装 現場担当→課管理 | AA63: 備 考 | AM63: 312
E64: ◆ 内 容 | N64: ◆ 数 量 | R64: ◆ 単 価 | V64: ◆ 金 額
B65: =請求データ入力!J26 -> 0 | N65: =請求データ入力!K26 -> 0 | P65: =請求データ入力!L26 -> 0 | R65: =請求データ入力!M26 -> 0 | V65: =請求データ入力!N26
AA66: 差替No.
AA67: 未請求No.
AA68: 経理責任者 | AE68: 経理担当 | AI68: 現場担当
B72: ◆取引先名/コード | G72: =請求データ入力!$K$2 -> 72130 | L72: 登録番号 | R72: ◆計（税抜）
L73: =請求データ入力!$K$6 -> 0 | V73: =請求データ入力!N26
B74: =請求データ入力!$F$2 -> 〒110-0012 東京都台東区竜泉3-40-4 | R74: ◆消費税
R75: （切捨） | T75: =請求データ入力!$O$11 -> 0.1 | V75: =請求データ入力!O26
B76: =請求データ入力!$F$6 -> 有限会社木村左官工業 | R76: ◆税込合計金額
V77: =請求データ入力!P26 | AC77: 明細 （ 有 ・ 無 ）
R78: ◆取引先担当者 | V78: ◆完成納品年月日 | AC78: 検 算 | AI78: INPUT
B79: ="TEL："&請求データ入力!$K$4 -> TEL：090-4609-2757 | R79: =請求データ入力!F26 -> 0 | V79: =CONCATENATE(請求データ入力!C26,"/",請求データ入力!D26,"/",請求データ入力!E26) -> //
B80: ◆工事コード/工事名 | R80: ◆藤田建装担当者
B81: =請求データ入力!H26 -> 0 | G81: =請求データ入力!I26 -> 0 | R81: =請求データ入力!G26 -> 0 | V81: T№ | W81: =請求データ入力!Q26 -> 2602012
B84: ③ 請求明細書 | P84: ㈱藤田建装 経理管理 | AA84: 備 考
E85: ◆ 内 容 | N85: ◆ 数 量 | R85: ◆ 単 価 | V85: ◆ 金 額
B86: =B65 -> 0 | N86: =N65 -> 0 | P86: =P65 -> 0 | R86: =R65 -> 0 | V86: =V65
AA87: 差替No.
AA88: 未請求No.
AA89: 経理責任者 | AE89: 経理担当 | AI89: 現場担当
B93: ◆取引先名/コード | G93: =請求データ入力!$K$2 -> 72130 | L93: 登録番号 | R93: ◆計（税抜）
L94: =請求データ入力!$K$6 -> 0 | V94: =V73
B95: =請求データ入力!$F$2 -> 〒110-0012 東京都台東区竜泉3-40-4 | R95: ◆消費税
R96: （切捨） | T96: =請求データ入力!$O$11 -> 0.1 | V96: =V75
B97: =請求データ入力!$F$6 -> 有限会社木村左官工業 | R97: ◆税込合計金額
V98: =V77 | AC98: 明細 （ 有 ・ 無 ）
R99: ◆取引先担当者 | V99: ◆完成納品年月日 | AC99: 検 算 | AI99: INPUT
B100: ="TEL："&請求データ入力!$K$4 -> TEL：090-4609-2757 | R100: =R79 -> 0 | V100: =V79 -> //
B101: ◆工事コード/工事名 | R101: ◆藤田建装担当者
B102: =B81 -> 0 | G102: =G81 -> 0 | R102: =R81 -> 0 | V102: T№ | W102: =W81 -> 2602012
B105: ④ 管理伝票 | P105: ㈱藤田建装 事業部管理 | AA105: 備 考
E106: ◆ 内 容 | N106: ◆ 数 量 | R106: ◆ 単 価 | V106: ◆ 金 額
B107: =B86 -> 0 | N107: =N86 -> 0 | P107: =P86 -> 0 | R107: =R86 -> 0 | V107: =V86
AA108: 差替No.
AA109: 未請求No.
AA110: 経理責任者 | AE110: 経理担当 | AI110: 現場担当
B114: ◆取引先名/コード | G114: =請求データ入力!$K$2 -> 72130 | L114: 登録番号 | R114: ◆計（税抜）
L115: =請求データ入力!$K$6 -> 0 | V115: =V94
B116: =請求データ入力!$F$2 -> 〒110-0012 東京都台東区竜泉3-40-4 | R116: ◆消費税
R117: （切捨） | T117: =請求データ入力!$O$11 -> 0.1 | V117: =V96
B118: =請求データ入力!$F$6 -> 有限会社木村左官工業 | R118: ◆税込合計金額
V119: =V98 | AC119: 明細 （ 有 ・ 無 ）
R120: ◆取引先担当者 | V120: ◆完成納品年月日 | AC120: 検 算 | AI120: INPUT
B121: ="TEL："&請求データ入力!$K$4 -> TEL：090-4609-2757 | R121: =R100 -> 0 | V121: =V100 -> //
B122: ◆工事コード/工事名 | R122: ◆藤田建装担当者
B123: =B102 -> 0 | G123: =G102 -> 0 | R123: =R102 -> 0 | V123: T№ | W123: =W102 -> 2602012
B125: ② 納品書 （原価計算書） | P125: ㈱藤田建装 現場担当→課管理 | AA125: 備 考 | AM125: 313
...

Sheet 個別021-030
B1: ② 納品書 （原価計算書） | P1: ㈱藤田建装 現場担当→課管理 | AA1: 備 考 | AM1: 321
E2: ◆ 内 容 | N2: ◆ 数 量 | R2: ◆ 単 価 | V2: ◆ 金 額 | AO2: 印刷範囲 | AP2: =IF(MAX($AP$5:$AP$19)=0,1,MAX($AP$5:$AP$19)) -> 1 | AQ2: 行目 | AR2: =IF(AP2=1,1,38) -> 1 | AS2: 列目まで印刷する
B3: =請求データ入力!J35 -> 0 | N3: =請求データ入力!K35 -> 0 | P3: =請求データ入力!L35 -> 0 | R3: =請求データ入力!M35 -> 0 | V3: =請求データ入力!N35
AA4: 差替No. | AO4: 伝票№連番 | AP4: 行数
AA5: 未請求No. | AO5: 021 | AP5: =IF(VLOOKUP(AO5,請求データ入力!$B$15:$P$114,9)=0,"",62)
AA6: 経理責任者 | AE6: 経理担当 | AI6: 現場担当 | AO6: 022 | AP6: =IF(VLOOKUP(AO6,請求データ入力!$B$15:$P$114,9)=0,"",124)
AO7: 023 | AP7: =IF(VLOOKUP(AO7,請求データ入力!$B$15:$P$114,9)=0,"",186)
AO8: 024 | AP8: =IF(VLOOKUP(AO8,請求データ入力!$B$15:$P$114,9)=0,"",248)
AO9: 025 | AP9: =IF(VLOOKUP(AO9,請求データ入力!$B$15:$P$114,9)=0,"",310)
B10: ◆取引先名/コード | G10: =請求データ入力!$K$2 -> 72130 | L10: 登録番号 | R10: ◆計（税抜） | AO10: 026 | AP10: =IF(VLOOKUP(AO10,請求データ入力!$B$15:$P$114,9)=0,"",372)
L11: =請求データ入力!$K$6 -> 0 | V11: =請求データ入力!N35
B12: =請求データ入力!$F$2 -> 〒110-0012 東京都台東区竜泉3-40-4 | R12: ◆消費税 | AO12: 027 | AP12: =IF(VLOOKUP(AO12,請求データ入力!$B$15:$P$114,9)=0,"",434)
R13: （切捨） | T13: =請求データ入力!$O$11 -> 0.1 | V13: =請求データ入力!O35
B14: =請求データ入力!$F$6 -> 有限会社木村左官工業 | R14: ◆税込合計金額 | AO14: 028 | AP14: =IF(VLOOKUP(AO14,請求データ入力!$B$15:$P$114,9)=0,"",496)
V15: =請求データ入力!P35 | AC15: 明細 （ 有 ・ 無 ）
R16: ◆取引先担当者 | V16: ◆完成納品年月日 | AC16: 検 算 | AI16: INPUT | AO16: 029 | AP16: =IF(VLOOKUP(AO16,請求データ入力!$B$15:$P$114,9)=0,"",558)
B17: ="TEL："&請求データ入力!$K$4 -> TEL：090-4609-2757 | R17: =請求データ入力!F35 -> 0 | V17: =CONCATENATE(請求データ入力!C35,"/",請求データ入力!D35,"/",請求データ入力!E35) -> //
B18: ◆工事コード/工事名 | R18: ◆藤田建装担当者 | AO18: 030 | AP18: =IF(VLOOKUP(AO18,請求データ入力!$B$15:$P$114,9)=0,"",620)
B19: =請求データ入力!H35 -> 0 | G19: =請求データ入力!I35 -> 0 | R19: =請求データ入力!G35 -> 0 | V19: T№ | W19: =請求データ入力!Q35 -> 2602021
B22: ③ 請求明細書 | P22: ㈱藤田建装 経理管理 | AA22: 備 考
E23: ◆ 内 容 | N23: ◆ 数 量 | R23: ◆ 単 価 | V23: ◆ 金 額
B24: =B3 -> 0 | N24: =N3 -> 0 | P24: =P3 -> 0 | R24: =R3 -> 0 | V24: =V3
AA25: 差替No.
AA26: 未請求No.
AA27: 経理責任者 | AE27: 経理担当 | AI27: 現場担当
B31: ◆取引先名/コード | G31: =請求データ入力!$K$2 -> 72130 | L31: 登録番号 | R31: ◆計（税抜）
L32: =請求データ入力!$K$6 -> 0 | V32: =V11
B33: =請求データ入力!$F$2 -> 〒110-0012 東京都台東区竜泉3-40-4 | R33: ◆消費税
R34: （切捨） | T34: =請求データ入力!$O$11 -> 0.1 | V34: =V13
B35: =請求データ入力!$F$6 -> 有限会社木村左官工業 | R35: ◆税込合計金額
V36: =V15 | AC36: 明細 （ 有 ・ 無 ）
R37: ◆取引先担当者 | V37: ◆完成納品年月日 | AC37: 検 算 | AI37: INPUT
B38: ="TEL："&請求データ入力!$K$4 -> TEL：090-4609-2757 | R38: =R17 -> 0 | V38: =V17 -> //
B39: ◆工事コード/工事名 | R39: ◆藤田建装担当者
B40: =B19 -> 0 | G40: =G19 -> 0 | R40: =R19 -> 0 | V40: T№ | W40: =W19 -> 2602021
B43: ④ 管理伝票 | P43: ㈱藤田建装 事業部管理 | AA43: 備 考
E44: ◆ 内 容 | N44: ◆ 数 量 | R44: ◆ 単 価 | V44: ◆ 金 額
B45: =B24 -> 0 | N45: =N24 -> 0 | P45: =P24 -> 0 | R45: =R24 -> 0 | V45: =V24
AA46: 差替No.
AA47: 未請求No.
AA48: 経理責任者 | AE48: 経理担当 | AI48: 現場担当
B52: ◆取引先名/コード | G52: =請求データ入力!$K$2 -> 72130 | L52: 登録番号 | R52: ◆計（税抜）
L53: =請求データ入力!$K$6 -> 0 | V53: =V32
B54: =請求データ入力!$F$2 -> 〒110-0012 東京都台東区竜泉3-40-4 | R54: ◆消費税
R55: （切捨） | T55: =請求データ入力!$O$11 -> 0.1 | V55: =V34
B56: =請求データ入力!$F$6 -> 有限会社木村左官工業 | R56: ◆税込合計金額
V57: =V36 | AC57: 明細 （ 有 ・ 無 ）
R58: ◆取引先担当者 | V58: ◆完成納品年月日 | AC58: 検 算 | AI58: INPUT
B59: ="TEL："&請求データ入力!$K$4 -> TEL：090-4609-2757 | R59: =R38 -> 0 | V59: =V38 -> //
B60: ◆工事コード/工事名 | R60: ◆藤田建装担当者
B61: =B40 -> 0 | G61: =G40 -> 0 | R61: =R40 -> 0 | V61: T№ | W61: =W40 -> 2602021
B63: ② 納品書 （原価計算書） | P63: ㈱藤田建装 現場担当→課管理 | AA63: 備 考 | AM63: 322
E64: ◆ 内 容 | N64: ◆ 数 量 | R64: ◆ 単 価 | V64: ◆ 金 額
B65: =請求データ入力!J36 -> 0 | N65: =請求データ入力!K36 -> 0 | P65: =請求データ入力!L36 -> 0 | R65: =請求データ入力!M36 -> 0 | V65: =請求データ入力!N36
AA66: 差替No.
AA67: 未請求No.
AA68: 経理責任者 | AE68: 経理担当 | AI68: 現場担当
B72: ◆取引先名/コード | G72: =請求データ入力!$K$2 -> 72130 | L72: 登録番号 | R72: ◆計（税抜）
L73: =請求データ入力!$K$6 -> 0 | V73: =請求データ入力!N36
B74: =請求データ入力!$F$2 -> 〒110-0012 東京都台東区竜泉3-40-4 | R74: ◆消費税
R75: （切捨） | T75: =請求データ入力!$O$11 -> 0.1 | V75: =請求データ入力!O36
B76: =請求データ入力!$F$6 -> 有限会社木村左官工業 | R76: ◆税込合計金額
V77: =請求データ入力!P36 | AC77: 明細 （ 有 ・ 無 ）
R78: ◆取引先担当者 | V78: ◆完成納品年月日 | AC78: 検 算 | AI78: INPUT
B79: ="TEL："&請求データ入力!$K$4 -> TEL：090-4609-2757 | R79: =請求データ入力!F36 -> 0 | V79: =CONCATENATE(請求データ入力!C36,"/",請求データ入力!D36,"/",請求データ入力!E36) -> //
B80: ◆工事コード/工事名 | R80: ◆藤田建装担当者
B81: =請求データ入力!H36 -> 0 | G81: =請求データ入力!I36 -> 0 | R81: =請求データ入力!G36 -> 0 | V81: T№ | W81: =請求データ入力!Q36 -> 2602022
B84: ③ 請求明細書 | P84: ㈱藤田建装 経理管理 | AA84: 備 考
E85: ◆ 内 容 | N85: ◆ 数 量 | R85: ◆ 単 価 | V85: ◆ 金 額
B86: =B65 -> 0 | N86: =N65 -> 0 | P86: =P65 -> 0 | R86: =R65 -> 0 | V86: =V65
AA87: 差替No.
AA88: 未請求No.
AA89: 経理責任者 | AE89: 経理担当 | AI89: 現場担当
B93: ◆取引先名/コード | G93: =請求データ入力!$K$2 -> 72130 | L93: 登録番号 | R93: ◆計（税抜）
L94: =請求データ入力!$K$6 -> 0 | V94: =V73
B95: =請求データ入力!$F$2 -> 〒110-0012 東京都台東区竜泉3-40-4 | R95: ◆消費税
R96: （切捨） | T96: =請求データ入力!$O$11 -> 0.1 | V96: =V75
B97: =請求データ入力!$F$6 -> 有限会社木村左官工業 | R97: ◆税込合計金額
V98: =V77 | AC98: 明細 （ 有 ・ 無 ）
R99: ◆取引先担当者 | V99: ◆完成納品年月日 | AC99: 検 算 | AI99: INPUT
B100: ="TEL："&請求データ入力!$K$4 -> TEL：090-4609-2757 | R100: =R79 -> 0 | V100: =V79 -> //
B101: ◆工事コード/工事名 | R101: ◆藤田建装担当者
B102: =B81 -> 0 | G102: =G81 -> 0 | R102: =R81 -> 0 | V102: T№ | W102: =W81 -> 2602022
B105: ④ 管理伝票 | P105: ㈱藤田建装 事業部管理 | AA105: 備 考
E106: ◆ 内 容 | N106: ◆ 数 量 | R106: ◆ 単 価 | V106: ◆ 金 額
B107: =B86 -> 0 | N107: =N86 -> 0 | P107: =P86 -> 0 | R107: =R86 -> 0 | V107: =V86
AA108: 差替No.
AA109: 未請求No.
AA110: 経理責任者 | AE110: 経理担当 | AI110: 現場担当
B114: ◆取引先名/コード | G114: =請求データ入力!$K$2 -> 72130 | L114: 登録番号 | R114: ◆計（税抜）
L115: =請求データ入力!$K$6 -> 0 | V115: =V94
B116: =請求データ入力!$F$2 -> 〒110-0012 東京都台東区竜泉3-40-4 | R116: ◆消費税
R117: （切捨） | T117: =請求データ入力!$O$11 -> 0.1 | V117: =V96
B118: =請求データ入力!$F$6 -> 有限会社木村左官工業 | R118: ◆税込合計金額
V119: =V98 | AC119: 明細 （ 有 ・ 無 ）
R120: ◆取引先担当者 | V120: ◆完成納品年月日 | AC120: 検 算 | AI120: INPUT
B121: ="TEL："&請求データ入力!$K$4 -> TEL：090-4609-2757 | R121: =R100 -> 0 | V121: =V100 -> //
B122: ◆工事コード/工事名 | R122: ◆藤田建装担当者
B123: =B102 -> 0 | G123: =G102 -> 0 | R123: =R102 -> 0 | V123: T№ | W123: =W102 -> 2602022
B125: ② 納品書 （原価計算書） | P125: ㈱藤田建装 現場担当→課管理 | AA125: 備 考 | AM125: 323
...

Sheet 個別031-040
B1: ② 納品書 （原価計算書） | P1: ㈱藤田建装 現場担当→課管理 | AA1: 備 考 | AM1: 331
E2: ◆ 内 容 | N2: ◆ 数 量 | R2: ◆ 単 価 | V2: ◆ 金 額 | AO2: 印刷範囲 | AP2: =IF(MAX($AP$5:$AP$19)=0,1,MAX($AP$5:$AP$19)) -> 1 | AQ2: 行目 | AR2: =IF(AP2=1,1,38) -> 1 | AS2: 列目まで印刷する
B3: =請求データ入力!J45 -> 0 | N3: =請求データ入力!K45 -> 0 | P3: =請求データ入力!L45 -> 0 | R3: =請求データ入力!M45 -> 0 | V3: =請求データ入力!N45
AA4: 差替No. | AO4: 伝票№連番 | AP4: 行数
AA5: 未請求No. | AO5: 031 | AP5: =IF(VLOOKUP(AO5,請求データ入力!$B$15:$P$114,9)=0,"",62)
AA6: 経理責任者 | AE6: 経理担当 | AI6: 現場担当 | AO6: 032 | AP6: =IF(VLOOKUP(AO6,請求データ入力!$B$15:$P$114,9)=0,"",124)
AO7: 033 | AP7: =IF(VLOOKUP(AO7,請求データ入力!$B$15:$P$114,9)=0,"",186)
AO8: 034 | AP8: =IF(VLOOKUP(AO8,請求データ入力!$B$15:$P$114,9)=0,"",248)
AO9: 035 | AP9: =IF(VLOOKUP(AO9,請求データ入力!$B$15:$P$114,9)=0,"",310)
B10: ◆取引先名/コード | G10: =請求データ入力!$K$2 -> 72130 | L10: 登録番号 | R10: ◆計（税抜） | AO10: 036 | AP10: =IF(VLOOKUP(AO10,請求データ入力!$B$15:$P$114,9)=0,"",372)
L11: =請求データ入力!$K$6 -> 0 | V11: =請求データ入力!N45
B12: =請求データ入力!$F$2 -> 〒110-0012 東京都台東区竜泉3-40-4 | R12: ◆消費税 | AO12: 037 | AP12: =IF(VLOOKUP(AO12,請求データ入力!$B$15:$P$114,9)=0,"",434)
R13: （切捨） | T13: =請求データ入力!$O$11 -> 0.1 | V13: =請求データ入力!O45
B14: =請求データ入力!$F$6 -> 有限会社木村左官工業 | R14: ◆税込合計金額 | AO14: 038 | AP14: =IF(VLOOKUP(AO14,請求データ入力!$B$15:$P$114,9)=0,"",496)
V15: =請求データ入力!P45 | AC15: 明細 （ 有 ・ 無 ）
R16: ◆取引先担当者 | V16: ◆完成納品年月日 | AC16: 検 算 | AI16: INPUT | AO16: 039 | AP16: =IF(VLOOKUP(AO16,請求データ入力!$B$15:$P$114,9)=0,"",558)
B17: ="TEL："&請求データ入力!$K$4 -> TEL：090-4609-2757 | R17: =請求データ入力!F45 -> 0 | V17: =CONCATENATE(請求データ入力!C45,"/",請求データ入力!D45,"/",請求データ入力!E45) -> //
B18: ◆工事コード/工事名 | R18: ◆藤田建装担当者 | AO18: 040 | AP18: =IF(VLOOKUP(AO18,請求データ入力!$B$15:$P$114,9)=0,"",620)
B19: =請求データ入力!H45 -> 0 | G19: =請求データ入力!I45 -> 0 | R19: =請求データ入力!G45 -> 0 | V19: T№ | W19: =請求データ入力!Q45 -> 2602031
B22: ③ 請求明細書 | P22: ㈱藤田建装 経理管理 | AA22: 備 考
E23: ◆ 内 容 | N23: ◆ 数 量 | R23: ◆ 単 価 | V23: ◆ 金 額
B24: =B3 -> 0 | N24: =N3 -> 0 | P24: =P3 -> 0 | R24: =R3 -> 0 | V24: =V3
AA25: 差替No.
AA26: 未請求No.
AA27: 経理責任者 | AE27: 経理担当 | AI27: 現場担当
B31: ◆取引先名/コード | G31: =請求データ入力!$K$2 -> 72130 | L31: 登録番号 | R31: ◆計（税抜）
L32: =請求データ入力!$K$6 -> 0 | V32: =V11
B33: =請求データ入力!$F$2 -> 〒110-0012 東京都台東区竜泉3-40-4 | R33: ◆消費税
R34: （切捨） | T34: =請求データ入力!$O$11 -> 0.1 | V34: =V13
B35: =請求データ入力!$F$6 -> 有限会社木村左官工業 | R35: ◆税込合計金額
V36: =V15 | AC36: 明細 （ 有 ・ 無 ）
R37: ◆取引先担当者 | V37: ◆完成納品年月日 | AC37: 検 算 | AI37: INPUT
B38: ="TEL："&請求データ入力!$K$4 -> TEL：090-4609-2757 | R38: =R17 -> 0 | V38: =V17 -> //
B39: ◆工事コード/工事名 | R39: ◆藤田建装担当者
B40: =B19 -> 0 | G40: =G19 -> 0 | R40: =R19 -> 0 | V40: T№ | W40: =W19 -> 2602031
B43: ④ 管理伝票 | P43: ㈱藤田建装 事業部管理 | AA43: 備 考
E44: ◆ 内 容 | N44: ◆ 数 量 | R44: ◆ 単 価 | V44: ◆ 金 額
B45: =B24 -> 0 | N45: =N24 -> 0 | P45: =P24 -> 0 | R45: =R24 -> 0 | V45: =V24
AA46: 差替No.
AA47: 未請求No.
AA48: 経理責任者 | AE48: 経理担当 | AI48: 現場担当
B52: ◆取引先名/コード | G52: =請求データ入力!$K$2 -> 72130 | L52: 登録番号 | R52: ◆計（税抜）
L53: =請求データ入力!$K$6 -> 0 | V53: =V32
B54: =請求データ入力!$F$2 -> 〒110-0012 東京都台東区竜泉3-40-4 | R54: ◆消費税
R55: （切捨） | T55: =請求データ入力!$O$11 -> 0.1 | V55: =V34
B56: =請求データ入力!$F$6 -> 有限会社木村左官工業 | R56: ◆税込合計金額
V57: =V36 | AC57: 明細 （ 有 ・ 無 ）
R58: ◆取引先担当者 | V58: ◆完成納品年月日 | AC58: 検 算 | AI58: INPUT
B59: ="TEL："&請求データ入力!$K$4 -> TEL：090-4609-2757 | R59: =R38 -> 0 | V59: =V38 -> //
B60: ◆工事コード/工事名 | R60: ◆藤田建装担当者
B61: =B40 -> 0 | G61: =G40 -> 0 | R61: =R40 -> 0 | V61: T№ | W61: =W40 -> 2602031
B63: ② 納品書 （原価計算書） | P63: ㈱藤田建装 現場担当→課管理 | AA63: 備 考 | AM63: 332
E64: ◆ 内 容 | N64: ◆ 数 量 | R64: ◆ 単 価 | V64: ◆ 金 額
B65: =請求データ入力!J46 -> 0 | N65: =請求データ入力!K46 -> 0 | P65: =請求データ入力!L46 -> 0 | R65: =請求データ入力!M46 -> 0 | V65: =請求データ入力!N46
AA66: 差替No.
AA67: 未請求No.
AA68: 経理責任者 | AE68: 経理担当 | AI68: 現場担当
B72: ◆取引先名/コード | G72: =請求データ入力!$K$2 -> 72130 | L72: 登録番号 | R72: ◆計（税抜）
L73: =請求データ入力!$K$6 -> 0 | V73: =請求データ入力!N46
B74: =請求データ入力!$F$2 -> 〒110-0012 東京都台東区竜泉3-40-4 | R74: ◆消費税
R75: （切捨） | T75: =請求データ入力!$O$11 -> 0.1 | V75: =請求データ入力!O46
B76: =請求データ入力!$F$6 -> 有限会社木村左官工業 | R76: ◆税込合計金額
V77: =請求データ入力!P46 | AC77: 明細 （ 有 ・ 無 ）
R78: ◆取引先担当者 | V78: ◆完成納品年月日 | AC78: 検 算 | AI78: INPUT
B79: ="TEL："&請求データ入力!$K$4 -> TEL：090-4609-2757 | R79: =請求データ入力!F46 -> 0 | V79: =CONCATENATE(請求データ入力!C46,"/",請求データ入力!D46,"/",請求データ入力!E46) -> //
B80: ◆工事コード/工事名 | R80: ◆藤田建装担当者
B81: =請求データ入力!H46 -> 0 | G81: =請求データ入力!I46 -> 0 | R81: =請求データ入力!G46 -> 0 | V81: T№ | W81: =請求データ入力!Q46 -> 2602032
B84: ③ 請求明細書 | P84: ㈱藤田建装 経理管理 | AA84: 備 考
E85: ◆ 内 容 | N85: ◆ 数 量 | R85: ◆ 単 価 | V85: ◆ 金 額
B86: =B65 -> 0 | N86: =N65 -> 0 | P86: =P65 -> 0 | R86: =R65 -> 0 | V86: =V65
AA87: 差替No.
AA88: 未請求No.
AA89: 経理責任者 | AE89: 経理担当 | AI89: 現場担当
B93: ◆取引先名/コード | G93: =請求データ入力!$K$2 -> 72130 | L93: 登録番号 | R93: ◆計（税抜）
L94: =請求データ入力!$K$6 -> 0 | V94: =V73
B95: =請求データ入力!$F$2 -> 〒110-0012 東京都台東区竜泉3-40-4 | R95: ◆消費税
R96: （切捨） | T96: =請求データ入力!$O$11 -> 0.1 | V96: =V75
B97: =請求データ入力!$F$6 -> 有限会社木村左官工業 | R97: ◆税込合計金額
V98: =V77 | AC98: 明細 （ 有 ・ 無 ）
R99: ◆取引先担当者 | V99: ◆完成納品年月日 | AC99: 検 算 | AI99: INPUT
B100: ="TEL："&請求データ入力!$K$4 -> TEL：090-4609-2757 | R100: =R79 -> 0 | V100: =V79 -> //
B101: ◆工事コード/工事名 | R101: ◆藤田建装担当者
B102: =B81 -> 0 | G102: =G81 -> 0 | R102: =R81 -> 0 | V102: T№ | W102: =W81 -> 2602032
B105: ④ 管理伝票 | P105: ㈱藤田建装 事業部管理 | AA105: 備 考
E106: ◆ 内 容 | N106: ◆ 数 量 | R106: ◆ 単 価 | V106: ◆ 金 額
B107: =B86 -> 0 | N107: =N86 -> 0 | P107: =P86 -> 0 | R107: =R86 -> 0 | V107: =V86
AA108: 差替No.
AA109: 未請求No.
AA110: 経理責任者 | AE110: 経理担当 | AI110: 現場担当
B114: ◆取引先名/コード | G114: =請求データ入力!$K$2 -> 72130 | L114: 登録番号 | R114: ◆計（税抜）
L115: =請求データ入力!$K$6 -> 0 | V115: =V94
B116: =請求データ入力!$F$2 -> 〒110-0012 東京都台東区竜泉3-40-4 | R116: ◆消費税
R117: （切捨） | T117: =請求データ入力!$O$11 -> 0.1 | V117: =V96
B118: =請求データ入力!$F$6 -> 有限会社木村左官工業 | R118: ◆税込合計金額
V119: =V98 | AC119: 明細 （ 有 ・ 無 ）
R120: ◆取引先担当者 | V120: ◆完成納品年月日 | AC120: 検 算 | AI120: INPUT
B121: ="TEL："&請求データ入力!$K$4 -> TEL：090-4609-2757 | R121: =R100 -> 0 | V121: =V100 -> //
B122: ◆工事コード/工事名 | R122: ◆藤田建装担当者
B123: =B102 -> 0 | G123: =G102 -> 0 | R123: =R102 -> 0 | V123: T№ | W123: =W102 -> 2602032
B125: ② 納品書 （原価計算書） | P125: ㈱藤田建装 現場担当→課管理 | AA125: 備 考 | AM125: 333
...

Sheet 個別041-050
B1: ② 納品書 （原価計算書） | P1: ㈱藤田建装 現場担当→課管理 | AA1: 備 考 | AM1: 341
E2: ◆ 内 容 | N2: ◆ 数 量 | R2: ◆ 単 価 | V2: ◆ 金 額 | AO2: 印刷範囲 | AP2: =IF(MAX($AP$5:$AP$19)=0,1,MAX($AP$5:$AP$19)) -> 1 | AQ2: 行目 | AR2: =IF(AP2=1,1,38) -> 1 | AS2: 列目まで印刷する
B3: =請求データ入力!J55 -> 0 | N3: =請求データ入力!K55 -> 0 | P3: =請求データ入力!L55 -> 0 | R3: =請求データ入力!M55 -> 0 | V3: =請求データ入力!N55
AA4: 差替No. | AO4: 伝票№連番 | AP4: 行数
AA5: 未請求No. | AO5: 041 | AP5: =IF(VLOOKUP(AO5,請求データ入力!$B$15:$P$114,9)=0,"",62)
AA6: 経理責任者 | AE6: 経理担当 | AI6: 現場担当 | AO6: 042 | AP6: =IF(VLOOKUP(AO6,請求データ入力!$B$15:$P$114,9)=0,"",124)
AO7: 043 | AP7: =IF(VLOOKUP(AO7,請求データ入力!$B$15:$P$114,9)=0,"",186)
AO8: 044 | AP8: =IF(VLOOKUP(AO8,請求データ入力!$B$15:$P$114,9)=0,"",248)
AO9: 045 | AP9: =IF(VLOOKUP(AO9,請求データ入力!$B$15:$P$114,9)=0,"",310)
B10: ◆取引先名/コード | G10: =請求データ入力!$K$2 -> 72130 | L10: 登録番号 | R10: ◆計（税抜） | AO10: 046 | AP10: =IF(VLOOKUP(AO10,請求データ入力!$B$15:$P$114,9)=0,"",372)
L11: =請求データ入力!$K$6 -> 0 | V11: =請求データ入力!N55
B12: =請求データ入力!$F$2 -> 〒110-0012 東京都台東区竜泉3-40-4 | R12: ◆消費税 | AO12: 047 | AP12: =IF(VLOOKUP(AO12,請求データ入力!$B$15:$P$114,9)=0,"",434)
R13: （切捨） | T13: =請求データ入力!$O$11 -> 0.1 | V13: =請求データ入力!O55
B14: =請求データ入力!$F$6 -> 有限会社木村左官工業 | R14: ◆税込合計金額 | AO14: 048 | AP14: =IF(VLOOKUP(AO14,請求データ入力!$B$15:$P$114,9)=0,"",496)
V15: =請求データ入力!P55 | AC15: 明細 （ 有 ・ 無 ）
R16: ◆取引先担当者 | V16: ◆完成納品年月日 | AC16: 検 算 | AI16: INPUT | AO16: 049 | AP16: =IF(VLOOKUP(AO16,請求データ入力!$B$15:$P$114,9)=0,"",558)
B17: ="TEL："&請求データ入力!$K$4 -> TEL：090-4609-2757 | R17: =請求データ入力!F55 -> 0 | V17: =CONCATENATE(請求データ入力!C55,"/",請求データ入力!D55,"/",請求データ入力!E55) -> //
B18: ◆工事コード/工事名 | R18: ◆藤田建装担当者 | AO18: 050 | AP18: =IF(VLOOKUP(AO18,請求データ入力!$B$15:$P$114,9)=0,"",620)
B19: =請求データ入力!H55 -> 0 | G19: =請求データ入力!I55 -> 0 | R19: =請求データ入力!G55 -> 0 | V19: T№ | W19: =請求データ入力!Q55 -> 2602041
B22: ③ 請求明細書 | P22: ㈱藤田建装 経理管理 | AA22: 備 考
E23: ◆ 内 容 | N23: ◆ 数 量 | R23: ◆ 単 価 | V23: ◆ 金 額
B24: =B3 -> 0 | N24: =N3 -> 0 | P24: =P3 -> 0 | R24: =R3 -> 0 | V24: =V3
AA25: 差替No.
AA26: 未請求No.
AA27: 経理責任者 | AE27: 経理担当 | AI27: 現場担当
B31: ◆取引先名/コード | G31: =請求データ入力!$K$2 -> 72130 | L31: 登録番号 | R31: ◆計（税抜）
L32: =請求データ入力!$K$6 -> 0 | V32: =V11
B33: =請求データ入力!$F$2 -> 〒110-0012 東京都台東区竜泉3-40-4 | R33: ◆消費税
R34: （切捨） | T34: =請求データ入力!$O$11 -> 0.1 | V34: =V13
B35: =請求データ入力!$F$6 -> 有限会社木村左官工業 | R35: ◆税込合計金額
V36: =V15 | AC36: 明細 （ 有 ・ 無 ）
R37: ◆取引先担当者 | V37: ◆完成納品年月日 | AC37: 検 算 | AI37: INPUT
B38: ="TEL："&請求データ入力!$K$4 -> TEL：090-4609-2757 | R38: =R17 -> 0 | V38: =V17 -> //
B39: ◆工事コード/工事名 | R39: ◆藤田建装担当者
B40: =B19 -> 0 | G40: =G19 -> 0 | R40: =R19 -> 0 | V40: T№ | W40: =W19 -> 2602041
B43: ④ 管理伝票 | P43: ㈱藤田建装 事業部管理 | AA43: 備 考
E44: ◆ 内 容 | N44: ◆ 数 量 | R44: ◆ 単 価 | V44: ◆ 金 額
B45: =B24 -> 0 | N45: =N24 -> 0 | P45: =P24 -> 0 | R45: =R24 -> 0 | V45: =V24
AA46: 差替No.
AA47: 未請求No.
AA48: 経理責任者 | AE48: 経理担当 | AI48: 現場担当
B52: ◆取引先名/コード | G52: =請求データ入力!$K$2 -> 72130 | L52: 登録番号 | R52: ◆計（税抜）
L53: =請求データ入力!$K$6 -> 0 | V53: =V32
B54: =請求データ入力!$F$2 -> 〒110-0012 東京都台東区竜泉3-40-4 | R54: ◆消費税
R55: （切捨） | T55: =請求データ入力!$O$11 -> 0.1 | V55: =V34
B56: =請求データ入力!$F$6 -> 有限会社木村左官工業 | R56: ◆税込合計金額
V57: =V36 | AC57: 明細 （ 有 ・ 無 ）
R58: ◆取引先担当者 | V58: ◆完成納品年月日 | AC58: 検 算 | AI58: INPUT
B59: ="TEL："&請求データ入力!$K$4 -> TEL：090-4609-2757 | R59: =R38 -> 0 | V59: =V38 -> //
B60: ◆工事コード/工事名 | R60: ◆藤田建装担当者
B61: =B40 -> 0 | G61: =G40 -> 0 | R61: =R40 -> 0 | V61: T№ | W61: =W40 -> 2602041
B63: ② 納品書 （原価計算書） | P63: ㈱藤田建装 現場担当→課管理 | AA63: 備 考 | AM63: 342
E64: ◆ 内 容 | N64: ◆ 数 量 | R64: ◆ 単 価 | V64: ◆ 金 額
B65: =請求データ入力!J56 -> 0 | N65: =請求データ入力!K56 -> 0 | P65: =請求データ入力!L56 -> 0 | R65: =請求データ入力!M56 -> 0 | V65: =請求データ入力!N56
AA66: 差替No.
AA67: 未請求No.
AA68: 経理責任者 | AE68: 経理担当 | AI68: 現場担当
B72: ◆取引先名/コード | G72: =請求データ入力!$K$2 -> 72130 | L72: 登録番号 | R72: ◆計（税抜）
L73: =請求データ入力!$K$6 -> 0 | V73: =請求データ入力!N56
B74: =請求データ入力!$F$2 -> 〒110-0012 東京都台東区竜泉3-40-4 | R74: ◆消費税
R75: （切捨） | T75: =請求データ入力!$O$11 -> 0.1 | V75: =請求データ入力!O56
B76: =請求データ入力!$F$6 -> 有限会社木村左官工業 | R76: ◆税込合計金額
V77: =請求データ入力!P56 | AC77: 明細 （ 有 ・ 無 ）
R78: ◆取引先担当者 | V78: ◆完成納品年月日 | AC78: 検 算 | AI78: INPUT
B79: ="TEL："&請求データ入力!$K$4 -> TEL：090-4609-2757 | R79: =請求データ入力!F56 -> 0 | V79: =CONCATENATE(請求データ入力!C56,"/",請求データ入力!D56,"/",請求データ入力!E56) -> //
B80: ◆工事コード/工事名 | R80: ◆藤田建装担当者
B81: =請求データ入力!H56 -> 0 | G81: =請求データ入力!I56 -> 0 | R81: =請求データ入力!G56 -> 0 | V81: T№ | W81: =請求データ入力!Q56 -> 2602042
B84: ③ 請求明細書 | P84: ㈱藤田建装 経理管理 | AA84: 備 考
E85: ◆ 内 容 | N85: ◆ 数 量 | R85: ◆ 単 価 | V85: ◆ 金 額
B86: =B65 -> 0 | N86: =N65 -> 0 | P86: =P65 -> 0 | R86: =R65 -> 0 | V86: =V65
AA87: 差替No.
AA88: 未請求No.
AA89: 経理責任者 | AE89: 経理担当 | AI89: 現場担当
B93: ◆取引先名/コード | G93: =請求データ入力!$K$2 -> 72130 | L93: 登録番号 | R93: ◆計（税抜）
L94: =請求データ入力!$K$6 -> 0 | V94: =V73
B95: =請求データ入力!$F$2 -> 〒110-0012 東京都台東区竜泉3-40-4 | R95: ◆消費税
R96: （切捨） | T96: =請求データ入力!$O$11 -> 0.1 | V96: =V75
B97: =請求データ入力!$F$6 -> 有限会社木村左官工業 | R97: ◆税込合計金額
V98: =V77 | AC98: 明細 （ 有 ・ 無 ）
R99: ◆取引先担当者 | V99: ◆完成納品年月日 | AC99: 検 算 | AI99: INPUT
B100: ="TEL："&請求データ入力!$K$4 -> TEL：090-4609-2757 | R100: =R79 -> 0 | V100: =V79 -> //
B101: ◆工事コード/工事名 | R101: ◆藤田建装担当者
B102: =B81 -> 0 | G102: =G81 -> 0 | R102: =R81 -> 0 | V102: T№ | W102: =W81 -> 2602042
B105: ④ 管理伝票 | P105: ㈱藤田建装 事業部管理 | AA105: 備 考
E106: ◆ 内 容 | N106: ◆ 数 量 | R106: ◆ 単 価 | V106: ◆ 金 額
B107: =B86 -> 0 | N107: =N86 -> 0 | P107: =P86 -> 0 | R107: =R86 -> 0 | V107: =V86
AA108: 差替No.
AA109: 未請求No.
AA110: 経理責任者 | AE110: 経理担当 | AI110: 現場担当
B114: ◆取引先名/コード | G114: =請求データ入力!$K$2 -> 72130 | L114: 登録番号 | R114: ◆計（税抜）
L115: =請求データ入力!$K$6 -> 0 | V115: =V94
B116: =請求データ入力!$F$2 -> 〒110-0012 東京都台東区竜泉3-40-4 | R116: ◆消費税
R117: （切捨） | T117: =請求データ入力!$O$11 -> 0.1 | V117: =V96
B118: =請求データ入力!$F$6 -> 有限会社木村左官工業 | R118: ◆税込合計金額
V119: =V98 | AC119: 明細 （ 有 ・ 無 ）
R120: ◆取引先担当者 | V120: ◆完成納品年月日 | AC120: 検 算 | AI120: INPUT
B121: ="TEL："&請求データ入力!$K$4 -> TEL：090-4609-2757 | R121: =R100 -> 0 | V121: =V100 -> //
B122: ◆工事コード/工事名 | R122: ◆藤田建装担当者
B123: =B102 -> 0 | G123: =G102 -> 0 | R123: =R102 -> 0 | V123: T№ | W123: =W102 -> 2602042
B125: ② 納品書 （原価計算書） | P125: ㈱藤田建装 現場担当→課管理 | AA125: 備 考 | AM125: 343
...

Sheet 個別051-060
B1: ② 納品書 （原価計算書） | P1: ㈱藤田建装 現場担当→課管理 | AA1: 備 考 | AM1: 351
E2: ◆ 内 容 | N2: ◆ 数 量 | R2: ◆ 単 価 | V2: ◆ 金 額 | AO2: 印刷範囲 | AP2: =IF(MAX($AP$5:$AP$19)=0,1,MAX($AP$5:$AP$19)) -> 1 | AQ2: 行目 | AR2: =IF(AP2=1,1,38) -> 1 | AS2: 列目まで印刷する
B3: =請求データ入力!J65 -> 0 | N3: =請求データ入力!K65 -> 0 | P3: =請求データ入力!L65 -> 0 | R3: =請求データ入力!M65 -> 0 | V3: =請求データ入力!N65
AA4: 差替No. | AO4: 伝票№連番 | AP4: 行数
AA5: 未請求No. | AO5: 051 | AP5: =IF(VLOOKUP(AO5,請求データ入力!$B$15:$P$114,9)=0,"",62)
AA6: 経理責任者 | AE6: 経理担当 | AI6: 現場担当 | AO6: 052 | AP6: =IF(VLOOKUP(AO6,請求データ入力!$B$15:$P$114,9)=0,"",124)
AO7: 053 | AP7: =IF(VLOOKUP(AO7,請求データ入力!$B$15:$P$114,9)=0,"",186)
AO8: 054 | AP8: =IF(VLOOKUP(AO8,請求データ入力!$B$15:$P$114,9)=0,"",248)
AO9: 055 | AP9: =IF(VLOOKUP(AO9,請求データ入力!$B$15:$P$114,9)=0,"",310)
B10: ◆取引先名/コード | G10: =請求データ入力!$K$2 -> 72130 | L10: 登録番号 | R10: ◆計（税抜） | AO10: 056 | AP10: =IF(VLOOKUP(AO10,請求データ入力!$B$15:$P$114,9)=0,"",372)
L11: =請求データ入力!$K$6 -> 0 | V11: =請求データ入力!N65
B12: =請求データ入力!$F$2 -> 〒110-0012 東京都台東区竜泉3-40-4 | R12: ◆消費税 | AO12: 057 | AP12: =IF(VLOOKUP(AO12,請求データ入力!$B$15:$P$114,9)=0,"",434)
R13: （切捨） | T13: =請求データ入力!$O$11 -> 0.1 | V13: =請求データ入力!O65
B14: =請求データ入力!$F$6 -> 有限会社木村左官工業 | R14: ◆税込合計金額 | AO14: 058 | AP14: =IF(VLOOKUP(AO14,請求データ入力!$B$15:$P$114,9)=0,"",496)
V15: =請求データ入力!P65 | AC15: 明細 （ 有 ・ 無 ）
R16: ◆取引先担当者 | V16: ◆完成納品年月日 | AC16: 検 算 | AI16: INPUT | AO16: 059 | AP16: =IF(VLOOKUP(AO16,請求データ入力!$B$15:$P$114,9)=0,"",558)
B17: ="TEL："&請求データ入力!$K$4 -> TEL：090-4609-2757 | R17: =請求データ入力!F65 -> 0 | V17: =CONCATENATE(請求データ入力!C65,"/",請求データ入力!D65,"/",請求データ入力!E65) -> //
B18: ◆工事コード/工事名 | R18: ◆藤田建装担当者 | AO18: 060 | AP18: =IF(VLOOKUP(AO18,請求データ入力!$B$15:$P$114,9)=0,"",620)
B19: =請求データ入力!H65 -> 0 | G19: =請求データ入力!I65 -> 0 | R19: =請求データ入力!G65 -> 0 | V19: T№ | W19: =請求データ入力!Q65 -> 2602051
B22: ③ 請求明細書 | P22: ㈱藤田建装 経理管理 | AA22: 備 考
E23: ◆ 内 容 | N23: ◆ 数 量 | R23: ◆ 単 価 | V23: ◆ 金 額
B24: =B3 -> 0 | N24: =N3 -> 0 | P24: =P3 -> 0 | R24: =R3 -> 0 | V24: =V3
AA25: 差替No.
AA26: 未請求No.
AA27: 経理責任者 | AE27: 経理担当 | AI27: 現場担当
B31: ◆取引先名/コード | G31: =請求データ入力!$K$2 -> 72130 | L31: 登録番号 | R31: ◆計（税抜）
L32: =請求データ入力!$K$6 -> 0 | V32: =V11
B33: =請求データ入力!$F$2 -> 〒110-0012 東京都台東区竜泉3-40-4 | R33: ◆消費税
R34: （切捨） | T34: =請求データ入力!$O$11 -> 0.1 | V34: =V13
B35: =請求データ入力!$F$6 -> 有限会社木村左官工業 | R35: ◆税込合計金額
V36: =V15 | AC36: 明細 （ 有 ・ 無 ）
R37: ◆取引先担当者 | V37: ◆完成納品年月日 | AC37: 検 算 | AI37: INPUT
B38: ="TEL："&請求データ入力!$K$4 -> TEL：090-4609-2757 | R38: =R17 -> 0 | V38: =V17 -> //
B39: ◆工事コード/工事名 | R39: ◆藤田建装担当者
B40: =B19 -> 0 | G40: =G19 -> 0 | R40: =R19 -> 0 | V40: T№ | W40: =W19 -> 2602051
B43: ④ 管理伝票 | P43: ㈱藤田建装 事業部管理 | AA43: 備 考
E44: ◆ 内 容 | N44: ◆ 数 量 | R44: ◆ 単 価 | V44: ◆ 金 額
B45: =B24 -> 0 | N45: =N24 -> 0 | P45: =P24 -> 0 | R45: =R24 -> 0 | V45: =V24
AA46: 差替No.
AA47: 未請求No.
AA48: 経理責任者 | AE48: 経理担当 | AI48: 現場担当
B52: ◆取引先名/コード | G52: =請求データ入力!$K$2 -> 72130 | L52: 登録番号 | R52: ◆計（税抜）
L53: =請求データ入力!$K$6 -> 0 | V53: =V32
B54: =請求データ入力!$F$2 -> 〒110-0012 東京都台東区竜泉3-40-4 | R54: ◆消費税
R55: （切捨） | T55: =請求データ入力!$O$11 -> 0.1 | V55: =V34
B56: =請求データ入力!$F$6 -> 有限会社木村左官工業 | R56: ◆税込合計金額
V57: =V36 | AC57: 明細 （ 有 ・ 無 ）
R58: ◆取引先担当者 | V58: ◆完成納品年月日 | AC58: 検 算 | AI58: INPUT
B59: ="TEL："&請求データ入力!$K$4 -> TEL：090-4609-2757 | R59: =R38 -> 0 | V59: =V38 -> //
B60: ◆工事コード/工事名 | R60: ◆藤田建装担当者
B61: =B40 -> 0 | G61: =G40 -> 0 | R61: =R40 -> 0 | V61: T№ | W61: =W40 -> 2602051
B63: ② 納品書 （原価計算書） | P63: ㈱藤田建装 現場担当→課管理 | AA63: 備 考 | AM63: 352
E64: ◆ 内 容 | N64: ◆ 数 量 | R64: ◆ 単 価 | V64: ◆ 金 額
B65: =請求データ入力!J66 -> 0 | N65: =請求データ入力!K66 -> 0 | P65: =請求データ入力!L66 -> 0 | R65: =請求データ入力!M66 -> 0 | V65: =請求データ入力!N66
AA66: 差替No.
AA67: 未請求No.
AA68: 経理責任者 | AE68: 経理担当 | AI68: 現場担当
B72: ◆取引先名/コード | G72: =請求データ入力!$K$2 -> 72130 | L72: 登録番号 | R72: ◆計（税抜）
L73: =請求データ入力!$K$6 -> 0 | V73: =請求データ入力!N66
B74: =請求データ入力!$F$2 -> 〒110-0012 東京都台東区竜泉3-40-4 | R74: ◆消費税
R75: （切捨） | T75: =請求データ入力!$O$11 -> 0.1 | V75: =請求データ入力!O66
B76: =請求データ入力!$F$6 -> 有限会社木村左官工業 | R76: ◆税込合計金額
V77: =請求データ入力!P66 | AC77: 明細 （ 有 ・ 無 ）
R78: ◆取引先担当者 | V78: ◆完成納品年月日 | AC78: 検 算 | AI78: INPUT
B79: ="TEL："&請求データ入力!$K$4 -> TEL：090-4609-2757 | R79: =請求データ入力!F66 -> 0 | V79: =CONCATENATE(請求データ入力!C66,"/",請求データ入力!D66,"/",請求データ入力!E66) -> //
B80: ◆工事コード/工事名 | R80: ◆藤田建装担当者
B81: =請求データ入力!H66 -> 0 | G81: =請求データ入力!I66 -> 0 | R81: =請求データ入力!G66 -> 0 | V81: T№ | W81: =請求データ入力!Q66 -> 2602052
B84: ③ 請求明細書 | P84: ㈱藤田建装 経理管理 | AA84: 備 考
E85: ◆ 内 容 | N85: ◆ 数 量 | R85: ◆ 単 価 | V85: ◆ 金 額
B86: =B65 -> 0 | N86: =N65 -> 0 | P86: =P65 -> 0 | R86: =R65 -> 0 | V86: =V65
AA87: 差替No.
AA88: 未請求No.
AA89: 経理責任者 | AE89: 経理担当 | AI89: 現場担当
B93: ◆取引先名/コード | G93: =請求データ入力!$K$2 -> 72130 | L93: 登録番号 | R93: ◆計（税抜）
L94: =請求データ入力!$K$6 -> 0 | V94: =V73
B95: =請求データ入力!$F$2 -> 〒110-0012 東京都台東区竜泉3-40-4 | R95: ◆消費税
R96: （切捨） | T96: =請求データ入力!$O$11 -> 0.1 | V96: =V75
B97: =請求データ入力!$F$6 -> 有限会社木村左官工業 | R97: ◆税込合計金額
V98: =V77 | AC98: 明細 （ 有 ・ 無 ）
R99: ◆取引先担当者 | V99: ◆完成納品年月日 | AC99: 検 算 | AI99: INPUT
B100: ="TEL："&請求データ入力!$K$4 -> TEL：090-4609-2757 | R100: =R79 -> 0 | V100: =V79 -> //
B101: ◆工事コード/工事名 | R101: ◆藤田建装担当者
B102: =B81 -> 0 | G102: =G81 -> 0 | R102: =R81 -> 0 | V102: T№ | W102: =W81 -> 2602052
B105: ④ 管理伝票 | P105: ㈱藤田建装 事業部管理 | AA105: 備 考
E106: ◆ 内 容 | N106: ◆ 数 量 | R106: ◆ 単 価 | V106: ◆ 金 額
B107: =B86 -> 0 | N107: =N86 -> 0 | P107: =P86 -> 0 | R107: =R86 -> 0 | V107: =V86
AA108: 差替No.
AA109: 未請求No.
AA110: 経理責任者 | AE110: 経理担当 | AI110: 現場担当
B114: ◆取引先名/コード | G114: =請求データ入力!$K$2 -> 72130 | L114: 登録番号 | R114: ◆計（税抜）
L115: =請求データ入力!$K$6 -> 0 | V115: =V94
B116: =請求データ入力!$F$2 -> 〒110-0012 東京都台東区竜泉3-40-4 | R116: ◆消費税
R117: （切捨） | T117: =請求データ入力!$O$11 -> 0.1 | V117: =V96
B118: =請求データ入力!$F$6 -> 有限会社木村左官工業 | R118: ◆税込合計金額
V119: =V98 | AC119: 明細 （ 有 ・ 無 ）
R120: ◆取引先担当者 | V120: ◆完成納品年月日 | AC120: 検 算 | AI120: INPUT
B121: ="TEL："&請求データ入力!$K$4 -> TEL：090-4609-2757 | R121: =R100 -> 0 | V121: =V100 -> //
B122: ◆工事コード/工事名 | R122: ◆藤田建装担当者
B123: =B102 -> 0 | G123: =G102 -> 0 | R123: =R102 -> 0 | V123: T№ | W123: =W102 -> 2602052
B125: ② 納品書 （原価計算書） | P125: ㈱藤田建装 現場担当→課管理 | AA125: 備 考 | AM125: 353
...

Sheet 個別061-070
B1: ② 納品書 （原価計算書） | P1: ㈱藤田建装 現場担当→課管理 | AA1: 備 考 | AM1: 361
E2: ◆ 内 容 | N2: ◆ 数 量 | R2: ◆ 単 価 | V2: ◆ 金 額 | AO2: 印刷範囲 | AP2: =IF(MAX($AP$5:$AP$19)=0,1,MAX($AP$5:$AP$19)) -> 1 | AQ2: 行目 | AR2: =IF(AP2=1,1,38) -> 1 | AS2: 列目まで印刷する
B3: =請求データ入力!J75 -> 0 | N3: =請求データ入力!K75 -> 0 | P3: =請求データ入力!L75 -> 0 | R3: =請求データ入力!M75 -> 0 | V3: =請求データ入力!N75
AA4: 差替No. | AO4: 伝票№連番 | AP4: 行数
AA5: 未請求No. | AO5: 061 | AP5: =IF(VLOOKUP(AO5,請求データ入力!$B$15:$P$114,9)=0,"",62)
AA6: 経理責任者 | AE6: 経理担当 | AI6: 現場担当 | AO6: 062 | AP6: =IF(VLOOKUP(AO6,請求データ入力!$B$15:$P$114,9)=0,"",124)
AO7: 063 | AP7: =IF(VLOOKUP(AO7,請求データ入力!$B$15:$P$114,9)=0,"",186)
AO8: 064 | AP8: =IF(VLOOKUP(AO8,請求データ入力!$B$15:$P$114,9)=0,"",248)
AO9: 065 | AP9: =IF(VLOOKUP(AO9,請求データ入力!$B$15:$P$114,9)=0,"",310)
B10: ◆取引先名/コード | G10: =請求データ入力!$K$2 -> 72130 | L10: 登録番号 | R10: ◆計（税抜） | AO10: 066 | AP10: =IF(VLOOKUP(AO10,請求データ入力!$B$15:$P$114,9)=0,"",372)
L11: =請求データ入力!$K$6 -> 0 | V11: =請求データ入力!N75
B12: =請求データ入力!$F$2 -> 〒110-0012 東京都台東区竜泉3-40-4 | R12: ◆消費税 | AO12: 067 | AP12: =IF(VLOOKUP(AO12,請求データ入力!$B$15:$P$114,9)=0,"",434)
R13: （切捨） | T13: =請求データ入力!$O$11 -> 0.1 | V13: =請求データ入力!O75
B14: =請求データ入力!$F$6 -> 有限会社木村左官工業 | R14: ◆税込合計金額 | AO14: 068 | AP14: =IF(VLOOKUP(AO14,請求データ入力!$B$15:$P$114,9)=0,"",496)
V15: =請求データ入力!P75 | AC15: 明細 （ 有 ・ 無 ）
R16: ◆取引先担当者 | V16: ◆完成納品年月日 | AC16: 検 算 | AI16: INPUT | AO16: 069 | AP16: =IF(VLOOKUP(AO16,請求データ入力!$B$15:$P$114,9)=0,"",558)
B17: ="TEL："&請求データ入力!$K$4 -> TEL：090-4609-2757 | R17: =請求データ入力!F75 -> 0 | V17: =CONCATENATE(請求データ入力!C75,"/",請求データ入力!D75,"/",請求データ入力!E75) -> //
B18: ◆工事コード/工事名 | R18: ◆藤田建装担当者 | AO18: 070 | AP18: =IF(VLOOKUP(AO18,請求データ入力!$B$15:$P$114,9)=0,"",620)
B19: =請求データ入力!H75 -> 0 | G19: =請求データ入力!I75 -> 0 | R19: =請求データ入力!G75 -> 0 | V19: T№ | W19: =請求データ入力!Q75 -> 2602061
B22: ③ 請求明細書 | P22: ㈱藤田建装 経理管理 | AA22: 備 考
E23: ◆ 内 容 | N23: ◆ 数 量 | R23: ◆ 単 価 | V23: ◆ 金 額
B24: =B3 -> 0 | N24: =N3 -> 0 | P24: =P3 -> 0 | R24: =R3 -> 0 | V24: =V3
AA25: 差替No.
AA26: 未請求No.
AA27: 経理責任者 | AE27: 経理担当 | AI27: 現場担当
B31: ◆取引先名/コード | G31: =請求データ入力!$K$2 -> 72130 | L31: 登録番号 | R31: ◆計（税抜）
L32: =請求データ入力!$K$6 -> 0 | V32: =V11
B33: =請求データ入力!$F$2 -> 〒110-0012 東京都台東区竜泉3-40-4 | R33: ◆消費税
R34: （切捨） | T34: =請求データ入力!$O$11 -> 0.1 | V34: =V13
B35: =請求データ入力!$F$6 -> 有限会社木村左官工業 | R35: ◆税込合計金額
V36: =V15 | AC36: 明細 （ 有 ・ 無 ）
R37: ◆取引先担当者 | V37: ◆完成納品年月日 | AC37: 検 算 | AI37: INPUT
B38: ="TEL："&請求データ入力!$K$4 -> TEL：090-4609-2757 | R38: =R17 -> 0 | V38: =V17 -> //
B39: ◆工事コード/工事名 | R39: ◆藤田建装担当者
B40: =B19 -> 0 | G40: =G19 -> 0 | R40: =R19 -> 0 | V40: T№ | W40: =W19 -> 2602061
B43: ④ 管理伝票 | P43: ㈱藤田建装 事業部管理 | AA43: 備 考
E44: ◆ 内 容 | N44: ◆ 数 量 | R44: ◆ 単 価 | V44: ◆ 金 額
B45: =B24 -> 0 | N45: =N24 -> 0 | P45: =P24 -> 0 | R45: =R24 -> 0 | V45: =V24
AA46: 差替No.
AA47: 未請求No.
AA48: 経理責任者 | AE48: 経理担当 | AI48: 現場担当
B52: ◆取引先名/コード | G52: =請求データ入力!$K$2 -> 72130 | L52: 登録番号 | R52: ◆計（税抜）
L53: =請求データ入力!$K$6 -> 0 | V53: =V32
B54: =請求データ入力!$F$2 -> 〒110-0012 東京都台東区竜泉3-40-4 | R54: ◆消費税
R55: （切捨） | T55: =請求データ入力!$O$11 -> 0.1 | V55: =V34
B56: =請求データ入力!$F$6 -> 有限会社木村左官工業 | R56: ◆税込合計金額
V57: =V36 | AC57: 明細 （ 有 ・ 無 ）
R58: ◆取引先担当者 | V58: ◆完成納品年月日 | AC58: 検 算 | AI58: INPUT
B59: ="TEL："&請求データ入力!$K$4 -> TEL：090-4609-2757 | R59: =R38 -> 0 | V59: =V38 -> //
B60: ◆工事コード/工事名 | R60: ◆藤田建装担当者
B61: =B40 -> 0 | G61: =G40 -> 0 | R61: =R40 -> 0 | V61: T№ | W61: =W40 -> 2602061
B63: ② 納品書 （原価計算書） | P63: ㈱藤田建装 現場担当→課管理 | AA63: 備 考 | AM63: 362
E64: ◆ 内 容 | N64: ◆ 数 量 | R64: ◆ 単 価 | V64: ◆ 金 額
B65: =請求データ入力!J76 -> 0 | N65: =請求データ入力!K76 -> 0 | P65: =請求データ入力!L76 -> 0 | R65: =請求データ入力!M76 -> 0 | V65: =請求データ入力!N76
AA66: 差替No.
AA67: 未請求No.
AA68: 経理責任者 | AE68: 経理担当 | AI68: 現場担当
B72: ◆取引先名/コード | G72: =請求データ入力!$K$2 -> 72130 | L72: 登録番号 | R72: ◆計（税抜）
L73: =請求データ入力!$K$6 -> 0 | V73: =請求データ入力!N76
B74: =請求データ入力!$F$2 -> 〒110-0012 東京都台東区竜泉3-40-4 | R74: ◆消費税
R75: （切捨） | T75: =請求データ入力!$O$11 -> 0.1 | V75: =請求データ入力!O76
B76: =請求データ入力!$F$6 -> 有限会社木村左官工業 | R76: ◆税込合計金額
V77: =請求データ入力!P76 | AC77: 明細 （ 有 ・ 無 ）
R78: ◆取引先担当者 | V78: ◆完成納品年月日 | AC78: 検 算 | AI78: INPUT
B79: ="TEL："&請求データ入力!$K$4 -> TEL：090-4609-2757 | R79: =請求データ入力!F76 -> 0 | V79: =CONCATENATE(請求データ入力!C76,"/",請求データ入力!D76,"/",請求データ入力!E76) -> //
B80: ◆工事コード/工事名 | R80: ◆藤田建装担当者
B81: =請求データ入力!H76 -> 0 | G81: =請求データ入力!I76 -> 0 | R81: =請求データ入力!G76 -> 0 | V81: T№ | W81: =請求データ入力!Q76 -> 2602062
B84: ③ 請求明細書 | P84: ㈱藤田建装 経理管理 | AA84: 備 考
E85: ◆ 内 容 | N85: ◆ 数 量 | R85: ◆ 単 価 | V85: ◆ 金 額
B86: =B65 -> 0 | N86: =N65 -> 0 | P86: =P65 -> 0 | R86: =R65 -> 0 | V86: =V65
AA87: 差替No.
AA88: 未請求No.
AA89: 経理責任者 | AE89: 経理担当 | AI89: 現場担当
B93: ◆取引先名/コード | G93: =請求データ入力!$K$2 -> 72130 | L93: 登録番号 | R93: ◆計（税抜）
L94: =請求データ入力!$K$6 -> 0 | V94: =V73
B95: =請求データ入力!$F$2 -> 〒110-0012 東京都台東区竜泉3-40-4 | R95: ◆消費税
R96: （切捨） | T96: =請求データ入力!$O$11 -> 0.1 | V96: =V75
B97: =請求データ入力!$F$6 -> 有限会社木村左官工業 | R97: ◆税込合計金額
V98: =V77 | AC98: 明細 （ 有 ・ 無 ）
R99: ◆取引先担当者 | V99: ◆完成納品年月日 | AC99: 検 算 | AI99: INPUT
B100: ="TEL："&請求データ入力!$K$4 -> TEL：090-4609-2757 | R100: =R79 -> 0 | V100: =V79 -> //
B101: ◆工事コード/工事名 | R101: ◆藤田建装担当者
B102: =B81 -> 0 | G102: =G81 -> 0 | R102: =R81 -> 0 | V102: T№ | W102: =W81 -> 2602062
B105: ④ 管理伝票 | P105: ㈱藤田建装 事業部管理 | AA105: 備 考
E106: ◆ 内 容 | N106: ◆ 数 量 | R106: ◆ 単 価 | V106: ◆ 金 額
B107: =B86 -> 0 | N107: =N86 -> 0 | P107: =P86 -> 0 | R107: =R86 -> 0 | V107: =V86
AA108: 差替No.
AA109: 未請求No.
AA110: 経理責任者 | AE110: 経理担当 | AI110: 現場担当
B114: ◆取引先名/コード | G114: =請求データ入力!$K$2 -> 72130 | L114: 登録番号 | R114: ◆計（税抜）
L115: =請求データ入力!$K$6 -> 0 | V115: =V94
B116: =請求データ入力!$F$2 -> 〒110-0012 東京都台東区竜泉3-40-4 | R116: ◆消費税
R117: （切捨） | T117: =請求データ入力!$O$11 -> 0.1 | V117: =V96
B118: =請求データ入力!$F$6 -> 有限会社木村左官工業 | R118: ◆税込合計金額
V119: =V98 | AC119: 明細 （ 有 ・ 無 ）
R120: ◆取引先担当者 | V120: ◆完成納品年月日 | AC120: 検 算 | AI120: INPUT
B121: ="TEL："&請求データ入力!$K$4 -> TEL：090-4609-2757 | R121: =R100 -> 0 | V121: =V100 -> //
B122: ◆工事コード/工事名 | R122: ◆藤田建装担当者
B123: =B102 -> 0 | G123: =G102 -> 0 | R123: =R102 -> 0 | V123: T№ | W123: =W102 -> 2602062
B125: ② 納品書 （原価計算書） | P125: ㈱藤田建装 現場担当→課管理 | AA125: 備 考 | AM125: 363
...

Sheet 個別071-080
B1: ② 納品書 （原価計算書） | P1: ㈱藤田建装 現場担当→課管理 | AA1: 備 考 | AM1: 371
E2: ◆ 内 容 | N2: ◆ 数 量 | R2: ◆ 単 価 | V2: ◆ 金 額 | AO2: 印刷範囲 | AP2: =IF(MAX($AP$5:$AP$19)=0,1,MAX($AP$5:$AP$19)) -> 1 | AQ2: 行目 | AR2: =IF(AP2=1,1,38) -> 1 | AS2: 列目まで印刷する
B3: =請求データ入力!J85 -> 0 | N3: =請求データ入力!K85 -> 0 | P3: =請求データ入力!L85 -> 0 | R3: =請求データ入力!M85 -> 0 | V3: =請求データ入力!N85
AA4: 差替No. | AO4: 伝票№連番 | AP4: 行数
AA5: 未請求No. | AO5: 071 | AP5: =IF(VLOOKUP(AO5,請求データ入力!$B$15:$P$114,9)=0,"",62)
AA6: 経理責任者 | AE6: 経理担当 | AI6: 現場担当 | AO6: 072 | AP6: =IF(VLOOKUP(AO6,請求データ入力!$B$15:$P$114,9)=0,"",124)
AO7: 073 | AP7: =IF(VLOOKUP(AO7,請求データ入力!$B$15:$P$114,9)=0,"",186)
AO8: 074 | AP8: =IF(VLOOKUP(AO8,請求データ入力!$B$15:$P$114,9)=0,"",248)
AO9: 075 | AP9: =IF(VLOOKUP(AO9,請求データ入力!$B$15:$P$114,9)=0,"",310)
B10: ◆取引先名/コード | G10: =請求データ入力!$K$2 -> 72130 | L10: 登録番号 | R10: ◆計（税抜） | AO10: 076 | AP10: =IF(VLOOKUP(AO10,請求データ入力!$B$15:$P$114,9)=0,"",372)
L11: =請求データ入力!$K$6 -> 0 | V11: =請求データ入力!N85
B12: =請求データ入力!$F$2 -> 〒110-0012 東京都台東区竜泉3-40-4 | R12: ◆消費税 | AO12: 077 | AP12: =IF(VLOOKUP(AO12,請求データ入力!$B$15:$P$114,9)=0,"",434)
R13: （切捨） | T13: =請求データ入力!$O$11 -> 0.1 | V13: =請求データ入力!O85
B14: =請求データ入力!$F$6 -> 有限会社木村左官工業 | R14: ◆税込合計金額 | AO14: 078 | AP14: =IF(VLOOKUP(AO14,請求データ入力!$B$15:$P$114,9)=0,"",496)
V15: =請求データ入力!P85 | AC15: 明細 （ 有 ・ 無 ）
R16: ◆取引先担当者 | V16: ◆完成納品年月日 | AC16: 検 算 | AI16: INPUT | AO16: 079 | AP16: =IF(VLOOKUP(AO16,請求データ入力!$B$15:$P$114,9)=0,"",558)
B17: ="TEL："&請求データ入力!$K$4 -> TEL：090-4609-2757 | R17: =請求データ入力!F85 -> 0 | V17: =CONCATENATE(請求データ入力!C85,"/",請求データ入力!D85,"/",請求データ入力!E85) -> //
B18: ◆工事コード/工事名 | R18: ◆藤田建装担当者 | AO18: 080 | AP18: =IF(VLOOKUP(AO18,請求データ入力!$B$15:$P$114,9)=0,"",620)
B19: =請求データ入力!H85 -> 0 | G19: =請求データ入力!I85 -> 0 | R19: =請求データ入力!G85 -> 0 | V19: T№ | W19: =請求データ入力!Q85 -> 2602071
B22: ③ 請求明細書 | P22: ㈱藤田建装 経理管理 | AA22: 備 考
E23: ◆ 内 容 | N23: ◆ 数 量 | R23: ◆ 単 価 | V23: ◆ 金 額
B24: =B3 -> 0 | N24: =N3 -> 0 | P24: =P3 -> 0 | R24: =R3 -> 0 | V24: =V3
AA25: 差替No.
AA26: 未請求No.
AA27: 経理責任者 | AE27: 経理担当 | AI27: 現場担当
B31: ◆取引先名/コード | G31: =請求データ入力!$K$2 -> 72130 | L31: 登録番号 | R31: ◆計（税抜）
L32: =請求データ入力!$K$6 -> 0 | V32: =V11
B33: =請求データ入力!$F$2 -> 〒110-0012 東京都台東区竜泉3-40-4 | R33: ◆消費税
R34: （切捨） | T34: =請求データ入力!$O$11 -> 0.1 | V34: =V13
B35: =請求データ入力!$F$6 -> 有限会社木村左官工業 | R35: ◆税込合計金額
V36: =V15 | AC36: 明細 （ 有 ・ 無 ）
R37: ◆取引先担当者 | V37: ◆完成納品年月日 | AC37: 検 算 | AI37: INPUT
B38: ="TEL："&請求データ入力!$K$4 -> TEL：090-4609-2757 | R38: =R17 -> 0 | V38: =V17 -> //
B39: ◆工事コード/工事名 | R39: ◆藤田建装担当者
B40: =B19 -> 0 | G40: =G19 -> 0 | R40: =R19 -> 0 | V40: T№ | W40: =W19 -> 2602071
B43: ④ 管理伝票 | P43: ㈱藤田建装 事業部管理 | AA43: 備 考
E44: ◆ 内 容 | N44: ◆ 数 量 | R44: ◆ 単 価 | V44: ◆ 金 額
B45: =B24 -> 0 | N45: =N24 -> 0 | P45: =P24 -> 0 | R45: =R24 -> 0 | V45: =V24
AA46: 差替No.
AA47: 未請求No.
AA48: 経理責任者 | AE48: 経理担当 | AI48: 現場担当
B52: ◆取引先名/コード | G52: =請求データ入力!$K$2 -> 72130 | L52: 登録番号 | R52: ◆計（税抜）
L53: =請求データ入力!$K$6 -> 0 | V53: =V32
B54: =請求データ入力!$F$2 -> 〒110-0012 東京都台東区竜泉3-40-4 | R54: ◆消費税
R55: （切捨） | T55: =請求データ入力!$O$11 -> 0.1 | V55: =V34
B56: =請求データ入力!$F$6 -> 有限会社木村左官工業 | R56: ◆税込合計金額
V57: =V36 | AC57: 明細 （ 有 ・ 無 ）
R58: ◆取引先担当者 | V58: ◆完成納品年月日 | AC58: 検 算 | AI58: INPUT
B59: ="TEL："&請求データ入力!$K$4 -> TEL：090-4609-2757 | R59: =R38 -> 0 | V59: =V38 -> //
B60: ◆工事コード/工事名 | R60: ◆藤田建装担当者
B61: =B40 -> 0 | G61: =G40 -> 0 | R61: =R40 -> 0 | V61: T№ | W61: =W40 -> 2602071
B63: ② 納品書 （原価計算書） | P63: ㈱藤田建装 現場担当→課管理 | AA63: 備 考 | AM63: 372
E64: ◆ 内 容 | N64: ◆ 数 量 | R64: ◆ 単 価 | V64: ◆ 金 額
B65: =請求データ入力!J86 -> 0 | N65: =請求データ入力!K86 -> 0 | P65: =請求データ入力!L86 -> 0 | R65: =請求データ入力!M86 -> 0 | V65: =請求データ入力!N86
AA66: 差替No.
AA67: 未請求No.
AA68: 経理責任者 | AE68: 経理担当 | AI68: 現場担当
B72: ◆取引先名/コード | G72: =請求データ入力!$K$2 -> 72130 | L72: 登録番号 | R72: ◆計（税抜）
L73: =請求データ入力!$K$6 -> 0 | V73: =請求データ入力!N86
B74: =請求データ入力!$F$2 -> 〒110-0012 東京都台東区竜泉3-40-4 | R74: ◆消費税
R75: （切捨） | T75: =請求データ入力!$O$11 -> 0.1 | V75: =請求データ入力!O86
B76: =請求データ入力!$F$6 -> 有限会社木村左官工業 | R76: ◆税込合計金額
V77: =請求データ入力!P86 | AC77: 明細 （ 有 ・ 無 ）
R78: ◆取引先担当者 | V78: ◆完成納品年月日 | AC78: 検 算 | AI78: INPUT
B79: ="TEL："&請求データ入力!$K$4 -> TEL：090-4609-2757 | R79: =請求データ入力!F86 -> 0 | V79: =CONCATENATE(請求データ入力!C86,"/",請求データ入力!D86,"/",請求データ入力!E86) -> //
B80: ◆工事コード/工事名 | R80: ◆藤田建装担当者
B81: =請求データ入力!H86 -> 0 | G81: =請求データ入力!I86 -> 0 | R81: =請求データ入力!G86 -> 0 | V81: T№ | W81: =請求データ入力!Q86 -> 2602072
B84: ③ 請求明細書 | P84: ㈱藤田建装 経理管理 | AA84: 備 考
E85: ◆ 内 容 | N85: ◆ 数 量 | R85: ◆ 単 価 | V85: ◆ 金 額
B86: =B65 -> 0 | N86: =N65 -> 0 | P86: =P65 -> 0 | R86: =R65 -> 0 | V86: =V65
AA87: 差替No.
AA88: 未請求No.
AA89: 経理責任者 | AE89: 経理担当 | AI89: 現場担当
B93: ◆取引先名/コード | G93: =請求データ入力!$K$2 -> 72130 | L93: 登録番号 | R93: ◆計（税抜）
L94: =請求データ入力!$K$6 -> 0 | V94: =V73
B95: =請求データ入力!$F$2 -> 〒110-0012 東京都台東区竜泉3-40-4 | R95: ◆消費税
R96: （切捨） | T96: =請求データ入力!$O$11 -> 0.1 | V96: =V75
B97: =請求データ入力!$F$6 -> 有限会社木村左官工業 | R97: ◆税込合計金額
V98: =V77 | AC98: 明細 （ 有 ・ 無 ）
R99: ◆取引先担当者 | V99: ◆完成納品年月日 | AC99: 検 算 | AI99: INPUT
B100: ="TEL："&請求データ入力!$K$4 -> TEL：090-4609-2757 | R100: =R79 -> 0 | V100: =V79 -> //
B101: ◆工事コード/工事名 | R101: ◆藤田建装担当者
B102: =B81 -> 0 | G102: =G81 -> 0 | R102: =R81 -> 0 | V102: T№ | W102: =W81 -> 2602072
B105: ④ 管理伝票 | P105: ㈱藤田建装 事業部管理 | AA105: 備 考
E106: ◆ 内 容 | N106: ◆ 数 量 | R106: ◆ 単 価 | V106: ◆ 金 額
B107: =B86 -> 0 | N107: =N86 -> 0 | P107: =P86 -> 0 | R107: =R86 -> 0 | V107: =V86
AA108: 差替No.
AA109: 未請求No.
AA110: 経理責任者 | AE110: 経理担当 | AI110: 現場担当
B114: ◆取引先名/コード | G114: =請求データ入力!$K$2 -> 72130 | L114: 登録番号 | R114: ◆計（税抜）
L115: =請求データ入力!$K$6 -> 0 | V115: =V94
B116: =請求データ入力!$F$2 -> 〒110-0012 東京都台東区竜泉3-40-4 | R116: ◆消費税
R117: （切捨） | T117: =請求データ入力!$O$11 -> 0.1 | V117: =V96
B118: =請求データ入力!$F$6 -> 有限会社木村左官工業 | R118: ◆税込合計金額
V119: =V98 | AC119: 明細 （ 有 ・ 無 ）
R120: ◆取引先担当者 | V120: ◆完成納品年月日 | AC120: 検 算 | AI120: INPUT
B121: ="TEL："&請求データ入力!$K$4 -> TEL：090-4609-2757 | R121: =R100 -> 0 | V121: =V100 -> //
B122: ◆工事コード/工事名 | R122: ◆藤田建装担当者
B123: =B102 -> 0 | G123: =G102 -> 0 | R123: =R102 -> 0 | V123: T№ | W123: =W102 -> 2602072
B125: ② 納品書 （原価計算書） | P125: ㈱藤田建装 現場担当→課管理 | AA125: 備 考 | AM125: 373
...

Sheet 個別081-090
B1: ② 納品書 （原価計算書） | P1: ㈱藤田建装 現場担当→課管理 | AA1: 備 考 | AM1: 381
E2: ◆ 内 容 | N2: ◆ 数 量 | R2: ◆ 単 価 | V2: ◆ 金 額 | AO2: 印刷範囲 | AP2: =IF(MAX($AP$5:$AP$19)=0,1,MAX($AP$5:$AP$19)) -> 1 | AQ2: 行目 | AR2: =IF(AP2=1,1,38) -> 1 | AS2: 列目まで印刷する
B3: =請求データ入力!J95 -> 0 | N3: =請求データ入力!K95 -> 0 | P3: =請求データ入力!L95 -> 0 | R3: =請求データ入力!M95 -> 0 | V3: =請求データ入力!N95
AA4: 差替No. | AO4: 伝票№連番 | AP4: 行数
AA5: 未請求No. | AO5: 081 | AP5: =IF(VLOOKUP(AO5,請求データ入力!$B$15:$P$114,9)=0,"",62)
AA6: 経理責任者 | AE6: 経理担当 | AI6: 現場担当 | AO6: 082 | AP6: =IF(VLOOKUP(AO6,請求データ入力!$B$15:$P$114,9)=0,"",124)
AO7: 083 | AP7: =IF(VLOOKUP(AO7,請求データ入力!$B$15:$P$114,9)=0,"",186)
AO8: 084 | AP8: =IF(VLOOKUP(AO8,請求データ入力!$B$15:$P$114,9)=0,"",248)
AO9: 085 | AP9: =IF(VLOOKUP(AO9,請求データ入力!$B$15:$P$114,9)=0,"",310)
B10: ◆取引先名/コード | G10: =請求データ入力!$K$2 -> 72130 | L10: 登録番号 | R10: ◆計（税抜） | AO10: 086 | AP10: =IF(VLOOKUP(AO10,請求データ入力!$B$15:$P$114,9)=0,"",372)
L11: =請求データ入力!$K$6 -> 0 | V11: =請求データ入力!N95
B12: =請求データ入力!$F$2 -> 〒110-0012 東京都台東区竜泉3-40-4 | R12: ◆消費税 | AO12: 087 | AP12: =IF(VLOOKUP(AO12,請求データ入力!$B$15:$P$114,9)=0,"",434)
R13: （切捨） | T13: =請求データ入力!$O$11 -> 0.1 | V13: =請求データ入力!O95
B14: =請求データ入力!$F$6 -> 有限会社木村左官工業 | R14: ◆税込合計金額 | AO14: 088 | AP14: =IF(VLOOKUP(AO14,請求データ入力!$B$15:$P$114,9)=0,"",496)
V15: =請求データ入力!P95 | AC15: 明細 （ 有 ・ 無 ）
R16: ◆取引先担当者 | V16: ◆完成納品年月日 | AC16: 検 算 | AI16: INPUT | AO16: 089 | AP16: =IF(VLOOKUP(AO16,請求データ入力!$B$15:$P$114,9)=0,"",558)
B17: ="TEL："&請求データ入力!$K$4 -> TEL：090-4609-2757 | R17: =請求データ入力!F95 -> 0 | V17: =CONCATENATE(請求データ入力!C95,"/",請求データ入力!D95,"/",請求データ入力!E95) -> //
B18: ◆工事コード/工事名 | R18: ◆藤田建装担当者 | AO18: 090 | AP18: =IF(VLOOKUP(AO18,請求データ入力!$B$15:$P$114,9)=0,"",620)
B19: =請求データ入力!H95 -> 0 | G19: =請求データ入力!I95 -> 0 | R19: =請求データ入力!G95 -> 0 | V19: T№ | W19: =請求データ入力!Q95 -> 2602081
B22: ③ 請求明細書 | P22: ㈱藤田建装 経理管理 | AA22: 備 考
E23: ◆ 内 容 | N23: ◆ 数 量 | R23: ◆ 単 価 | V23: ◆ 金 額
B24: =B3 -> 0 | N24: =N3 -> 0 | P24: =P3 -> 0 | R24: =R3 -> 0 | V24: =V3
AA25: 差替No.
AA26: 未請求No.
AA27: 経理責任者 | AE27: 経理担当 | AI27: 現場担当
B31: ◆取引先名/コード | G31: =請求データ入力!$K$2 -> 72130 | L31: 登録番号 | R31: ◆計（税抜）
L32: =請求データ入力!$K$6 -> 0 | V32: =V11
B33: =請求データ入力!$F$2 -> 〒110-0012 東京都台東区竜泉3-40-4 | R33: ◆消費税
R34: （切捨） | T34: =請求データ入力!$O$11 -> 0.1 | V34: =V13
B35: =請求データ入力!$F$6 -> 有限会社木村左官工業 | R35: ◆税込合計金額
V36: =V15 | AC36: 明細 （ 有 ・ 無 ）
R37: ◆取引先担当者 | V37: ◆完成納品年月日 | AC37: 検 算 | AI37: INPUT
B38: ="TEL："&請求データ入力!$K$4 -> TEL：090-4609-2757 | R38: =R17 -> 0 | V38: =V17 -> //
B39: ◆工事コード/工事名 | R39: ◆藤田建装担当者
B40: =B19 -> 0 | G40: =G19 -> 0 | R40: =R19 -> 0 | V40: T№ | W40: =W19 -> 2602081
B43: ④ 管理伝票 | P43: ㈱藤田建装 事業部管理 | AA43: 備 考
E44: ◆ 内 容 | N44: ◆ 数 量 | R44: ◆ 単 価 | V44: ◆ 金 額
B45: =B24 -> 0 | N45: =N24 -> 0 | P45: =P24 -> 0 | R45: =R24 -> 0 | V45: =V24
AA46: 差替No.
AA47: 未請求No.
AA48: 経理責任者 | AE48: 経理担当 | AI48: 現場担当
B52: ◆取引先名/コード | G52: =請求データ入力!$K$2 -> 72130 | L52: 登録番号 | R52: ◆計（税抜）
L53: =請求データ入力!$K$6 -> 0 | V53: =V32
B54: =請求データ入力!$F$2 -> 〒110-0012 東京都台東区竜泉3-40-4 | R54: ◆消費税
R55: （切捨） | T55: =請求データ入力!$O$11 -> 0.1 | V55: =V34
B56: =請求データ入力!$F$6 -> 有限会社木村左官工業 | R56: ◆税込合計金額
V57: =V36 | AC57: 明細 （ 有 ・ 無 ）
R58: ◆取引先担当者 | V58: ◆完成納品年月日 | AC58: 検 算 | AI58: INPUT
B59: ="TEL："&請求データ入力!$K$4 -> TEL：090-4609-2757 | R59: =R38 -> 0 | V59: =V38 -> //
B60: ◆工事コード/工事名 | R60: ◆藤田建装担当者
B61: =B40 -> 0 | G61: =G40 -> 0 | R61: =R40 -> 0 | V61: T№ | W61: =W40 -> 2602081
B63: ② 納品書 （原価計算書） | P63: ㈱藤田建装 現場担当→課管理 | AA63: 備 考 | AM63: 382
E64: ◆ 内 容 | N64: ◆ 数 量 | R64: ◆ 単 価 | V64: ◆ 金 額
B65: =請求データ入力!J96 -> 0 | N65: =請求データ入力!K96 -> 0 | P65: =請求データ入力!L96 -> 0 | R65: =請求データ入力!M96 -> 0 | V65: =請求データ入力!N96
AA66: 差替No.
AA67: 未請求No.
AA68: 経理責任者 | AE68: 経理担当 | AI68: 現場担当
B72: ◆取引先名/コード | G72: =請求データ入力!$K$2 -> 72130 | L72: 登録番号 | R72: ◆計（税抜）
L73: =請求データ入力!$K$6 -> 0 | V73: =請求データ入力!N96
B74: =請求データ入力!$F$2 -> 〒110-0012 東京都台東区竜泉3-40-4 | R74: ◆消費税
R75: （切捨） | T75: =請求データ入力!$O$11 -> 0.1 | V75: =請求データ入力!O96
B76: =請求データ入力!$F$6 -> 有限会社木村左官工業 | R76: ◆税込合計金額
V77: =請求データ入力!P96 | AC77: 明細 （ 有 ・ 無 ）
R78: ◆取引先担当者 | V78: ◆完成納品年月日 | AC78: 検 算 | AI78: INPUT
B79: ="TEL："&請求データ入力!$K$4 -> TEL：090-4609-2757 | R79: =請求データ入力!F96 -> 0 | V79: =CONCATENATE(請求データ入力!C96,"/",請求データ入力!D96,"/",請求データ入力!E96) -> //
B80: ◆工事コード/工事名 | R80: ◆藤田建装担当者
B81: =請求データ入力!H96 -> 0 | G81: =請求データ入力!I96 -> 0 | R81: =請求データ入力!G96 -> 0 | V81: T№ | W81: =請求データ入力!Q96 -> 2602082
B84: ③ 請求明細書 | P84: ㈱藤田建装 経理管理 | AA84: 備 考
E85: ◆ 内 容 | N85: ◆ 数 量 | R85: ◆ 単 価 | V85: ◆ 金 額
B86: =B65 -> 0 | N86: =N65 -> 0 | P86: =P65 -> 0 | R86: =R65 -> 0 | V86: =V65
AA87: 差替No.
AA88: 未請求No.
AA89: 経理責任者 | AE89: 経理担当 | AI89: 現場担当
B93: ◆取引先名/コード | G93: =請求データ入力!$K$2 -> 72130 | L93: 登録番号 | R93: ◆計（税抜）
L94: =請求データ入力!$K$6 -> 0 | V94: =V73
B95: =請求データ入力!$F$2 -> 〒110-0012 東京都台東区竜泉3-40-4 | R95: ◆消費税
R96: （切捨） | T96: =請求データ入力!$O$11 -> 0.1 | V96: =V75
B97: =請求データ入力!$F$6 -> 有限会社木村左官工業 | R97: ◆税込合計金額
V98: =V77 | AC98: 明細 （ 有 ・ 無 ）
R99: ◆取引先担当者 | V99: ◆完成納品年月日 | AC99: 検 算 | AI99: INPUT
B100: ="TEL："&請求データ入力!$K$4 -> TEL：090-4609-2757 | R100: =R79 -> 0 | V100: =V79 -> //
B101: ◆工事コード/工事名 | R101: ◆藤田建装担当者
B102: =B81 -> 0 | G102: =G81 -> 0 | R102: =R81 -> 0 | V102: T№ | W102: =W81 -> 2602082
B105: ④ 管理伝票 | P105: ㈱藤田建装 事業部管理 | AA105: 備 考
E106: ◆ 内 容 | N106: ◆ 数 量 | R106: ◆ 単 価 | V106: ◆ 金 額
B107: =B86 -> 0 | N107: =N86 -> 0 | P107: =P86 -> 0 | R107: =R86 -> 0 | V107: =V86
AA108: 差替No.
AA109: 未請求No.
AA110: 経理責任者 | AE110: 経理担当 | AI110: 現場担当
B114: ◆取引先名/コード | G114: =請求データ入力!$K$2 -> 72130 | L114: 登録番号 | R114: ◆計（税抜）
L115: =請求データ入力!$K$6 -> 0 | V115: =V94
B116: =請求データ入力!$F$2 -> 〒110-0012 東京都台東区竜泉3-40-4 | R116: ◆消費税
R117: （切捨） | T117: =請求データ入力!$O$11 -> 0.1 | V117: =V96
B118: =請求データ入力!$F$6 -> 有限会社木村左官工業 | R118: ◆税込合計金額
V119: =V98 | AC119: 明細 （ 有 ・ 無 ）
R120: ◆取引先担当者 | V120: ◆完成納品年月日 | AC120: 検 算 | AI120: INPUT
B121: ="TEL："&請求データ入力!$K$4 -> TEL：090-4609-2757 | R121: =R100 -> 0 | V121: =V100 -> //
B122: ◆工事コード/工事名 | R122: ◆藤田建装担当者
B123: =B102 -> 0 | G123: =G102 -> 0 | R123: =R102 -> 0 | V123: T№ | W123: =W102 -> 2602082
B125: ② 納品書 （原価計算書） | P125: ㈱藤田建装 現場担当→課管理 | AA125: 備 考 | AM125: 383
...

Sheet 個別091-100
B1: ② 納品書 （原価計算書） | P1: ㈱藤田建装 現場担当→課管理 | AA1: 備 考 | AM1: 391
E2: ◆ 内 容 | N2: ◆ 数 量 | R2: ◆ 単 価 | V2: ◆ 金 額 | AO2: 印刷範囲 | AP2: =IF(MAX($AP$5:$AP$19)=0,1,MAX($AP$5:$AP$19)) -> 1 | AQ2: 行目 | AR2: =IF(AP2=1,1,38) -> 1 | AS2: 列目まで印刷する
B3: =請求データ入力!J105 -> 0 | N3: =請求データ入力!K105 -> 0 | P3: =請求データ入力!L105 -> 0 | R3: =請求データ入力!M105 -> 0 | V3: =請求データ入力!N105
AA4: 差替No. | AO4: 伝票№連番 | AP4: 行数
AA5: 未請求No. | AO5: 091 | AP5: =IF(VLOOKUP(AO5,請求データ入力!$B$15:$P$114,9)=0,"",62)
AA6: 経理責任者 | AE6: 経理担当 | AI6: 現場担当 | AO6: 092 | AP6: =IF(VLOOKUP(AO6,請求データ入力!$B$15:$P$114,9)=0,"",124)
AO7: 093 | AP7: =IF(VLOOKUP(AO7,請求データ入力!$B$15:$P$114,9)=0,"",186)
AO8: 094 | AP8: =IF(VLOOKUP(AO8,請求データ入力!$B$15:$P$114,9)=0,"",248)
AO9: 095 | AP9: =IF(VLOOKUP(AO9,請求データ入力!$B$15:$P$114,9)=0,"",310)
B10: ◆取引先名/コード | G10: =請求データ入力!$K$2 -> 72130 | L10: 登録番号 | R10: ◆計（税抜） | AO10: 096 | AP10: =IF(VLOOKUP(AO10,請求データ入力!$B$15:$P$114,9)=0,"",372)
L11: =請求データ入力!$K$6 -> 0 | V11: =請求データ入力!N105
B12: =請求データ入力!$F$2 -> 〒110-0012 東京都台東区竜泉3-40-4 | R12: ◆消費税 | AO12: 097 | AP12: =IF(VLOOKUP(AO12,請求データ入力!$B$15:$P$114,9)=0,"",434)
R13: （切捨） | T13: =請求データ入力!$O$11 -> 0.1 | V13: =請求データ入力!O105
B14: =請求データ入力!$F$6 -> 有限会社木村左官工業 | R14: ◆税込合計金額 | AO14: 098 | AP14: =IF(VLOOKUP(AO14,請求データ入力!$B$15:$P$114,9)=0,"",496)
V15: =請求データ入力!P105 | AC15: 明細 （ 有 ・ 無 ）
R16: ◆取引先担当者 | V16: ◆完成納品年月日 | AC16: 検 算 | AI16: INPUT | AO16: 099 | AP16: =IF(VLOOKUP(AO16,請求データ入力!$B$15:$P$114,9)=0,"",558)
B17: ="TEL："&請求データ入力!$K$4 -> TEL：090-4609-2757 | R17: =請求データ入力!F105 -> 0 | V17: =CONCATENATE(請求データ入力!C105,"/",請求データ入力!D105,"/",請求データ入力!E105) -> //
B18: ◆工事コード/工事名 | R18: ◆藤田建装担当者 | AO18: 100 | AP18: =IF(VLOOKUP(AO18,請求データ入力!$B$15:$P$114,9)=0,"",620)
B19: =請求データ入力!H105 -> 0 | G19: =請求データ入力!I105 -> 0 | R19: =請求データ入力!G105 -> 0 | V19: T№ | W19: =請求データ入力!Q105 -> 2602091
B22: ③ 請求明細書 | P22: ㈱藤田建装 経理管理 | AA22: 備 考
E23: ◆ 内 容 | N23: ◆ 数 量 | R23: ◆ 単 価 | V23: ◆ 金 額
B24: =B3 -> 0 | N24: =N3 -> 0 | P24: =P3 -> 0 | R24: =R3 -> 0 | V24: =V3
AA25: 差替No.
AA26: 未請求No.
AA27: 経理責任者 | AE27: 経理担当 | AI27: 現場担当
B31: ◆取引先名/コード | G31: =請求データ入力!$K$2 -> 72130 | L31: 登録番号 | R31: ◆計（税抜）
L32: =請求データ入力!$K$6 -> 0 | V32: =V11
B33: =請求データ入力!$F$2 -> 〒110-0012 東京都台東区竜泉3-40-4 | R33: ◆消費税
R34: （切捨） | T34: =請求データ入力!$O$11 -> 0.1 | V34: =V13
B35: =請求データ入力!$F$6 -> 有限会社木村左官工業 | R35: ◆税込合計金額
V36: =V15 | AC36: 明細 （ 有 ・ 無 ）
R37: ◆取引先担当者 | V37: ◆完成納品年月日 | AC37: 検 算 | AI37: INPUT
B38: ="TEL："&請求データ入力!$K$4 -> TEL：090-4609-2757 | R38: =R17 -> 0 | V38: =V17 -> //
B39: ◆工事コード/工事名 | R39: ◆藤田建装担当者
B40: =B19 -> 0 | G40: =G19 -> 0 | R40: =R19 -> 0 | V40: T№ | W40: =W19 -> 2602091
B43: ④ 管理伝票 | P43: ㈱藤田建装 事業部管理 | AA43: 備 考
E44: ◆ 内 容 | N44: ◆ 数 量 | R44: ◆ 単 価 | V44: ◆ 金 額
B45: =B24 -> 0 | N45: =N24 -> 0 | P45: =P24 -> 0 | R45: =R24 -> 0 | V45: =V24
AA46: 差替No.
AA47: 未請求No.
AA48: 経理責任者 | AE48: 経理担当 | AI48: 現場担当
B52: ◆取引先名/コード | G52: =請求データ入力!$K$2 -> 72130 | L52: 登録番号 | R52: ◆計（税抜）
L53: =請求データ入力!$K$6 -> 0 | V53: =V32
B54: =請求データ入力!$F$2 -> 〒110-0012 東京都台東区竜泉3-40-4 | R54: ◆消費税
R55: （切捨） | T55: =請求データ入力!$O$11 -> 0.1 | V55: =V34
B56: =請求データ入力!$F$6 -> 有限会社木村左官工業 | R56: ◆税込合計金額
V57: =V36 | AC57: 明細 （ 有 ・ 無 ）
R58: ◆取引先担当者 | V58: ◆完成納品年月日 | AC58: 検 算 | AI58: INPUT
B59: ="TEL："&請求データ入力!$K$4 -> TEL：090-4609-2757 | R59: =R38 -> 0 | V59: =V38 -> //
B60: ◆工事コード/工事名 | R60: ◆藤田建装担当者
B61: =B40 -> 0 | G61: =G40 -> 0 | R61: =R40 -> 0 | V61: T№ | W61: =W40 -> 2602091
B63: ② 納品書 （原価計算書） | P63: ㈱藤田建装 現場担当→課管理 | AA63: 備 考 | AM63: 392
E64: ◆ 内 容 | N64: ◆ 数 量 | R64: ◆ 単 価 | V64: ◆ 金 額
B65: =請求データ入力!J106 -> 0 | N65: =請求データ入力!K106 -> 0 | P65: =請求データ入力!L106 -> 0 | R65: =請求データ入力!M106 -> 0 | V65: =請求データ入力!N106
AA66: 差替No.
AA67: 未請求No.
AA68: 経理責任者 | AE68: 経理担当 | AI68: 現場担当
B72: ◆取引先名/コード | G72: =請求データ入力!$K$2 -> 72130 | L72: 登録番号 | R72: ◆計（税抜）
L73: =請求データ入力!$K$6 -> 0 | V73: =請求データ入力!N106
B74: =請求データ入力!$F$2 -> 〒110-0012 東京都台東区竜泉3-40-4 | R74: ◆消費税
R75: （切捨） | T75: =請求データ入力!$O$11 -> 0.1 | V75: =請求データ入力!O106
B76: =請求データ入力!$F$6 -> 有限会社木村左官工業 | R76: ◆税込合計金額
V77: =請求データ入力!P106 | AC77: 明細 （ 有 ・ 無 ）
R78: ◆取引先担当者 | V78: ◆完成納品年月日 | AC78: 検 算 | AI78: INPUT
B79: ="TEL："&請求データ入力!$K$4 -> TEL：090-4609-2757 | R79: =請求データ入力!F106 -> 0 | V79: =CONCATENATE(請求データ入力!C106,"/",請求データ入力!D106,"/",請求データ入力!E106) -> //
B80: ◆工事コード/工事名 | R80: ◆藤田建装担当者
B81: =請求データ入力!H106 -> 0 | G81: =請求データ入力!I106 -> 0 | R81: =請求データ入力!G106 -> 0 | V81: T№ | W81: =請求データ入力!Q106 -> 2602092
B84: ③ 請求明細書 | P84: ㈱藤田建装 経理管理 | AA84: 備 考
E85: ◆ 内 容 | N85: ◆ 数 量 | R85: ◆ 単 価 | V85: ◆ 金 額
B86: =B65 -> 0 | N86: =N65 -> 0 | P86: =P65 -> 0 | R86: =R65 -> 0 | V86: =V65
AA87: 差替No.
AA88: 未請求No.
AA89: 経理責任者 | AE89: 経理担当 | AI89: 現場担当
B93: ◆取引先名/コード | G93: =請求データ入力!$K$2 -> 72130 | L93: 登録番号 | R93: ◆計（税抜）
L94: =請求データ入力!$K$6 -> 0 | V94: =V73
B95: =請求データ入力!$F$2 -> 〒110-0012 東京都台東区竜泉3-40-4 | R95: ◆消費税
R96: （切捨） | T96: =請求データ入力!$O$11 -> 0.1 | V96: =V75
B97: =請求データ入力!$F$6 -> 有限会社木村左官工業 | R97: ◆税込合計金額
V98: =V77 | AC98: 明細 （ 有 ・ 無 ）
R99: ◆取引先担当者 | V99: ◆完成納品年月日 | AC99: 検 算 | AI99: INPUT
B100: ="TEL："&請求データ入力!$K$4 -> TEL：090-4609-2757 | R100: =R79 -> 0 | V100: =V79 -> //
B101: ◆工事コード/工事名 | R101: ◆藤田建装担当者
B102: =B81 -> 0 | G102: =G81 -> 0 | R102: =R81 -> 0 | V102: T№ | W102: =W81 -> 2602092
B105: ④ 管理伝票 | P105: ㈱藤田建装 事業部管理 | AA105: 備 考
E106: ◆ 内 容 | N106: ◆ 数 量 | R106: ◆ 単 価 | V106: ◆ 金 額
B107: =B86 -> 0 | N107: =N86 -> 0 | P107: =P86 -> 0 | R107: =R86 -> 0 | V107: =V86
AA108: 差替No.
AA109: 未請求No.
AA110: 経理責任者 | AE110: 経理担当 | AI110: 現場担当
B114: ◆取引先名/コード | G114: =請求データ入力!$K$2 -> 72130 | L114: 登録番号 | R114: ◆計（税抜）
L115: =請求データ入力!$K$6 -> 0 | V115: =V94
B116: =請求データ入力!$F$2 -> 〒110-0012 東京都台東区竜泉3-40-4 | R116: ◆消費税
R117: （切捨） | T117: =請求データ入力!$O$11 -> 0.1 | V117: =V96
B118: =請求データ入力!$F$6 -> 有限会社木村左官工業 | R118: ◆税込合計金額
V119: =V98 | AC119: 明細 （ 有 ・ 無 ）
R120: ◆取引先担当者 | V120: ◆完成納品年月日 | AC120: 検 算 | AI120: INPUT
B121: ="TEL："&請求データ入力!$K$4 -> TEL：090-4609-2757 | R121: =R100 -> 0 | V121: =V100 -> //
B122: ◆工事コード/工事名 | R122: ◆藤田建装担当者
B123: =B102 -> 0 | G123: =G102 -> 0 | R123: =R102 -> 0 | V123: T№ | W123: =W102 -> 2602092
B125: ② 納品書 （原価計算書） | P125: ㈱藤田建装 現場担当→課管理 | AA125: 備 考 | AM125: 393
...
